Workbook

Sheet FORMULARIO 1
A1: MINISTERIO DE ECONOMIA Y FINANZAS
A2: FORMULARIO 1: "FUENTES DE FINANCIAMIENTO DEL PROYECTO DE CONTRATO COLECTIVO"
A3: DETALLE DE INGRESOS
A5: GOBIERNO AUTÓNOMO DESCENTRALIZADO: Provincial de Loja
A6: Nº PROYECTO CONTRATO COLECTIVO: Décimo Noveno
A8: FUENTES DE FINANCIAMIENTO | C8: FINANCIAMIENTO CONTRATO COLECTIVO VIGENTE 2014 | D8: FINANCIAMIENTO CONTRATO COLECTIVO PROPUESTO 2015 | E8: FINANCIAMIENTO CONTRATO COLECTIVO PROPUESTO 2016 | F8: FINANCIAMIENTO CONTRATO COLECTIVO PROPUESTO 2017 | G8: FINANCIAMIENTO CONTRATO COLECTIVO PROPUESTO 2018 | H8: FINANCIAMIENTO CONTRATO COLECTIVO PROPUESTO 2019 | I8: OBSERVACIONES
A9: INGRESOS DE INVERSION Y CAPITAL
A10: 28 | B10: TRANSFERENCIAS Y DONACIONES INVERSION
A11: 2806 | B11: Aportes y Participaciones de Capital e Inversión del Régimen Seccional Autónomo | C11: =+'FORMULARIO 2'!C28 -> 2650827.1 | D11: =+'FORMULARIO 2'!D28 -> 2742689 | E11: =+'FORMULARIO 2'!E28 -> 2740745.7 | F11: =+'FORMULARIO 2'!F28 -> 2930353.4 | G11: =+'FORMULARIO 2'!G28 -> 2895724.2 | H11: =+'FORMULARIO 2'!H28 -> 3086266
A12: TOTAL | C12: =+C11 -> 2650827.1 | D12: =+D11 -> 2742689 | E12: =+E11 -> 2740745.7 | F12: =+F11 -> 2930353.4 | G12: =+G11 -> 2895724.2 | H12: =+H11 -> 3086266
A13: INCREMENTO PORCENTUAL | D13: 0.0347 | E13: 0.0339 | F13: 0.1054 | G13: 0.0924 | H13: 0.1643
A18: ____________________________________________________
A19: DIRECTOR FINANCIERO GAD PROVINCIAL LOJA
A20: Ing. Eduardo Aguirre Valdiviezo
A22: Loja, 24 de junio de 2019

Sheet FORMULARIO 2
A1: MINISTERIO DE ECONOMIA Y FINANZAS
A2: FORMULARIO 2: "COSTOS DEL PROYECTO DE CONTRATO COLECTIVO"
A4: GOBIERNO AUTÓNOMO DESCENTRALIZADO: Provincial de Loja
A5: Nº PROYECTO CONTRATO COLECTIVO: Proyecto décimo noveno
A7: CLASIFICADOR PRESUPUESTARIO | B7: GASTO DEL PERSONAL | C7: COSTO CONTRATO COLECTIVO VIGENTE 2014 | D7: COSTO CONTRATO COLECTIVO PROPUESTO 2015 | E7: COSTO CONTRATO COLECTIVO PROPUESTO 2016 | F7: COSTO CONTRATO COLECTIVO PROPUESTO 2017 | G7: COSTO CONTRATO COLECTIVO PROPUESTO 2018 | H7: COSTO CONTRATO COLECTIVO PROPUESTO 2019 | I7: OBSERVACIONES
A8: GASTO PERSONAL
A9: 7101 | B9: REMUNERACIONES BASICAS
A10: 710106 | B10: SALARIOS UNIFICADOS | C10: 1580916.1 | D10: 1567033.3 | E10: 1673589.2 | F10: 1766386.4 | G10: 1752619.8 | H10: 1718996.9
A11: 7102 | B11: REMUNERACIONES COMPLEMENTARIAS
A12: 710203 | B12: DECIMOTERCER SUELDO | C12: =+(C10/C31)*12 -> 87828.673 | D12: =+(D10/D31)*12 -> 88283.567 | E12: =+(E10/E31)*12 -> 88083.644 | F12: =+(F10/F31)*12 -> 88319.322 | G12: =+(G10/G31)*12 -> 88367.385 | H12: =+(H10/H31)*12 -> 87778.564
A13: 710204 | B13: DECIMOCUARTO SUELDO | C13: =340*C31 -> 73440 | D13: =354*D31 -> 75402 | E13: =366*E31 -> 83448 | F13: =375*F31 -> 90000 | G13: =386*G31 -> 91868 | H13: =394*H31 -> 92590
A14: 7103 | B14: REMUNERACIONES COMPENSATORIAS
A15: 710304 | B15: COMPENSACION POR TRANSPORTE | C15: 24792 | D15: 24665 | E15: 25362.5 | F15: 26445.5 | G15: 26470.5 | H15: 30855
A16: 710307 | B16: ALIMENTACION | C16: 198336 | D16: 197320 | E16: 202900 | F16: 211564 | G16: 213924 | H16: 246840
A17: 7104 | B17: SUBSIDIOS
A18: 710401 | B18: POR CARGAS FAMILIARES | C18: 9274.75 | D18: 9258.49 | E18: 10811.64 | F18: 11186.43 | G18: 11282.78 | H18: 11173.84
A19: 710401 | B19: POR ANTIGÜEDAD | C19: 14670.37 | D19: 18348.32 | E19: 22366.63 | F19: 27864.59 | G19: 31746.47 | H19: 38498.22
A20: 7106 | B20: APORTES A LA SEGURIDAD SOCIAL
A21: 710601 | B21: APORTE PATRONAL | C21: =ROUND(C10*12.15%,2) -> 192081.31 | D21: =ROUND(D10*12.15%,2) -> 190394.55 | E21: =ROUND(E10*12.15%,2) -> 203341.09 | F21: =ROUND(F10*12.15%,2) -> 214615.95 | G21: =ROUND(G10*12.15%,2) -> 212943.31 | H21: =ROUND(H10*12.15%,2) -> 208858.12
A22: 710602 | B22: FONDO DE RESERVA | C22: =ROUND(C10*8.33%,2) -> 131690.31 | D22: =ROUND(D10*8.33%,2) -> 130533.88 | E22: =ROUND(E10*8.33%,2) -> 139409.98 | F22: =ROUND(F10*8.33%,2) -> 147139.99 | G22: =ROUND(G10*8.33%,2) -> 145993.23 | H22: =ROUND(H10*8.33%,2) -> 143192.44
A23: 710603 | B23: FONDO DE JUBILACION PATRONAL | C23: 247746.67 | D23: 283639.82 | E23: 281538.82 | F23: 271965.82 | G23: 265160.17 | H23: 254961.71
A24: 7307 | B24: IDEMNIZACIONES
A25: 710706 | B25: BENEFICIOS POR JUBILACION | G25: 55348.56 | H25: 162521.24
A26: 7308 | B26: BIENES DE USO Y CONSUMO DE INVERSION
A27: 730802 | B27: VESTUARIO, LENCERIA Y PRENDAS DE PROTECCION | C27: 90050.91 | D27: 157810.02 | E27: 9894.19 | F27: 74865.34 | G27: 0 | H27: 90000
A28: TOTAL | C28: =SUM(C10:C27) -> 2650827.1 | D28: =SUM(D10:D27) -> 2742689 | E28: =SUM(E10:E27) -> 2740745.7 | F28: =SUM(F10:F27) -> 2930353.4 | G28: =SUM(G10:G27) -> 2895724.2 | H28: =SUM(H10:H27) -> 3086266
A29: INCREMENTO PORCENTUAL | D29: 0.0347 | E29: 0.0339 | F29: 0.1054 | G29: 0.0924 | H29: 0.1643
C31: =248-32 -> 216 | D31: =248-35 -> 213 | E31: =248-20 -> 228 | F31: =248-8 -> 240 | G31: =248-10 -> 238 | H31: =248-13 -> 235
A35: ______________________________________________________
A36: DIRECTOR FINANCIERO GAD PROVINCIAL LOJA
A37: Ing. Eduardo Aguirre Valdiviezo
A39: Loja, 24 de junio de 2019

Sheet FORMULARIO 3 
A1: MINISTERIO DE ECONOMIA Y FINANZAS
A2: FORMULARIO 3: "COMPARATIVO ENTRE REMUNERACIÓN UNIFICADA Y PROPUESTA"
A3: DISTRIBUTIVO DE SALARIO UNIFICADO DESAGREGADO POR TRABAJADOR
A5: GOBIERNO AUTÓNOMO DESCENTRALIZADO DE LA PROVINCIA DE LOJA
A6: Nº PROYECTO CONTRATO COLECTIVO DÉCIMO NOVENO
A8: CEDULA | B8: APELLIDOS Y NOMBRES | C8: No. TRABAJ | D8: GRADO DEL CARGO O PUESTO | E8: DENOMINACIÓN DEL PUESTO O CARGO DE OCUPACIÓN | F8: REMUNERACION UNIFICADA CONTRATO COLECTIVO VIGENTE 2014 | G8: REMUNERACION UNIFICADA CONTRATO COLECTIVO VIGENTE 2015 | H8: REMUNERACION UNIFICADA CONTRATO COLECTIVO VIGENTE 2016 | I8: REMUNERACION UNIFICADA CONTRATO COLECTIVO VIGENTE 2017 | J8: REMUNERACION UNIFICADA CONTRATO COLECTIVO VIGENTE 2018 | K8: REMUNERACION UNIFICADA CONTRATO COLECTIVO PROPUESTO 2019 | L8: FECHA DE INGRESO | M8: PROYECTO DE INVERSION
A9: 1712052750 | B9: ABAD RAMIREZ FABRICIO MARCELO | C9: 1 | D9: 1 | E9: AUXILIAR DE SERVICIOS | F9: 565.22 | G9: 565.22 | H9: 565.22 | I9: 565.22 | J9: 565.22 | K9: 565.22 | L9: 40709 | M9: Atención Social Matilde Hidalgo
A10: 1103496830 | B10: AGUILAR ORDOÑEZ DARWIN JAVIER | C10: =C9+1 -> 2 | D10: 6 | E10: SUPERVISOR DE VIVEROS Y ÁREAS REFORESTADAS | F10: 822.37 | G10: 822.37 | H10: 822.37 | I10: 822.37 | J10: 822.37 | K10: 822.37 | L10: 36601 | M10: Obras de Administración Directa
A11: 1102409560 | B11: AGUINSACA LOARTE MIGUEL NUMAN | C11: =C10+1 -> 3 | D11: 1 | E11: AUXILIAR DE SERVICIOS | F11: 565.22 | G11: 565.22 | H11: 565.22 | I11: 565.22 | J11: 565.22 | K11: 565.22 | L11: 40544 | M11: Obras de Administración Directa
A12: 1102809330 | B12: ALULIMA BUELE JOSE RODRIGO | C12: =C11+1 -> 4 | D12: 2 | E12: ALBAÑIL | F12: 581.22 | G12: 581.22 | H12: 581.22 | I12: 581.22 | J12: 581.22 | K12: 581.22 | L12: 40544 | M12: Vialidad y Obras Civiles
A13: 1100414141 | B13: ALVARADO MEDINA EULOGIO AMADO | C13: =C12+1 -> 5 | D13: 2 | E13: ALBAÑIL | F13: 581.22 | G13: 581.22 | H13: 581.22 | I13: 581.22 | J13: 581.22 | K13: 581.22 | L13: 40544 | M13: Vialidad y Obras Civiles
A14: 1104542905 | B14: ALVEAR CALDERON CARLOS VINICIO | C14: =C13+1 -> 6 | D14: 1 | E14: AUXILIAR DE SERVICIOS | F14: 565.22 | G14: 565.22 | H14: 565.22 | I14: 565.22 | J14: 565.22 | K14: 565.22 | L14: 40544 | M14: Obras de Administración Directa
A15: 1102900600 | B15: ALVEAR OCHOA ANGEL PATRICIO | C15: =C14+1 -> 7 | D15: 1 | E15: AYUDANTE DE ALBAÑIL | F15: 565.22 | G15: 565.22 | H15: 565.22 | I15: 565.22 | J15: 565.22 | K15: 565.22 | L15: 40544 | M15: Obras de Administración Directa
A16: 1900350123 | B16: ALVERCA ABAD FRANCLIN ERNAN | C16: =C15+1 -> 8 | D16: 2 | E16: ALBAÑIL | F16: 581.22 | G16: 581.22 | H16: 581.22 | I16: 581.22 | J16: 581.22 | K16: 581.22 | L16: 40544 | M16: Vialidad y Obras Civiles
A17: 1102749536 | B17: AMBULUDI CALERO ROOSEVELTH GEOVANNY | C17: =C16+1 -> 9 | D17: 3 | E17: CHOFER DE VEHÍCULOS LIVIANOS | F17: 876 | G17: 876 | H17: 876 | I17: 876 | J17: 876 | K17: 876 | L17: 32807 | M17: Obras de Administración Directa
A18: 1103297279 | B18: AMBULUDI PUGLLA CARLOS AURELIO | C18: =C17+1 -> 10 | D18: 4 | E18: CHOFER DE VEHÍCULOS PESADOS | F18: 620.87 | G18: 620.87 | H18: 620.87 | I18: 620.87 | J18: 620.87 | K18: 620.87 | L18: 37347 | M18: Obras de Administración Directa
A19: 1103949044 | B19: ANDRADE CHALAN YURI DANIEL | C19: =C18+1 -> 11 | D19: 1 | E19: AYUDANTE DE CULTIVOS | F19: 615.22 | G19: 615.22 | H19: 615.22 | I19: 615.22 | J19: 615.22 | K19: 615.22 | L19: 40544 | M19: Riego y Gestión Ambiental
A20: 1103530927 | B20: AREVALO CARRILLO MANUEL DE JESUS | C20: =C19+1 -> 12 | D20: 1 | E20: AYUDANTE DE CARPINTERÍA | F20: 565.22 | G20: 565.22 | H20: 565.22 | I20: 565.22 | J20: 565.22 | K20: 565.22 | L20: 40544 | M20: Obras de Administración Directa
A21: 1102091509 | B21: AREVALO FRANCO CARLOS ANTONIO | C21: =C20+1 -> 13 | D21: 3 | E21: CONSERJE CON RESIDENCIA | H21: 612 | I21: 612 | J21: 612 | K21: 612 | L21: 36923 | M21: Obras de Administración Directa (CAMBIO DE REGIMEN LABORAL - RESOLUCION N° RP-RDE-22-2016)
A22: 1104148026 | B22: ARMIJOS AMBULUDI JOSE ANTONIO | C22: =C21+1 -> 14 | D22: 1 | E22: AUXILIAR DE SERVICIOS | F22: 565.22 | G22: 565.22 | H22: 565.22 | I22: 565.22 | J22: 565.22 | K22: 565.22 | L22: 40787 | M22: Obras de Administración Directa
A23: 0703002816 | B23: ARMIJOS CHAMORRO CECILIA ANGELICA | C23: =C22+1 -> 15 | D23: 1 | E23: CONSERJE | H23: 582 | I23: 582 | J23: 582 | K23: 582 | L23: 39814 | M23: Obras de Administración Directa (CAMBIO DE REGIMEN LABORAL - RESOLUCION N° RP-RDE-22-2016)
A24: 1102374806 | B24: ARMIJOS CORDOVA FRANCO VINICIO | C24: =C23+1 -> 16 | D24: 4 | E24: CHOFER DE VEHÍCULOS PESADOS | F24: 615.22 | G24: 615.22 | H24: 615.22 | I24: 615.22 | J24: 615.22 | K24: 615.22 | L24: 40544 | M24: Obras de Administración Directa
A25: 1103166524 | B25: ASTUDILLO ESPARZA LUISA ENRIQUETA | C25: =C24+1 -> 17 | D25: 1 | E25: CONSERJE EXTERNO | F25: 565.22 | G25: 565.22 | H25: 565.22 | I25: 565.22 | J25: 565.22 | K25: 565.22 | L25: 40544 | M25: Obras de Administración Directa
A26: 1102854229 | B26: ATARIHUANA NOLIVOS INRY HECTOR | C26: =C25+1 -> 18 | D26: 1 | E26: GUARDIÁN | F26: 565.22 | G26: 565.22 | H26: 565.22 | I26: 565.22 | J26: 565.22 | K26: 565.22 | L26: 40544 | M26: Vialidad y Obras Civiles
A27: 1103021562 | B27: AUQUILLA GALAN JUAN BOLIVAR | C27: =C26+1 -> 19 | D27: 3 | E27: CONSERJE CON RESIDENCIA | F27: 598.22 | G27: 598.22 | H27: 598.22 | I27: 598.22 | J27: 598.22 | K27: 598.22 | L27: 36342 | M27: Atención Social Matilde Hidalgo
A28: 1103386668 | B28: BANEGAS BANEGAS BRAULIO BENJAMIN | C28: =C27+1 -> 20 | D28: 3 | E28: CHOFER DE VEHÍCULOS LIVIANOS | I28: 598.22 | J28: 598.22 | K28: 598.22 | L28: 40544 | M28: Desarrollo Productivo (TRASPASO DESDE DEPROSUR EP EL 01 DE ENERO DE 2017)
A29: 1104670664 | B29: BARRIGAS JARAMILLO MARCO ANTONIO | C29: =C28+1 -> 21 | D29: 1 | E29: AYUDANTE DE CULTIVOS | F29: 615.22 | G29: 615.22 | H29: 615.22 | I29: 615.22 | J29: 615.22 | K29: 615.22 | L29: 40544 | M29: Riego y Gestión Ambiental
A30: 1303281222 | B30: BAZURTO CHAVEZ NARSISO RUBEN | C30: =C29+1 -> 22 | D30: 2 | E30: ALBAÑIL | F30: 581.22 | G30: 581.22 | H30: 581.22 | I30: 581.22 | J30: 581.22 | K30: 581.22 | L30: 40544 | M30: Vialidad y Obras Civiles
A31: 0703689463 | B31: BENAVIDES ROJAS LUCIO ARTEMIO | C31: =C30+1 -> 23 | D31: 2 | E31: ALBAÑIL | F31: 581.22 | G31: 581.22 | H31: 581.22 | I31: 581.22 | J31: 581.22 | K31: 581.22 | L31: 40544 | M31: Obras de Administración Directa
A32: 1101353900 | B32: BURI LOARTE VICTOR EMILIO | C32: =C31+1 -> 24 | D32: 2 | E32: ALBAÑIL | F32: 581.22 | G32: 581.22 | H32: 581.22 | I32: 581.22 | J32: 581.22 | K32: 581.22 | L32: 40544 | M32: Obras de Administración Directa
A33: 1103559520 | B33: BUSTOS SAMANIEGO ALEX ENRIQUE | C33: =C32+1 -> 25 | D33: 1 | E33: CONSERJE EXTERNO | F33: 565.22 | G33: 565.22 | H33: 565.22 | I33: 565.22 | J33: 565.22 | K33: 565.22 | L33: 40544 | M33: Obras de Administración Directa
A34: 1103702971 | B34: CABRERA CABRERA SANTOS BENJAMIN | C34: =C33+1 -> 26 | D34: 2 | E34: ALBAÑIL | F34: 581.22 | G34: 581.22 | H34: 581.22 | I34: 581.22 | J34: 581.22 | K34: 581.22 | L34: 40544 | M34: Vialidad y Obras Civiles
A35: 1103034201 | B35: CABRERA GRANDA CESAR HUMBERTO | C35: =C34+1 -> 27 | D35: 2 | E35: ALBAÑIL | I35: 581 | J35: 581 | K35: 581 | L35: 40909 | M35: Riego y Gestión Ambiental (TRASPASO DESDE RIDRENSUR EP EL 01 DE ENERO DE 2017)
A36: 1100646353 | B36: CABRERA PARDO ROBERT FRANCISCO | C36: =C35+1 -> 28 | D36: 1 | E36: AYUDANTE DE MECÁNICA DE EQUIPO Y/O MAQUINARIA | F36: 596.82 | G36: 596.82 | H36: 596.82 | I36: 596.82 | J36: 596.82 | K36: 596.82 | L36: 40909 | M36: Obras de Administración Directa
A37: 1104389372 | B37: CAJAMARCA AMBULUDI JAIME ANTONIO | C37: =C36+1 -> 29 | D37: 1 | E37: AYUDANTE DE CULTIVOS | F37: 565.22 | G37: 565.22 | H37: 565.22 | I37: 565.22 | J37: 565.22 | K37: 565.22 | L37: 40709 | M37: Riego y Gestión Ambiental
A38: 1103934640 | B38: CALLE CARRION RONNAL FRANCISCO | C38: =C37+1 -> 30 | D38: 1 | E38: GUARDIÁN | F38: 565.22 | G38: 565.22 | H38: 565.22 | I38: 565.22 | J38: 565.22 | K38: 565.22 | L38: 40544 | M38: Vialidad y Obras Civiles
A39: 1101408217 | B39: CALVAS JORGE ENRIQUE | C39: =C38+1 -> 31 | D39: 2 | E39: PINTOR | F39: 581.22 | G39: 581.22 | H39: 581.22 | I39: 581.22 | J39: 581.22 | K39: 581.22 | L39: 38322 | M39: Vialidad y Obras Civiles
A40: 1102772413 | B40: CAMACHO CASTILLO LILIANA ELIZABETH | C40: =C39+1 -> 32 | D40: 1 | E40: CONSERJE EXTERNO | F40: 565.22 | G40: 565.22 | H40: 565.22 | I40: 565.22 | J40: 565.22 | K40: 565.22 | L40: 40909 | M40: Obras de Administración Directa
A41: 1100794245 | B41: CAMBISACA BAILON LUIS AFRANIO | C41: =C40+1 -> 33 | D41: 1 | E41: GUARDIÁN | F41: 681.97 | G41: 681.97 | H41: 681.97 | I41: 681.97 | J41: 681.97 | L41: 37469 | M41: Vialidad y Obras Civiles - SE DESVINCULO EL 31 DE JULIO DE 2018
A42: 1104195811 | B42: CAMPOVERDE ANDRADE LEONCIO DAVID | C42: =C41+1 -> 34 | D42: 1 | E42: CONSERJE EXTERNO | F42: 565.22 | G42: 565.22 | H42: 565.22 | I42: 565.22 | J42: 565.22 | K42: 565.22 | L42: 40544 | M42: Obras de Administración Directa
A43: 1100867181 | B43: CANO ABAD MANUEL AGUSTIN | C43: =C42+1 -> 35 | D43: 1 | E43: GUARDIÁN | H43: 565.22 | I43: 565.22 | J43: 565.22 | K43: 565.22 | L43: 40544 | M43: Obras de Administración Directa (TRASPASO DESDE VIALSUR EP EL 01 DE ENERO DE 2016)
A44: 01101838561 | B44: CARCHI BERMEO CARMITA DE JESUS | C44: =C43+1 -> 36 | D44: 2 | E44: COSTURERA | K44: 531 | L44: 43626 | M44: Atención Social Matilde Hidalgo - (TRASPASO DESDE CASMH EL 10 DE JUNIO DE 2019)
A45: 1104544778 | B45: CARPIO JARAMILLO MANUEL ALEJANDRO | C45: =C44+1 -> 37 | D45: 1 | E45: CONSERJE EXTERNO | F45: 565.22 | G45: 565.22 | H45: 565.22 | I45: 565.22 | J45: 565.22 | K45: 565.22 | L45: 40909 | M45: Obras de Administración Directa
A46: 1101708376 | B46: CARRION VALLEJO MAXIMILIANO | C46: =C45+1 -> 38 | D46: 9 | E46: SUPERVISOR DE OBRAS PÚBLICAS | F46: 1332.19 | G46: 1332.19 | H46: 1332.19 | I46: 1332.19 | J46: 1332.19 | K46: 1332.19 | L46: 27956 | M46: Obras de Administración Directa
A47: 1100866944 | B47: CARTUCHE ORTEGA GONZALO ENRIQUE | C47: =C46+1 -> 39 | D47: 1 | E47: CONSERJE EXTERNO | F47: 565.22 | G47: 565.22 | H47: 565.22 | I47: 565.22 | J47: 565.22 | K47: 565.22 | L47: 40909 | M47: Obras de Administración Directa
A48: 1103303275 | B48: CARTUCHE PASACA LUIS ALBERTO | C48: =C47+1 -> 40 | D48: 2 | E48: SOLDADOR | F48: 581.22 | G48: 581.22 | H48: 581.22 | I48: 581.22 | J48: 581.22 | K48: 581.22 | L48: 40544 | M48: Obras de Administración Directa
A49: 1103677124 | B49: CASTILLO AREVALO BOLIVAR ENRIQUE | C49: =C48+1 -> 41 | D49: 4 | E49: CHOFER DE VEHÍCULOS PESADOS | F49: 615.22 | G49: 615.22 | H49: 615.22 | I49: 615.22 | J49: 615.22 | K49: 615.22 | L49: 40544 | M49: Atención Social Matilde Hidalgo
A50: 1104370737 | B50: CASTILLO CORDOVA ARIOSTO JAVIER | C50: =C49+1 -> 42 | D50: 2 | E50: SOLDADOR | F50: 581.22 | G50: 581.22 | H50: 581.22 | I50: 581.22 | J50: 581.22 | K50: 581.22 | L50: 40544 | M50: Obras de Administración Directa
A51: 1100233798 | B51: CASTILLO FRANCISCO NICANOR | C51: =C50+1 -> 43 | D51: 1 | E51: AUXILIAR DE SERVICIOS | F51: 565.22 | G51: 565.22 | H51: 565.22 | I51: 565.22 | J51: 565.22 | K51: 565.22 | L51: 40544 | M51: Vialidad y Obras Civiles
A52: 1100309333 | B52: CASTILLO GONZALO MARINO | C52: =C51+1 -> 44 | D52: 4 | E52: CHOFER DE VEHÍCULOS PESADOS | F52: 864.31 | G52: 864.31 | H52: 864.31 | I52: 864.31 | J52: 864.31 | K52: 864.31 | L52: 28850 | M52: Obras de Administración Directa
A53: 1102124052 | B53: CASTILLO HERRERA FELICITO GUZMAN | C53: =C52+1 -> 45 | D53: 4 | E53: CHOFER DE VEHÍCULOS PESADOS | F53: 615.22 | G53: 615.22 | H53: 615.22 | I53: 615.22 | J53: 615.22 | K53: 615.22 | L53: 40909 | M53: Obras de Administración Directa
A54: 1103479836 | B54: CASTRO GUTIERREZ LEONARDO ARTURO | C54: =C53+1 -> 46 | D54: 3 | E54: OPERADOR DE DISTRIBUCIÓN DE AGUA | F54: 598.22 | G54: 598.22 | H54: 598.22 | I54: 598.22 | J54: 598.22 | K54: 598.22 | L54: 40544 | M54: Vialidad y Obras Civiles
A55: 0701952103 | B55: CASTRO NEIRA HERNAN BOLIVAR | C55: =C54+1 -> 47 | D55: 4 | E55: CHOFER DE VEHÍCULOS PESADOS | F55: 615.22 | G55: 615.22 | H55: 615.22 | I55: 615.22 | J55: 615.22 | K55: 615.22 | L55: 40544 | M55: Obras de Administración Directa
A56: 1103338768 | B56: CASTRO QUIZHPE BYRON FIDEL | C56: =C55+1 -> 48 | D56: 9 | E56: SUPERVISOR PROCESOS PRODUCTIVOS, OPERATIVOS Y/O ESPECIALIZACIÓN INDUSTRIAL | I56: 876 | J56: 876 | K56: 876 | L56: 38322 | M56: Desarrollo Productivo (TRASPASO DESDE DEPROSUR EP EL 01 DE ENERO DE 2017)
A57: 1702927417 | B57: CASTRO RIVERA JULIO MARCELO | C57: =C56+1 -> 49 | D57: 1 | E57: CONSERJE EXTERNO | I57: 565.22 | J57: 565.22 | K57: 565.22 | L57: 37151 | M57: Desarrollo Productivo (TRASPASO DESDE DEPROSUR EP EL 01 DE ENERO DE 2017)
A58: 1105032864 | B58: CELI BELTRAN MARCO JAVIER | C58: =C57+1 -> 50 | D58: 1 | E58: CONSERJE EXTERNO | F58: 565.22 | G58: 565.22 | H58: 565.22 | I58: 565.22 | J58: 565.22 | K58: 565.22 | L58: 40544 | M58: Obras de Administración Directa
A59: 1102601992 | B59: CEVALLOS LUNA MARIA ALEXANDRA | C59: =C58+1 -> 51 | D59: 1 | E59: CONSERJE EXTERNO | F59: 565.22 | G59: 565.22 | H59: 565.22 | I59: 565.22 | J59: 565.22 | K59: 565.22 | L59: 39301 | M59: Obras de Administración Directa
A60: 1103143549 | B60: CHALAN LOZANO JOSE FRANCISCO | C60: =C59+1 -> 52 | D60: 4 | E60: CHOFER DE VEHÍCULOS PESADOS | F60: 615.22 | G60: 615.22 | H60: 615.22 | I60: 615.22 | J60: 615.22 | K60: 615.22 | L60: 39084 | M60: Obras de Administración Directa
A61: 1101430476 | B61: CHAMBA BENITEZ GILBERTO | C61: =C60+1 -> 53 | D61: 6 | E61: SUPERVISOR DE AUXILIARES DE SERVICIOS | F61: 1002.43 | G61: 1002.43 | H61: 1002.43 | I61: 1002.43 | J61: 1002.43 | K61: 1002.43 | L61: 30909 | M61: Obras de Administración Directa
A62: 1101805826 | B62: CHAMBA BENITEZ TEODORO | C62: =C61+1 -> 54 | D62: 2 | E62: ALBAÑIL | F62: 581.22 | G62: 581.22 | H62: 581.22 | I62: 581.22 | J62: 581.22 | K62: 581.22 | L62: 40544 | M62: Vialidad y Obras Civiles
A63: 1100754934 | B63: CHAMBA RODRIGUEZ ANGEL DELFIN | C63: =C62+1 -> 55 | D63: 2 | E63: HERRERO | F63: 565.22 | G63: 565.22 | H63: 565.22 | I63: 565.22 | J63: 565.22 | K63: 565.22 | L63: 40544 | M63: Atención Social Matilde Hidalgo
A64: 1102814405 | B64: CHICAIZA GUAMO EDGAR AUGUSTO | C64: =C63+1 -> 56 | D64: 1 | E64: AYUDANTE DE EQUIPO Y/O MAQUINARIA PESADA | F64: 565.22 | G64: 565.22 | H64: 565.22 | I64: 565.22 | L64: 40544 | M64: Obras de Administración Directa - SE DESVINCULO EL 03 DE OCTUBRE DE 2017
A65: 1103138556 | B65: CHIMBO ALULIMA JAIME RODRIGO | C65: =C64+1 -> 57 | D65: 1 | E65: AYUDANTE DE CULTIVOS | F65: 615.22 | G65: 615.22 | H65: 615.22 | I65: 615.22 | J65: 615.22 | K65: 615.22 | L65: 39995 | M65: Riego y Gestión Ambiental
A66: 1709217218 | B66: CHOEZ BELTRAN MANUEL ENRIQUE | C66: =C65+1 -> 58 | D66: 2 | E66: ELECTRICISTA | F66: 581.22 | G66: 581.22 | H66: 581.22 | I66: 581.22 | J66: 581.22 | K66: 581.22 | L66: 40544 | M66: Obras de Administración Directa
A67: 1103844682 | B67: CISNEROS PAREDES JUAN PABLO | C67: =C66+1 -> 59 | D67: 1 | E67: AUXILIAR DE SERVICIOS | F67: 565.22 | G67: 565.22 | H67: 565.22 | I67: 565.22 | J67: 565.22 | K67: 565.22 | L67: 40544 | M67: Atención Social Matilde Hidalgo
A68: 1101340253 | B68: COLLAGUAZO SARANGO CESAR AUGUSTO | C68: =C67+1 -> 60 | D68: 4 | E68: CHOFER DE VEHÍCULOS PESADOS | F68: 876 | G68: 876 | H68: 876 | I68: 876 | J68: 876 | L68: 29768 | M68: Obras de Administración Directa - SE DESVINCULO EL 20 DE JULIO DE 2018
A69: 1102471867 | B69: CORDOVA MALDONADO FRANGEL ALMILCAR | C69: =C68+1 -> 61 | D69: 1 | E69: AYUDANTE DE ALBAÑIL | F69: 565.22 | G69: 565.22 | H69: 565.22 | I69: 565.22 | J69: 565.22 | K69: 565.22 | L69: 40725 | M69: Vialidad y Obras Civiles
A70: 1103633390 | B70: CORDOVA TORRES MIRIAN ELIZABETH | C70: =C69+1 -> 62 | D70: 1 | E70: GUARDIÁN | F70: 565.22 | G70: 565.22 | H70: 565.22 | I70: 565.22 | J70: 565.22 | K70: 565.22 | L70: 41640 | M70: Desarrollo Productivo
A71: 1102911268 | B71: CORNEJO OCHOA SEGUNDO JOSE | C71: =C70+1 -> 63 | D71: 2 | E71: ALBAÑIL | F71: 581.22 | G71: 581.22 | H71: 581.22 | I71: 581.22 | J71: 581.22 | K71: 581.22 | L71: 40544 | M71: Vialidad y Obras Civiles
A72: 1102699541 | B72: CORONEL CARDENAS LUIS BERNARDO | C72: =C71+1 -> 64 | D72: 1 | E72: AYUDANTE DE CULTIVOS | F72: 821.72 | G72: 821.72 | H72: 821.72 | I72: 821.72 | J72: 821.72 | K72: 821.72 | L72: 36787 | M72: Riego y Gestión Ambiental
A73: 1101299228 | B73: CORONEL ZARUMA EDMUNDO | C73: =C72+1 -> 65 | D73: 1 | E73: AYUDANTE DE CUADRILLA | F73: 565.22 | G73: 565.22 | H73: 565.22 | I73: 565.22 | J73: 565.22 | L73: 40544 | M73: Obras de Administración Directa - SE DESVINCULO EL 31 DE JULIO DE 2018
A74: 1103299457 | B74: CORREA GUAMAN MARIA DEL CISNE | C74: =C73+1 -> 66 | D74: 1 | E74: CONSERJE EXTERNO | F74: 565.22 | G74: 565.22 | H74: 565.22 | I74: 565.22 | J74: 565.22 | K74: 565.22 | L74: 38322 | M74: Obras de Administración Directa
A75: 1102765862 | B75: CUENCA NALVAY YOLANDA | C75: =C74+1 -> 67 | D75: 1 | E75: CONSERJE EXTERNO | F75: 565.22 | G75: 565.22 | H75: 565.22 | I75: 565.22 | J75: 565.22 | K75: 565.22 | L75: 40544 | M75: Obras de Administración Directa
A76: 1101378675 | B76: CUENCA PUCHA ENRIQUE | C76: =C75+1 -> 68 | D76: 2 | E76: GASFITERO O PLOMERO | F76: 581.22 | G76: 581.22 | H76: 581.22 | I76: 581.22 | J76: 581.22 | K76: 581.22 | L76: 40544 | M76: Obras de Administración Directa
A77: 1103637862 | B77: CUEVA ELIZALDE OSWALDO MERINO | C77: =C76+1 -> 69 | D77: 1 | E77: AYUDANTE DE CULTIVOS | F77: 615.22 | G77: 615.22 | H77: 615.22 | I77: 615.22 | J77: 615.22 | K77: 615.22 | L77: 40544 | M77: Riego y Gestión Ambiental
A78: 1103072201 | B78: CUEVA JARAMILLO WILLAN RICARDO | C78: =C77+1 -> 70 | D78: 4 | E78: CHOFER DE VEHÍCULOS PESADOS | F78: 653.64 | G78: 653.64 | H78: 653.64 | I78: 653.64 | J78: 653.64 | K78: 653.64 | L78: 38322 | M78: Obras de Administración Directa
A79: 1103424899 | B79: CUMBICUS ROJAS ROSA NOEMI | C79: =C78+1 -> 71 | D79: 1 | E79: CONSERJE EXTERNO | F79: 565.22 | G79: 565.22 | H79: 565.22 | I79: 565.22 | J79: 565.22 | K79: 565.22 | L79: 40544 | M79: Atención Social Matilde Hidalgo
A80: 1711216083 | B80: CURIPOMA RUILOVA MIGUEL ANTONIO | C80: =C79+1 -> 72 | D80: 2 | E80: ALBAÑIL | F80: 581.22 | G80: 581.22 | H80: 581.22 | I80: 581.22 | J80: 581.22 | K80: 581.22 | L80: 40544 | M80: Vialidad y Obras Civiles
A81: 1309027827 | B81: DELGADO VERA JORGE IVAN | C81: =C80+1 -> 73 | D81: 2 | E81: ALBAÑIL | F81: 581.22 | G81: 581.22 | H81: 581.22 | I81: 581.22 | J81: 581.22 | K81: 581.22 | L81: 40544 | M81: Vialidad y Obras Civiles
A82: 1900135649 | B82: ENRIQUEZ MANUEL JUVENTINO | C82: =C81+1 -> 74 | D82: 4 | E82: CHOFER DE VEHÍCULOS PESADOS | F82: 694.1 | G82: 694.1 | H82: 694.1 | I82: 694.1 | J82: 694.1 | K82: 694.1 | L82: 36388 | M82: Obras de Administración Directa
A83: 1103970909 | B83: ERAS DIAZ ALVARO HERNAN | C83: =C82+1 -> 75 | D83: 3 | E83: CHOFER DE VEHÍCULOS LIVIANOS | I83: 598.22 | J83: 598.22 | K83: 598.22 | L83: 39934 | M83: Desarrollo Productivo (TRASPASO DESDE DEPROSUR EP EL 01 DE ENERO DE 2017)
A84: 1103544423 | B84: ERAS DIAZ BYRON AMANDO | C84: =C83+1 -> 76 | D84: 3 | E84: CHOFER DE VEHÍCULOS LIVIANOS | I84: 598.22 | J84: 598.22 | K84: 598.22 | L84: 39539 | M84: Desarrollo Productivo (TRASPASO DESDE DEPROSUR EP EL 01 DE ENERO DE 2017)
A85: 1103641385 | B85: ERAS SANTIN RUTH DEL CISNE | C85: =C84+1 -> 77 | D85: 8 | E85: TÉCNICO SERVICIOS CORPORATIVOS | I85: 901 | J85: 901 | K85: 901 | L85: 41641 | M85: Desarrollo Productivo (TRASPASO DESDE DEPROSUR EP EL 01 DE ENERO DE 2017)
A86: 1103647184 | B86: ERREYES SARMIENTO JOSE PATRICIO | C86: =C85+1 -> 78 | D86: 4 | E86: CHOFER DE VEHÍCULOS PESADOS | F86: 615.22 | G86: 615.22 | H86: 615.22 | I86: 615.22 | J86: 615.22 | K86: 615.22 | L86: 40544 | M86: Atención Social Matilde Hidalgo
A87: 1101090494 | B87: ESPINOZA FLORES LUZ AMERICA | C87: =C86+1 -> 79 | D87: 1 | E87: AUXILIAR DE SERVICIOS | H87: 582 | I87: 582 | J87: 582 | K87: 582 | L87: 39879 | M87: Atención Social Matilde Hidalgo (CAMBIO DE REGIMEN LABORAL - RESOLUCION N° RP-RDE-22-2016)
A88: 1103381669 | B88: ESPINOZA LANCHI HENRY ALCIVAR | C88: =C87+1 -> 80 | D88: 3 | E88: CHOFER | I88: 598 | J88: 598 | K88: 598 | L88: 41640 | M88: Riego y Gestión Ambiental (TRASPASO DESDE RIDRENSUR EP EL 01 DE ENERO DE 2017)
A89: 1102589072 | B89: ESTRELLA CAMPOVERDE MANUEL AUGUSTO | C89: =C88+1 -> 81 | D89: 3 | E89: CHOFER | I89: 598 | J89: 598 | K89: 598 | L89: 41640 | M89: Riego y Gestión Ambiental (TRASPASO DESDE RIDRENSUR EP EL 01 DE ENERO DE 2017)
A90: 1103300024 | B90: ESTRELLA SILVA GERMANIA JANNETH | C90: =C89+1 -> 82 | D90: 2 | E90: COCINERO | I90: 581.22 | J90: 581.22 | K90: 581.22 | L90: 38322 | M90: Atención Social Matilde Hidalgo (TRASPASO DESDE VIALSUR EP EL 01 DE SEPTIEMBRE DE 2017)
A91: 1103229082 | B91: FERNANDEZ ESPINOZA EDINSON JAVIER | C91: =C90+1 -> 83 | D91: 3 | E91: CHOFER DE VEHÍCULOS LIVIANOS | F91: 598.22 | G91: 598.22 | H91: 598.22 | I91: 598.22 | J91: 598.22 | K91: 598.22 | L91: 40544 | M91: Obras de Administración Directa
A92: 1102782990 | B92: FIERRO JARAMILLO JOFFRE ULISES | C92: =C91+1 -> 84 | D92: 4 | E92: CHOFER DE VEHÍCULOS PESADOS | F92: 615.22 | G92: 615.22 | H92: 615.22 | I92: 615.22 | J92: 615.22 | K92: 615.22 | L92: 38322 | M92: Obras de Administración Directa
A93: 1104490592 | B93: FLORES ORELLANA FRANCISCO JAVIER | C93: =C92+1 -> 85 | D93: 1 | E93: AUXILIAR DE SERVICIOS | F93: 565.22 | G93: 565.22 | H93: 565.22 | I93: 565.22 | J93: 565.22 | K93: 565.22 | L93: 40544 | M93: Obras de Administración Directa
A94: 1101511796 | B94: GALAN SOTO ZOILA LUZ | C94: =C93+1 -> 86 | D94: 1 | E94: AUXILIAR DE SERVICIOS | H94: 582 | I94: 582 | J94: 582 | K94: 582 | L94: 39904 | M94: Atención Social Matilde Hidalgo (CAMBIO DE REGIMEN LABORAL - RESOLUCION N° RP-RDE-22-2016)
A95: 1103998934 | B95: GAONA ROA KATTY LAURA | C95: =C94+1 -> 87 | D95: 1 | E95: CONSERJE EXTERNO | F95: 565.22 | G95: 565.22 | H95: 565.22 | I95: 565.22 | J95: 565.22 | K95: 565.22 | L95: 40544 | M95: Obras de Administración Directa
A96: 1104876238 | B96: GARRIDO SOTO NELLY ELIZABETH | C96: =C95+1 -> 88 | D96: 1 | E96: CONSERJE EXTERNO | F96: 565.22 | G96: 565.22 | H96: 565.22 | I96: 565.22 | J96: 565.22 | K96: 565.22 | L96: 40544 | M96: Obras de Administración Directa
A97: 1101861993 | B97: GARROCHAMBA SINCHIRE SALOMON | C97: =C96+1 -> 89 | D97: 1 | E97: AYUDANTE DE CUADRILLA | F97: 565.22 | G97: 565.22 | H97: 565.22 | I97: 565.22 | J97: 565.22 | K97: 565.22 | L97: 40544 | M97: Vialidad y Obras Civiles
A98: 1101394045 | B98: GOMEZ GUAMAN LIZARDO | C98: =C97+1 -> 90 | D98: 1 | E98: AUXILIAR DE SERVICIOS | F98: 631.16 | G98: 631.16 | H98: 631.16 | I98: 631.16 | J98: 631.16 | K98: 631.16 | L98: 38322 | M98: Obras de Administración Directa
A99: 1102620976 | B99: GONZAGA CORREA BENITO RAMIRO | C99: =C98+1 -> 91 | D99: 4 | E99: CHOFER DE VEHÍCULOS PESADOS | I99: 598 | J99: 598 | K99: 598 | L99: 41640 | M99: Riego y Gestión Ambiental (TRASPASO DESDE RIDRENSUR EP EL 01 DE ENERO DE 2017)
A100: 1104419385 | B100: GONZALEZ JARAMILLO EDGAR ROLANDO | C100: =C99+1 -> 92 | D100: 1 | E100: AUXILIAR DE SERVICIOS | F100: 565.22 | G100: 565.22 | H100: 565.22 | I100: 565.22 | J100: 565.22 | K100: 565.22 | L100: 40544 | M100: Obras de Administración Directa
A101: 1103032601 | B101: GONZALEZ PINEDA MARIA ESPERANZA | C101: =C100+1 -> 93 | D101: 1 | E101: AUXILIAR DE SERVICIOS | H101: 582 | I101: 582 | J101: 582 | K101: 582 | L101: 39879 | M101: Atención Social Matilde Hidalgo (CAMBIO DE REGIMEN LABORAL - RESOLUCION N° RP-RDE-22-2016)
A102: 1900447911 | B102: GONZALEZ SANCHEZ ROY WILFRIDO | C102: =C101+1 -> 94 | D102: 2 | E102: ALBAÑIL | F102: 581.22 | G102: 581.22 | H102: 581.22 | I102: 581.22 | J102: 581.22 | K102: 581.22 | L102: 40544 | M102: Obras de Administración Directa
...

Sheet FORMULARIO 4
A1: MINISTERIO DE ECONOMIA Y FINANZAS
A2: FORMULARIO 4
A3: FLUJO PRESUPUESTARIO DE INGRESOS Y GASTOS
A5: GOBIERNO AUTÓNOMO DESCENTRALIZADO: Provincial de Loja
A7: DETALLE DE GRUPOS Y SUBGRUPOS | C7: FLUJO HISTÓRICO | H7: FLUJO PROYECTADO | J7: OBSERVACIONES
A8: Grupo y Subgrupo | B8: Descripción | C8: 2014 | D8: 2015 | E8: 2016 | F8: 2017 | G8: 2018 | H8: 2019 | I8: 2020
A9: TOTAL INGRESOS CORRIENTES (1) | C9: =+C10+C15+C20+C23+C27+C30 -> 10536290 | D9: =+D10+D15+D20+D23+D27+D30 -> 8827658.7 | E9: =+E10+E15+E20+E23+E27+E30 -> 10185824 | F9: =+F10+F15+F20+F23+F27+F30 -> 8802351.1 | G9: =+G10+G15+G20+G23+G27+G30 -> 10057107 | H9: =+H10+H15+H20+H23+H27+H30 -> 11298696 | I9: =+I10+I15+I20+I23+I27+I30 -> 11298696
A10: 11 | B10: Impuestos | C10: =SUM(C11:C14) -> 15743.09 | D10: =SUM(D11:D14) -> 19479.48 | E10: =SUM(E11:E14) -> 17063.76 | F10: =SUM(F11:F14) -> 21342.2 | G10: =SUM(G11:G14) -> 27624.72 | H10: =SUM(H11:H14) -> 20865.41 | I10: =SUM(I11:I14) -> 20865.41
A11: 1101 | B11: Sobre la Renta, Utilidades y Ganancias de Capital | C11: 0 | D11: 0 | E11: 0 | F11: 0 | G11: 0 | H11: 0 | I11: 0
A12: 1102 | B12: Sobre la propiedad | C12: 15743.09 | D12: 19479.48 | E12: 17063.76 | F12: 21342.2 | G12: 27624.72 | H12: 20865.41 | I12: 20865.41
A13: 1103 | B13: Al consumo de Bienes y Servicios | C13: 0 | D13: 0 | E13: 0 | F13: 0 | G13: 0 | H13: 0 | I13: 0
A14: 1107 | B14: Impuestos Diversos | C14: 0 | D14: 0 | E14: 0 | F14: 0 | G14: 0 | H14: 0 | I14: 0
A15: 13 | B15: Tasas y contribuciones | C15: =SUM(C16:C19) -> 21915.88 | D15: =SUM(D16:D19) -> 34937.9 | E15: =SUM(E16:E19) -> 84158.7 | F15: =SUM(F16:F19) -> 56468 | G15: =SUM(G16:G19) -> 73442.99 | H15: =SUM(H16:H19) -> 40255.3 | I15: =SUM(I16:I19) -> 40255.3
A16: 1301 | B16: Tasas generales | C16: 21915.88 | D16: 34937.9 | E16: 84158.7 | F16: 56468 | G16: 73442.99 | H16: 40255.3 | I16: 40255.3
A17: 1302 | B17: Tasas portuarias y aeroportuarias | C17: 0 | D17: 0 | E17: 0 | F17: 0 | G17: 0 | H17: 0 | I17: 0
A18: 1303 | B18: Tasas diversas | C18: 0 | D18: 0 | E18: 0 | F18: 0 | G18: 0 | H18: 0 | I18: 0
A19: 1304 | B19: Contribuciones | C19: 0 | D19: 0 | E19: 0 | F19: 0 | G19: 0 | H19: 0 | I19: 0
A20: 14 | B20: Venta de Bienes y Servicios | C20: =SUM(C21:C22) -> 2352.82 | D20: =SUM(D21:D22) -> 0 | E20: =SUM(E21:E22) -> 166.21 | F20: =SUM(F21:F22) -> 58567.58 | G20: =SUM(G21:G22) -> 245707.01 | H20: =SUM(H21:H22) -> 82999.31 | I20: =SUM(I21:I22) -> 82999.31
A21: 1402 | B21: Venta de Productos y Materiales | C21: 2105.07 | D21: 0 | E21: 0 | F21: 58567.58 | G21: 21636.52 | H21: 75943.67 | I21: 75943.67
A22: 1403 | B22: Ventas no industriales | C22: 247.75 | D22: 0 | E22: 166.21 | F22: 0 | G22: 224070.49 | H22: 7055.64 | I22: 7055.64
A23: 17 | B23: Rentas de Invesiones y Multas | C23: =SUM(C24:C26) -> 1686.76 | D23: =SUM(D24:D26) -> 2434.12 | E23: =SUM(E24:E26) -> 1160 | F23: =SUM(F24:F26) -> 22279.4 | G23: =SUM(G24:G26) -> 1489.3 | H23: =SUM(H24:H26) -> 1160 | I23: =SUM(I24:I26) -> 1160
A24: 1701 | B24: Renta de inversiones | C24: 26.76 | D24: 0 | E24: 0 | F24: 0 | G24: 0 | H24: 0 | I24: 0
A25: 1702 | B25: Renta por arrendamiento de Bienes | C25: 1660 | D25: 1520 | E25: 1160 | F25: 1517.2 | G25: 1489.3 | H25: 1160 | I25: 1160
A26: 1704 | B26: Multas | C26: 0 | D26: 914.12 | E26: 0 | F26: 20762.2 | G26: 0 | H26: 0 | I26: 0
A27: 18 | B27: Transferencias y Donaciones Corrientes | C27: =SUM(C28:C29) -> 10430444 | D27: =SUM(D28:D29) -> 8668729.9 | E27: =SUM(E28:E29) -> 9939519.5 | F27: =SUM(F28:F29) -> 8546360.2 | G27: =SUM(G28:G29) -> 9424413.8 | H27: =SUM(H28:H29) -> 11054500 | I27: =SUM(I28:I29) -> 11054500
A28: 1801 | B28: Transferencias Corrientes del Sector Publico | C28: 9798828.3 | D28: 0 | E28: 0 | F28: 6417.01 | G28: 0 | H28: 0 | I28: 0
A29: 1806 | B29: Aportes y participaciones Corrientes del régimen Seccional Autónomo | C29: 631615.38 | D29: 8668729.9 | E29: 9939519.5 | F29: 8539943.2 | G29: 9424413.8 | H29: 11054500 | I29: 11054500
A30: 19 | B30: Otros ingresos | C30: =+C31 -> 64147.51 | D30: =+D31 -> 102077.27 | E30: =+E31 -> 143755.98 | F30: =+F31 -> 97333.7 | G30: =+G31 -> 284428.99 | H30: =+H31 -> 98915.94 | I30: =+I31 -> 98915.94
A31: 1904 | B31: Otros no Operacionales | C31: 64147.51 | D31: 102077.27 | E31: 143755.98 | F31: 97333.7 | G31: 284428.99 | H31: 98915.94 | I31: 98915.94
A32: TOTAL GASTOS CORRIENTES (2) | C32: =+C33+C42+C43+C44+C45+C46 -> 4995776.9 | D32: =+D33+D42+D43+D44+D45+D46 -> 6920481.2 | E32: =+E33+E42+E43+E44+E45+E46 -> 5982372.7 | F32: =+F33+F42+F43+F44+F45+F46 -> 6051206 | G32: =+G33+G42+G43+G44+G45+G46 -> 6077631.8 | H32: =+H33+H42+H43+H44+H45+H46 -> 7718671.6 | I32: =+I33+I42+I43+I44+I45+I46 -> 7718671.6
A33: 51 | B33: Gastos en personal | C33: =SUM(C34:C41) -> 3605533.1 | D33: =SUM(D34:D41) -> 3794540.7 | E33: =SUM(E34:E41) -> 3487547.7 | F33: =SUM(F34:F41) -> 3961263.7 | G33: =SUM(G34:G41) -> 3921804 | H33: =SUM(H34:H41) -> 4951922.9 | I33: =SUM(I34:I41) -> 4951922.9
A34: 5101 | B34: Remuneraciones Básicas | C34: 2566196.7 | D34: 2587001.4 | E34: 2482429.6 | F34: 2841525.2 | G34: 2841180.1 | H34: 3452914 | I34: 3452914
A35: 5102 | B35: Remuneraciones Complementarias | C35: =214892+55126.22 -> 270018.22 | D35: =243284.26+67979.31 -> 311263.57 | E35: =221107.63+59517.46 -> 280625.09 | F35: =251414.25+67256.05 -> 318670.3 | G35: =246733.57+70370.13 -> 317103.7 | H35: =297058.81+85357.98 -> 382416.79 | I35: =297058.81+85357.98 -> 382416.79
A36: 5103 | B36: Remuneraciones Compensatorias | C36: 0 | D36: 0 | E36: 0 | F36: 0 | G36: 0 | H36: 0 | I36: 0
A37: 5104 | B37: Subsidios | C37: 0 | D37: 0 | E37: 0 | F37: 0 | G37: 0 | H37: 0 | I37: 0
A38: 5105 | B38: Remuneraciones Temporales | C38: =18494.52+14013.33+23178.46 -> 55686.31 | D38: =9304.6+273298.55+13218.64+24894.97 -> 320716.76 | E38: =711.2+103320.03+9374.43+54401.99 -> 167807.65 | F38: =3783+129396.03+17207.53+18082.43 -> 168468.99 | G38: =4855.76+81033.87+9285.32+25078.16 -> 120253.11 | H38: =72708+19462.44+13464.31 -> 105634.75 | I38: =72708+19462.44+13464.31 -> 105634.75
A39: 5106 | B39: Aportes Patronales a la Seguridad Social | C39: =302946.02+188416.05 -> 491362.07 | D39: =338757.03+212509.09 -> 551266.12 | E39: =308759.89+209446.5 -> 518206.39 | F39: =350671.1+243235.28 -> 593906.38 | G39: =345013.83+238780.61 -> 583794.44 | H39: =415211.1+294787.35 -> 709998.45 | I39: =415211.1+294787.35 -> 709998.45
A40: 5107 | B40: Indemnizaciones | C40: =81292.3+140977.45 -> 222269.75 | D40: 24292.84 | E40: =27168.12+11310.78 -> 38478.9 | F40: =13275+13889.48+11528.35 -> 38692.83 | G40: =29352.5+16923.82+13196.33 -> 59472.65 | H40: =103245.08+34893.5+162820.33 -> 300958.91 | I40: =103245.08+34893.5+162820.33 -> 300958.91
A41: 5199 | B41: Asignaciones a distribuir | C41: 0 | D41: 0 | E41: 0 | F41: 0 | G41: 0 | H41: 0 | I41: 0
A42: 53 | B42: Bienes y servicios de consumo | C42: 0 | D42: 1017489.2 | E42: 808405.93 | F42: 681827.81 | G42: 790006.61 | H42: 874708.92 | I42: 874708.92
A43: 56 | B43: Gastos Financieros | C43: 767323.39 | D43: 680700.67 | E43: 655743.89 | F43: 638207.38 | G43: 603431.93 | H43: 980000 | I43: 980000
A44: 57 | B44: Otros gastos corrientes | C44: 25200 | D44: 248849.97 | E44: 184363.82 | F44: 160653.16 | G44: 168966.96 | H44: 309078.06 | I44: 309078.06
A45: 58 | B45: Transferencias y donaciones corrientes | C45: 597720.42 | D45: 1178900.6 | E45: 846311.43 | F45: 609253.94 | G45: 593422.32 | H45: 602961.71 | I45: 602961.71
A46: 59 | B46: Previsiones para reasignaciones | C46: 0 | D46: 0 | E46: 0 | F46: 0 | G46: 0 | H46: 0 | I46: 0
A47: SUPERAVIT/DEFICIT CORRIENTE (1) - (2) = (3) | C47: =+C9-C32 -> 5540512.9 | D47: =+D9-D32 -> 1907177.6 | E47: =+E9-E32 -> 4203451.4 | F47: =+F9-F32 -> 2751145.1 | G47: =+G9-G32 -> 3979475 | H47: =+H9-H32 -> 3580024.3 | I47: =+I9-I32 -> 3580024.3
A48: INGRESOS DE CAPITAL E INVERSIÓN (4) | C48: =+C49+C50+C51 -> 23640716 | D48: =+D49+D50+D51 -> 24079592 | E48: =+E49+E50+E51 -> 26727362 | F48: =+F49+F50+F51 -> 25599963 | G48: =+G49+G50+G51 -> 25211753 | H48: =+H49+H50+H51 -> 40781984 | I48: =+I49+I50+I51 -> 20663374
A49: 24 | B49: Venta de Activos no Financieros | C49: 0 | D49: 1273562.7 | E49: 0 | F49: 0 | G49: 0 | H49: 0 | I49: 0
A50: 27 | B50: Recuperación de inversiones | C50: 0 | D50: 0 | E50: 0 | F50: 0 | G50: 0 | H50: 0 | I50: 0
A51: 28 | B51: Transferencias y Donaciones de Capital e Inversión | C51: 23640716 | D51: 22806029 | E51: 26727362 | F51: 25599963 | G51: 25211753 | H51: 40781984 | I51: 20663374
A52: GASTOS DE CAPITAL E INVERSIÓN (5) | C52: =+C53+C62+C63+C64+C65+C66 -> 25704927 | D52: =+D53+D62+D63+D64+D65+D66 -> 24311785 | E52: =+E53+E62+E63+E64+E65+E66 -> 31996084 | F52: =+F53+F62+F63+F64+F65+F66 -> 30809369 | G52: =+G53+G62+G63+G64+G65+G66 -> 36661343 | H52: =+H53+H62+H63+H64+H65+H66 -> 54320993 | I52: =+I53+I62+I63+I64+I65+I66 -> 30085895
A53: 71 | B53: Gastos en personal para Inversión | C53: =SUM(C54:C61) -> 3818018.3 | D53: =SUM(D54:D61) -> 3255181 | E53: =SUM(E54:E61) -> 3631504.3 | F53: =SUM(F54:F61) -> 3920660 | G53: =SUM(G54:G61) -> 4176407.6 | H53: =SUM(H54:H61) -> 5076716.5 | I53: =SUM(I54:I61) -> 5076716.5
A54: 7101 | B54: Remuneraciones Básicas | C54: =483661.92+1569724.14 -> 2053386.1 | D54: =480107.92+1561788.2 -> 2041896.1 | E54: =502614.96+1613600.52 -> 2116215.5 | F54: =516394.92+1745682.13 -> 2262077 | G54: =464316+1727258.56 -> 2191574.6 | H54: =498468.55+1755613.08 -> 2254081.6 | I54: =498468.55+1755613.08 -> 2254081.6
A55: 7102 | B55: Remuneraciones Complementarias | C55: =206697.29+98660.92 -> 305358.21 | D55: =187050.97+97956.93 -> 285007.9 | E55: =206150.69+103922.11 -> 310072.8 | F55: =228891.25+114025.49 -> 342916.74 | G55: =240849.93+124954.54 -> 365804.47 | H55: =249319.67+136089.57 -> 385409.24 | I55: =249319.67+136089.57 -> 385409.24
A56: 7103 | B56: Remuneraciones Compensatorias | C56: =24792+198336 -> 223128 | D56: =24665+197320 -> 221985 | E56: =25362.5+202900 -> 228262.5 | F56: =26445.5+211564 -> 238009.5 | G56: =26740.5+213924 -> 240664.5 | H56: =30855+246840 -> 277695 | I56: =30855+246840 -> 277695
A57: 7104 | B57: Subsidios | C57: =9274.75+14670.37 -> 23945.12 | D57: =9258.49+18348.32 -> 27606.81 | E57: =10811.64+22366.63 -> 33178.27 | F57: =11186.43+27864.59 -> 39051.02 | G57: =11282.76+31746.47 -> 43029.23 | H57: =11173.84+38498.22 -> 49672.06 | I57: =11173.84+38498.22 -> 49672.06
A58: 7105 | B58: Remuneraciones Temporales | C58: =427656.68+894.11+19526 -> 448076.79 | D58: =170384.84+53055.25 -> 223440.09 | E58: =318271.48+523.87+56454.7 -> 375250.05 | F58: =484566.86+4581.22+3105.65 -> 492253.73 | G58: =701916.26+120.48+3052.71 -> 705089.45 | H58: =3580+1305462.36+3214.45 -> 1312256.8 | I58: =3580+1305462.36+3214.45 -> 1312256.8
A59: 7106 | B59: Aportes Patronales a la Seguridad Social | C59: =299532.01+181029.9 -> 480561.91 | D59: =272096.42+175077.19 -> 447173.61 | E59: =298343.59+194785.01 -> 493128.6 | F59: =329619.37+210443.21 -> 540062.58 | G59: =346002.07+216388.87 -> 562390.94 | H59: =355481.96+241460.56 -> 596942.52 | I59: =355481.96+241460.56 -> 596942.52
A60: 7107 | B60: Indemnizaciones | C60: =247746.67+35815.52 -> 283562.19 | D60: 8071.47 | E60: =57015.72+12725.17+1845.66+3810.07 -> 75396.62 | F60: =4971.34+1318.06 -> 6289.4 | G60: =55348.56+12505.86 -> 67854.42 | H60: =162521.24+38137.97 -> 200659.21 | I60: =162521.24+38137.97 -> 200659.21
A61: 7199 | B61: Asignaciones a distribuir | C61: 0 | D61: 0 | E61: 0 | F61: 0 | G61: 0 | H61: 0 | I61: 0
A62: 73 | B62: Bienes y servicios para inversión | C62: 3292963 | D62: 4465495.5 | E62: 2819690.8 | F62: 1927661.8 | G62: 3323524.4 | H62: 5481851.1 | I62: 5481851.1
A63: 75 | B63: Obras públicas | C63: 1900958.2 | D63: 3055364.3 | E63: 15053766 | F63: 15805137 | G63: 19199810 | H63: 35080411 | I63: =14961801.09-4116488.11 -> 10845313
A64: 77 | B64: Otros Gastos de Inversión | C64: 211902.88 | D64: 37637.91 | E64: 2663.36 | F64: 2580.02 | G64: 2706.27 | H64: 33532.56 | I64: 33532.56
A65: 78 | B65: Transferencias y donaciones para inversión | C65: 15747665 | D65: 11481733 | E65: 10132200 | F65: 8969291.9 | G65: 9638635.5 | H65: 7446170.1 | I65: 7446170.1
A66: 84 | B66: Bienes de larga duración | C66: 733419.38 | D66: 2016373.2 | E66: 356259.59 | F66: 184038.38 | G66: 320259.69 | H66: 1202312.1 | I66: 1202312.1
A67: SUPERAVIT/DEFICIT DE CAPITAL E INVERSIÓN (4) - (5) = (6) | C67: =+C48-C52 -> -2064211 | D67: =+D48-D52 -> -232192.68 | E67: =+E48-E52 -> -5268722 | F67: =+F48-F52 -> -5209406.7 | G67: =+G48-G52 -> -11449590 | H67: =+H48-H52 -> -13539010 | I67: =+I48-I52 -> -9422521.6
A68: SUPERAVIT/DEFICIT FISCAL (3) + (6) | C68: =+C47+C67 -> 3476301.9 | D68: =+D47+D67 -> 1674984.9 | E68: =+E47+E67 -> -1065270.6 | F68: =+F47+F67 -> -2458261.5 | G68: =+G47+G67 -> -7470115 | H68: =+H47+H67 -> -9958985.3 | I68: =+I47+I67 -> -5842497.2
A69: FUENTES FINANCIERAS (7) | C69: =SUM(C70:C72) -> 2469983.8 | D69: =SUM(D70:D72) -> 3688836.2 | E69: =SUM(E70:E72) -> 6417647.5 | F69: =SUM(F70:F72) -> 5324262 | G69: =SUM(G70:G72) -> 8415454.6 | H69: =SUM(H70:H72) -> 7505351.2 | I69: =SUM(I70:I72) -> 3388863.1
A70: 36 | B70: Financiamiento Público | C70: 1667386.7 | D70: 2201595.3 | E70: 2568506.6 | F70: 810000 | G70: 2234101.7 | H70: 4116488.1 | I70: 0
A71: 37 | B71: Saldos disponibles | C71: 0 | D71: 0 | E71: 0 | F71: 0 | H71: 0 | I71: 0
A72: 38 | B72: Cuenta Pendientes por Cobrar | C72: 802597.1 | D72: 1487240.9 | E72: 3849140.9 | F72: 4514262 | G72: 6181352.8 | H72: 3388863.1 | I72: 3388863.1
A73: USOS FINANCIEROS (8) | C73: =SUM(C74:C77) -> 3425565.5 | D73: =SUM(D74:D77) -> 2117420.7 | E73: =SUM(E74:E77) -> 1884863.1 | F73: =SUM(F74:F77) -> 2274156.8 | G73: =SUM(G74:G77) -> 1957718 | H73: =SUM(H74:H77) -> 1293184.4 | I73: =SUM(I74:I77) -> 1293184.4
A74: 87 | B74: Inversiones financieras | C74: 0 | D74: 0 | E74: 0 | F74: 0 | G74: 0 | H74: 0 | I74: 0
A75: 96 | B75: Amortización de la deuda | C75: 3040751.3 | D75: 2071059.2 | E75: 1872159.6 | F75: 2200056.5 | G75: 1862139.5 | H75: 1120000 | I75: 1120000
A76: 97 | B76: Pasivo Circulante | C76: 0 | D76: 0 | E76: 0 | F76: 0 | G76: 0 | H76: 0 | I76: 0
A77: 99 | B77: Otros Pasivos | C77: 384814.21 | D77: 46361.52 | E77: 12703.41 | F77: 74100.36 | G77: 95578.51 | H77: 173184.45 | I77: 173184.45
A78: SUPERAVIT/DEFICIT DE FINANCIAMIENTO (7) - (8) | C78: =+C69-C73 -> -955581.74 | D78: =+D69-D73 -> 1571415.5 | E78: =+E69-E73 -> 4532784.4 | F78: =+F69-F73 -> 3050105.2 | G78: =+G69-G73 -> 6457736.6 | H78: =+H69-H73 -> 6212166.8 | I78: =+I69-I73 -> 2095678.7
A79: SUPERAVIT/DEFICIT PRESUPUESTARIO | C79: =+C47+C67+C78 -> 2520720.1 | D79: =+D47+D67+D78 -> 3246400.4 | E79: =+E47+E67+E78 -> 3467513.8 | F79: =+F47+F67+F78 -> 591843.72 | G79: =+G47+G67+G78 -> -1012378.4 | H79: =+H47+H67+H78 -> -3746818.6 | I79: =+I47+I67+I78 -> -3746818.6
A81: LIMITES DE ENDEUDAMIENTO | C81: 2014 | D81: 2015 | E81: 2016 | F81: 2017 | G81: 2018 | H81: 2019 | I81: 2020
A82: DEUDA PUBLICA | C82: 0.5961 | D82: 0.6454 | E82: 0.54935347 | F82: 0.54759172 | G82: 0.4 | H82: 0.27
A83: SERVICIO DE DEUDA | C83: 0.1089 | D83: 0.083621689 | E83: 0.068482398 | F83: 0.082502121 | G83: 0.07 | H83: 0.04
A85: Nota: Las proyecciones del flujos se realizaron tomando el indicide inflacion del 2,50%
B91: ________________________________________ | E91: _____________________________________________
B92: PREFECTO DE LOJA | E92: DIRECTOR FINANCIERO GAD PROVINCIAL LOJA
B93: Ing. Rafael Dávila Egüez | E93: Ing. Eduardo Aguirre Valdiviezo
A95: Loja, 24 de junio de 2019
