Workbook
Name Excel_BuiltIn__FilterDatabase_4: #REF!
Name Excel_BuiltIn_Print_Area_4_1: #REF!
Name OLE_LINK1_4: #REF!

Sheet FORMULARIO 1
A1: MINISTERIO DE ECONOMIA Y FINANZAS
A2: FORMULARIO 1: "FUENTES DE FINANCIAMIENTO DEL PROYECTO DE CONTRATO COLECTIVO"
A3: DETALLE DE INGRESOS
A5: GOBIERNO AUTÓNOMO DESCENTRALIZADO MUNICIPAL DE YANTZAZA
A6: Nº PROYECTO CONTRATO COLECTIVO: DECIMO CUARTO
A8: FUENTES DE FINANCIAMIENTO | C8: FINANCIAMIENTO CONTRATO COLECTIVO VIGENTE ENE - ABR 2015 | D8: FINANCIAMIENTO CONTRATO COLECTIVO PROPUESTO MAY - DIC 2015 | E8: FINANCIAMIENTO CONTRATO COLECTIVO PROPUESTO ENE - DIC 2016 | F8: FINANCIAMIENTO CONTRATO COLECTIVO PROPUESTO ENE - DIC 2017 | G8: FINANCIAMIENTO CONTRATO COLECTIVO PROPUESTO ENE - DIC 2018 | H8: OBSERVACIONES
A9: 11 | B9: IMPUESTOS
A10: 1101 | B10: Sobre la Renta, Utilidades y Ganancias de Capital | C10: =E10/3 -> 9533.3333 | D10: =C10*2 -> 19066.667 | E10: 28600 | F10: =E10*1.01 -> 28886 | G10: =F10*1.01 -> 29174.86
A11: 1102 | B11: Sobre la propiedad | C11: =E11/3 -> 78666.667 | D11: =C11*2 -> 157333.33 | E11: 236000 | F11: =E11*1.01 -> 238360 | G11: =F11*1.01 -> 240743.6
A12: 1107 | B12: Impuestos Diversos | C12: =E12/3 -> 39200 | D12: =C12*2 -> 78400 | E12: 117600 | F12: =E12*1.01 -> 118776 | G12: =F12*1.01 -> 119963.76
A13: 13 | B13: TASAS Y CONTRIBUCIONES
A14: 1301 | B14: Tasas generales | C14: =E14/3 -> 65800 | D14: =C14*2 -> 131600 | E14: 197400 | F14: =E14*1.01 -> 199374 | G14: =F14*1.01 -> 201367.74
A15: 14 | B15: VENTA DE BIENES Y SERVICIOS
A16: 1403 | B16: Ventas no Industriales | C16: =E16/3 -> 10866.667 | D16: =C16*2 -> 21733.333 | E16: 32600 | F16: =E16*1.01 -> 32926 | G16: =F16*1.01 -> 33255.26
A17: 18 | B17: TRANSFERENCIAS Y DONACIONES CORRIENTES
A18: 1801 | B18: Transferencias Corrientes del Sector Público | C18: ='FORMULARIO 2'!C27-(SUM(C9:C17)) -> 121423.01 | D18: ='FORMULARIO 2'!D27-(SUM(D9:D17)) -> 207669.06 | E18: ='FORMULARIO 2'!E27-(SUM(E9:E17)) -> 286493.06 | F18: ='FORMULARIO 2'!F27-(SUM(F9:F17)) -> 281100.06 | G18: ='FORMULARIO 2'!G27-(SUM(G9:G17)) -> 275807.84
A19: TOTAL | C19: =SUM(C9:C18) -> 325489.68 | D19: =SUM(D9:D18) -> 615802.4 | E19: =SUM(E9:E18) -> 898693.06 | F19: =SUM(F9:F18) -> 899422.06 | G19: =SUM(G9:G18) -> 900313.06
A20: NOTA.-
A21: Se cumple con la regla fiscal.
A28: Ing. Leonardo Heriberto Cueva Jimenez
A29: DIRECTOR FINANCIERO GADM YANTZAZA
A31: Yantzaza, 23 de abril de 2021

Sheet FORMULARIO 2
A1: ='FORMULARIO 1'!A1:H1 -> MINISTERIO DE ECONOMIA Y FINANZAS
A2: FORMULARIO 2: "COSTOS DEL PROYECTO DE CONTRATO COLECTIVO"
A3: DETALLE DE GASTOS
A5: ='FORMULARIO 1'!A5:H5 -> GOBIERNO AUTÓNOMO DESCENTRALIZADO MUNICIPAL DE YANTZAZA
A6: ='FORMULARIO 1'!A6:H6 -> Nº PROYECTO CONTRATO COLECTIVO: DECIMO CUARTO
A8: GASTO DEL PERSONAL | C8: COSTO CONTRATO COLECTIVO VIGENTE ENE - ABR 2015 | D8: COSTO CONTRATO COLECTIVO PROPUESTO MAY - DIC 2015 | E8: COSTO CONTRATO COLECTIVO PROPUESTO ENE - DIC 2016 | F8: COSTO CONTRATO COLECTIVO PROPUESTO ENE - DIC 2017 | G8: COSTO CONTRATO COLECTIVO PROPUESTO ENE - DIC 2018 | H8: OBSERVACIONES
A9: GASTO PERSONAL
A10: 5101 | B10: REMUNERACIONES BASICAS
A11: 510105 | B11: REMUNERACION UNIFICADA | C11: ='FORMULARIO 3'!F95 -> 202100.24 | D11: ='FORMULARIO 3'!G95 -> 415720.48 | E11: ='FORMULARIO 3'!H95 -> 623580.72 | F11: ='FORMULARIO 3'!I95 -> 623580.72 | G11: ='FORMULARIO 3'!J95 -> 623580.72
A12: 5102 | B12: REMUNERACIONES COMPLEMENTARIAS
A13: 510203 | B13: DECIMOTERCER SUELDO | C13: ='FORMULARIO 3'!F94 -> 50525.06 | D13: ='FORMULARIO 3'!G94 -> 51965.06 | E13: ='FORMULARIO 3'!H94 -> 51965.06 | F13: ='FORMULARIO 3'!I94 -> 51965.06 | G13: ='FORMULARIO 3'!J94 -> 51965.06
A14: 510204 | B14: DECIMOCUARTO SUELDO | C14: =(354*81)/3 -> 9558 | D14: =((354*81)/3)*2 -> 19116 | E14: =366*81 -> 29646 | F14: =375*81 -> 30375 | G14: =386*81 -> 31266
A15: 5103 | B15: REMUNERACIONES COMPENSATORIAS
A16: 510306 | B16: ALIMENTACION | C16: =((2*24)*4)*81 -> 15552 | D16: =((2*24)*8)*81 -> 31104 | E16: =((2*24)*12)*81 -> 46656 | F16: =((2*24)*12)*81 -> 46656 | G16: =((2*24)*12)*81 -> 46656
A17: 5104 | B17: SUBSIDIOS
A18: 510401 | B18: POR CARGAS FAMILIARES | C18: =C11*0.01 -> 2021.0024 | D18: =D11*0.01 -> 4157.2048 | E18: =E11*0.01 -> 6235.8072 | F18: =F11*0.01 -> 6235.8072 | G18: =G11*0.01 -> 6235.8072
A19: 510408 | B19: SUBSIDIO DE ANTIGUEDAD | C19: =C11*0.0025 -> 505.2506 | D19: =D11*0.0025 -> 1039.3012 | E19: =E11*0.0025 -> 1558.9518 | F19: =F11*0.0025 -> 1558.9518 | G19: =G11*0.0025 -> 1558.9518
A20: 5106 | B20: APORTES PATRONALES A LA SEGURIDAD SOCIAL
A21: 510601 | B21: APORTE PATRONAL | C21: =C11*0.1115 -> 22534.177 | D21: =D11*0.1115 -> 46352.834 | E21: =E11*0.1115 -> 69529.25 | F21: =F11*0.1115 -> 69529.25 | G21: =G11*0.1115 -> 69529.25
A22: 510602 | B22: FONDO DE RESERVA | C22: =C11*0.0833 -> 16834.95 | D22: =D11*0.0833 -> 34629.516 | E22: =E11*0.0833 -> 51944.274 | F22: =F11*0.0833 -> 51944.274 | G22: =G11*0.0833 -> 51944.274
A23: 5308 | B23: BIENES DE USO Y CONSUMO CORRIENTE
A24: 530802 | B24: VESTUARIO, LENCERIA, PRENDAS DE PROTECCION | C24: =(169*81)/3 -> 4563 | D24: =((169*81)/3)*2 -> 9126 | E24: =169*81 -> 13689 | F24: =169*81 -> 13689 | G24: =169*81 -> 13689
A25: 5702 | B25: SEGUROS, COSTOS FINANCIEROS Y OTROS GASTOS
A26: 570201 | B26: SEGUROS | C26: =(4*4)*81 -> 1296 | D26: =(4*8)*81 -> 2592 | E26: =(4*12)*81 -> 3888 | F26: =(4*12)*81 -> 3888 | G26: =(4*12)*81 -> 3888
A27: TOTAL DE GASTO | C27: =SUM(C10:C26) -> 325489.68 | D27: =SUM(D10:D26) -> 615802.4 | E27: =SUM(E10:E26) -> 898693.06 | F27: =SUM(F10:F26) -> 899422.06 | G27: =SUM(G10:G26) -> 900313.06
A28: NOTA.-
A29: El cálculo de remuneraciones compensatorias se realizó tomando como referancia 24 dias laborados al mes.
A36: ='FORMULARIO 1'!A28:H28 -> Ing. Leonardo Heriberto Cueva Jimenez
A37: ='FORMULARIO 1'!A29:H29 -> DIRECTOR FINANCIERO GADM YANTZAZA
A39: ='FORMULARIO 1'!A31:H31 -> Yantzaza, 23 de abril de 2021

Sheet CERTIFICACION
A1: CERTIFICACION PRESUPUESTARIA
A3: La Dirección Financiera del Gobierno Autónomo Descentralizado Municipal del Cantón Yantzaza, CERTIFICA, que los costos del Decimo Cuarto Contrato Colectivo de Trabajo a ser suscrito con el Sindicato Único de Trabajadores del GAD, están contemplados en los respectivos presupuestos y la diferecia de incremento sera cancelada en el presente ejercicio fiscal 2021, de acuerdo al siguiente detalle:
A9: GASTO DEL PERSONAL | C9: COSTO CONTRATO COLECTIVO MAY - DIC 2015 | D9: COSTO CONTRATO COLECTIVO ENE - DIC 2016 | E9: COSTO CONTRATO COLECTIVO ENE - DIC 2017 | F9: COSTO CONTRATO COLECTIVO ENE - DIC 2018
A10: GASTO PERSONAL
A11: 5101 | B11: REMUNERACIONES BASICAS
A12: 510105 | B12: REMUNERACION UNIFICADA | C12: ='FORMULARIO 2'!D11 -> 415720.48 | D12: ='FORMULARIO 2'!E11 -> 623580.72 | E12: ='FORMULARIO 2'!F11 -> 623580.72 | F12: ='FORMULARIO 2'!G11 -> 623580.72
A13: 5102 | B13: REMUNERACIONES COMPLEMENTARIAS
A14: 510203 | B14: DECIMOTERCER SUELDO | C14: ='FORMULARIO 2'!D13 -> 51965.06 | D14: ='FORMULARIO 2'!E13 -> 51965.06 | E14: ='FORMULARIO 2'!F13 -> 51965.06 | F14: ='FORMULARIO 2'!G13 -> 51965.06
A15: 510204 | B15: DECIMOCUARTO SUELDO | C15: ='FORMULARIO 2'!D14 -> 19116 | D15: ='FORMULARIO 2'!E14 -> 29646 | E15: ='FORMULARIO 2'!F14 -> 30375 | F15: ='FORMULARIO 2'!G14 -> 31266
A16: 5103 | B16: REMUNERACIONES COMPENSATORIAS
A17: 510306 | B17: ALIMENTACION | C17: ='FORMULARIO 2'!D16 -> 31104 | D17: ='FORMULARIO 2'!E16 -> 46656 | E17: ='FORMULARIO 2'!F16 -> 46656 | F17: ='FORMULARIO 2'!G16 -> 46656
A18: 5104 | B18: SUBSIDIOS
A19: 510401 | B19: POR CARGAS FAMILIARES | C19: ='FORMULARIO 2'!D18 -> 4157.2048 | D19: ='FORMULARIO 2'!E18 -> 6235.8072 | E19: ='FORMULARIO 2'!F18 -> 6235.8072 | F19: ='FORMULARIO 2'!G18 -> 6235.8072
A20: 510408 | B20: SUBSIDIO DE ANTIGUEDAD | C20: ='FORMULARIO 2'!D19 -> 1039.3012 | D20: ='FORMULARIO 2'!E19 -> 1558.9518 | E20: ='FORMULARIO 2'!F19 -> 1558.9518 | F20: ='FORMULARIO 2'!G19 -> 1558.9518
A21: 5106 | B21: APORTES PATRONALES A LA SEGURIDAD SOCIAL
A22: 510601 | B22: APORTE PATRONAL | C22: ='FORMULARIO 2'!D21 -> 46352.834 | D22: ='FORMULARIO 2'!E21 -> 69529.25 | E22: ='FORMULARIO 2'!F21 -> 69529.25 | F22: ='FORMULARIO 2'!G21 -> 69529.25
A23: 510602 | B23: FONDO DE RESERVA | C23: ='FORMULARIO 2'!D22 -> 34629.516 | D23: ='FORMULARIO 2'!E22 -> 51944.274 | E23: ='FORMULARIO 2'!F22 -> 51944.274 | F23: ='FORMULARIO 2'!G22 -> 51944.274
A24: 5308 | B24: BIENES DE USO Y CONSUMO CORRIENTE
A25: 530802 | B25: VESTUARIO, LENCERIA, PRENDAS DE PROTECCION | C25: ='FORMULARIO 2'!D24 -> 9126 | D25: ='FORMULARIO 2'!E24 -> 13689 | E25: ='FORMULARIO 2'!F24 -> 13689 | F25: ='FORMULARIO 2'!G24 -> 13689
A26: 5702 | B26: SEGUROS, COSTOS FINANCIEROS Y OTROS GASTOS
A27: 570201 | B27: SEGUROS | C27: ='FORMULARIO 2'!D26 -> 2592 | D27: ='FORMULARIO 2'!E26 -> 3888 | E27: ='FORMULARIO 2'!F26 -> 3888 | F27: ='FORMULARIO 2'!G26 -> 3888
A28: TOTAL DE GASTO | C28: =SUM(C11:C27) -> 615802.4 | D28: =SUM(D11:D27) -> 898693.06 | E28: =SUM(E11:E27) -> 899422.06 | F28: =SUM(F11:F27) -> 900313.06
A29: NOTA.-
A30: La presente certificacion es total responsabilidad del GADM ECHEANDÍA
A37: ='FORMULARIO 1'!A28:H28 -> Ing. Leonardo Heriberto Cueva Jimenez
A38: ='FORMULARIO 1'!A29:H29 -> DIRECTOR FINANCIERO GADM YANTZAZA
A40: ='FORMULARIO 1'!A31:H31 -> Yantzaza, 23 de abril de 2021

Sheet FORMULARIO 3
A2: ='FORMULARIO 1'!A1:H1 -> MINISTERIO DE ECONOMIA Y FINANZAS
A3: FORMULARIO 3: "COMPARATIVO ENTRE REMUNERACIÓN UNIFICADA Y PROPUESTA"
A4: DISTRIBUTIVO DE SALARIO UNIFICADO DESAGREGADO POR TRABAJADOR
A7: ='FORMULARIO 1'!A5:H5 -> GOBIERNO AUTÓNOMO DESCENTRALIZADO MUNICIPAL DE YANTZAZA
A8: ='FORMULARIO 1'!A6:H6 -> Nº PROYECTO CONTRATO COLECTIVO: DECIMO CUARTO
A11: CEDULA | B11: APELLIDOS Y NOMBRES | C11: No. TRBJ. | D11: GRADO DEL CARGO O PUESTO | E11: DENOMINACIÓN DEL PUESTO O CARGO DE OCUPACIÓN | F11: R.M.U. VIGENTE ENE - ABR 2015 | G11: R.M.U. PROPUESTA MAY - DIC 2015 | H11: R.M.U. PROPUESTA ENE - DIC 2016 | I11: R.M.U. PROPUESTA ENE - DIC 2017 | J11: R.M.U. PROPUESTA ENE - DIC 2018 | K11: OBSERVACIONES
A12: 1103055552 | B12: Aguinsaca Jaura José Pedro | C12: 1 | D12: 2 | E12: ALBAÑIL | F12: 548 | G12: 578 | H12: 578 | I12: 578 | J12: 578
A13: 1204917619 | B13: Anguisaca Campuzano Juan Carlos | C13: 2 | D13: 5 | E13: OPERADOR DE EXCAVADORA | F13: 708 | G13: 738 | H13: 738 | I13: 738 | J13: 738
A14: 1900284207 | B14: Arévalo Arévalo Mario Alcivar | C14: 3 | D14: 1 | E14: AYUDANTE DE EQUIPO CAMINERO | F14: 531 | G14: 561 | H14: 561 | I14: 561 | J14: 561
A15: 1105004830 | B15: Arévalo Correa David Waldimir | C15: 4 | D15: 3 | E15: POLICIA MUNICIPAL | F15: 566 | G15: 596 | H15: 596 | I15: 596 | J15: 596
A16: 1900457134 | B16: Armijos Godoy Franklin Hernán | C16: 5 | D16: 1 | E16: AYUDANTE DE EQUIPO CAMINERO | F16: 583.06 | G16: 583.06 | H16: 583.06 | I16: 583.06 | J16: 583.06
A17: 1900307941 | B17: Armijos González Richard Leonel | C17: 6 | D17: 8 | E17: TÉCNICO DE ELECTRICIDAD | F17: 703.83 | G17: 733.83 | H17: 733.83 | I17: 733.83 | J17: 733.83
A18: 1900310622 | B18: Armijos Puglla Henry José | C18: 7 | D18: 1 | E18: SOBRESTANTE DE HIGIENE AMBIENTAL | F18: 603.71 | G18: 603.71 | H18: 603.71 | I18: 603.71 | J18: 603.71
A19: 1900515329 | B19: Banegas Torres Bolívar Hernán | C19: 8 | D19: 5 | E19: OPERADOR DE EXCAVADORA | F19: 708 | G19: 738 | H19: 738 | I19: 738 | J19: 738
A20: 1102815279 | B20: Barba Cevallos José Reinaldo | C20: 9 | D20: 4 | E20: CHOFER DE VEHÍCULOS PESADOS | F20: 749.54 | G20: 749.54 | H20: 749.54 | I20: 749.54 | J20: 749.54
A21: 1104157688 | B21: Bastidas Galvez Lauro Miguel | C21: 10 | D21: 1 | E21: AYUDANTE DE RECOLECCIÓN DE ASEO | F21: 531 | G21: 561 | H21: 561 | I21: 561 | J21: 561
A22: 1900453224 | B22: Bautista Michay Víctor Patricio | C22: 11 | D22: 1 | E22: AYUDANTE DE EQUIPO Y/O MAQUINARIA PESADA | F22: 624.12 | G22: 624.12 | H22: 624.12 | I22: 624.12 | J22: 624.12
A23: 1900185057 | B23: Benitez Acaro Abel Mateo | C23: 12 | D23: 5 | E23: OPERADOR DE CARGADORA | F23: 921.65 | G23: 921.65 | H23: 921.65 | I23: 921.65 | J23: 921.65
... A26: 1900066695 | B26: Camacho Soto Aníbal Vidal | C26: 15 | D26: 3 | E26: POLICIA MUNICIPAL | F26: 610.36 | G26: 610.36 | H26: 610.36 | I26: 610.36 | J26: 610.36
A27: 0704860246 | B27: Cango Armijos Luis Eduardo | C27: 16 | D27: 2 | E27: SOLDADOR | F27: 548 | G27: 578 | H27: 578 | I27: 578 | J27: 578
A28: 1900406552 | B28: Cango Cuenca Fausto Lenín | C28: 17 | D28: 1 | E28: AUXILIAR DE SERVICIOS | F28: 531 | G28: 561 | H28: 561 | I28: 561 | J28: 561
A29: 1900333053 | B29: Castillo Castillo Edy Fausto | C29: 18 | D29: 1 | E29: AYUDANTE DE EQUIPO CAMINERO | F29: 567.19 | G29: 567.19 | H29: 567.19 | I29: 567.19 | J29: 567.19
A30: 1900451590 | B30: Chumapi Jumbo Walter Humberto | C30: 19 | D30: 1 | E30: JORNALERO | F30: 531 | G30: 561 | H30: 561 | I30: 561 | J30: 561
A31: 1900198589 | B31: Condolo Guaillas Pedro Francisco | C31: 20 | D31: 1 | E31: PEÓN | F31: 531 | G31: 561 | H31: 561 | I31: 561 | J31: 561
A32: 1900466721 | B32: Cuenca Cuenca César Augusto | C32: 21 | D32: 5 | E32: OPERADOR DE MAQUINARIA O EQUIPO PESADO | F32: 708 | G32: 738 | H32: 738 | I32: 738 | J32: 738
A33: 1900127752 | B33: Cueva Ochoa Vicente Medardo | C33: 22 | D33: 1 | E33: JORNALERO DE PARQUES Y JARDINES | F33: 594.11 | G33: 594.11 | H33: 594.11 | I33: 594.11 | J33: 594.11
A34: 1101576856 | B34: Curipoma Macas Manuel Salvador | C34: 23 | D34: 1 | E34: JORNALERO DE PARQUES Y JARDINES | F34: 531 | G34: 561 | H34: 561 | I34: 561 | J34: 561
A35: 1103226997 | B35: Espinosa Cumbicos Neli Esmeralda | C35: 24 | D35: 1 | E35: JORNALERO | F35: 603.68 | G35: 603.68 | H35: 603.68 | I35: 603.68 | J35: 603.68
A36: 1900668763 | B36: Godoy Mendoza Braulio Ricardo | C36: 25 | D36: 1 | E36: MENSAJERO | F36: 531 | G36: 561 | H36: 561 | I36: 561 | J36: 561
A37: 1900240050 | B37: González Cabrera Darwin Patricio | C37: 26 | D37: 4 | E37: CHOFER DE RECOLECTOR | F37: 584 | G37: 614 | H37: 614 | I37: 614 | J37: 614
A38: 1900334440 | B38: Gualán Caillagua Fredy Gustavo | C38: 27 | D38: 2 | E38: GASFITERO O PLOMERO | F38: 612.76 | G38: 612.76 | H38: 612.76 | I38: 612.76 | J38: 612.76
A39: 1103301725 | B39: Gualán Gualán Ángel Benigno | C39: 28 | D39: 5 | E39: OPERADOR RETROEXCAVADORA | F39: 708 | G39: 738 | H39: 738 | I39: 738 | J39: 738
... A54: 1900369560 | B54: Montalvan Gómez Jaime Rodrigo | C54: 43 | D54: 5 | E54: OPERADOR DE MOTONIVELADORA | F54: 708 | G54: 738 | H54: 738 | I54: 738 | J54: 738
A55: 1900411404 | B55: Montaño Márquez Roberto Carlos | C55: 44 | D55: 3 | E55: POLICIA MUNICIPAL | F55: 610.36 | G55: 610.36 | H55: 610.36 | I55: 610.36 | J55: 610.36
A56: 1900253558 | B56: Morales Cabrera José Efrén | C56: 45 | D56: 5 | E56: OPERADOR RETROEXCAVADORA | F56: 708 | G56: 738 | H56: 738 | I56: 738 | J56: 738
A57: 1101785986 | B57: Morocho Chamba Ángel Benigno | C57: 46 | D57: 4 | E57: CHOFER DE VEHÍCULOS PESADOS | F57: 584 | G57: 614 | H57: 614 | I57: 614 | J57: 614
A58: 1102603444 | B58: Morocho Salinas José Patricio | C58: 47 | D58: 4 | E58: CHOFER DE VEHÍCULOS PESADOS | F58: 630 | G58: 630 | H58: 630 | I58: 630 | J58: 630
A59: 1900359082 | B59: Mosquera Calero Manuel Agustín | C59: 48 | D59: 6 | E59: INSPECTOR DE MAQUINARIA Y TRABAJOS MUN | F59: 743 | G59: 773 | H59: 773 | I59: 773 | J59: 773
A60: 1900568534 | B60: Naula Montaño Marcelo Ismael | C60: 49 | D60: 5 | E60: OPERADOR DE EXCAVADORA | F60: 708 | G60: 738 | H60: 738 | I60: 738 | J60: 738
A61: 1900521939 | B61: Ochoa Rodríguez José Joaquin | C61: 50 | D61: 1 | E61: AYUDANTE DE EQUIPO CAMINERO | F61: 531 | G61: 561 | H61: 561 | I61: 561 | J61: 561
A62: 1900228506 | B62: Ojeda Ojeda Melecio | C62: 51 | D62: 1 | E62: GUARDIÁN DE PLANTA | F62: 807.86 | G62: 807.86 | H62: 807.86 | I62: 807.86 | J62: 807.86
A63: 101018976 | B63: Palacios Castro Emiliano Telmo | C63: 52 | D63: 5 | E63: OPERADOR DE LA PLANTA DE TRATAMIENTO DE AP | F63: 708 | G63: 738 | H63: 738 | I63: 738 | J63: 738
A64: 1900243807 | B64: Palta Rivera Jhonson Amable | C64: 53 | D64: 4 | E64: CHOFER DE VEHÍCULOS PESADOS | F64: 758.01 | G64: 758.01 | H64: 758.01 | I64: 758.01 | J64: 758.01
A65: 1900286467 | B65: Peralta Sarango Nolmi Silger | C65: 54 | D65: 5 | E65: OPERADOR DE AUTO TREN TRAILER | F65: 708 | G65: 738 | H65: 738 | I65: 738 | J65: 738
A66: 1900296805 | B66: Puchaicela Armijos Hernán Gustavo | C66: 55 | D66: 5 | E66: OPERADOR DE EXCAVADORA | F66: 800.08 | G66: 800.08 | H66: 800.08 | I66: 800.08 | J66: 800.08
A67: 1900282185 | B67: Puchaicela Viñamagua Ángel Floresmilo | C67: 56 | D67: 4 | E67: CHOFER DE VEHÍCULOS PESADOS | F67: 616.17 | G67: 616.17 | H67: 616.17 | I67: 616.17 | J67: 616.17
A68: 1707510846 | B68: Puglla Cabrera Bolivar | C68: 57 | D68: 1 | E68: JORNALERO | F68: 531 | G68: 561 | H68: 561 | I68: 561 | J68: 561
A69: 1900493931 | B69: Quezada Jima Franklin Euclides | C69: 58 | D69: 3 | E69: CHOFER DE VEHÍCULO LIVIANO | F69: 566 | G69: 596 | H69: 596 | I69: 596 | J69: 596
A70: 1102061627 | B70: Quezada Masa Segundo Gabriel | C70: 59 | D70: 2 | E70: ALBAÑIL | F70: 548 | G70: 578 | H70: 578 | I70: 578 | J70: 578
A71: 102284460 | B71: Quezada Quezada Leandro Salomón | C71: 60 | D71: 3 | E71: CHOFER DE VEHÍCULO LIVIANO | F71: 566 | G71: 596 | H71: 596 | I71: 596 | J71: 596
A72: 1900413731 | B72: Quezada Quezada Manuel Agustin | C72: 61 | D72: 1 | E72: AYUDANTE DE TRACTOR | F72: 596 | G72: 596 | H72: 596 | I72: 596 | J72: 596
A73: 1900705987 | B73: Quezada Vicente Fernando Isaias | C73: 62 | D73: 3 | E73: POLICIA MUNICIPAL | F73: 596.15 | G73: 596.15 | H73: 596.15 | I73: 596.15 | J73: 596.15
A74: 701385684 | B74: Quilli Chacha Luis Aurelio | C74: 63 | D74: 4 | E74: CHOFER DE VEHÍCULOS PESADOS | F74: 626.36 | G74: 626.36 | H74: 626.36 | I74: 626.36 | J74: 626.36
A75: 1900513266 | B75: Quituizaca Guamán Segundo Patricio | C75: 64 | D75: 1 | E75: JORNALERO | F75: 614.58 | G75: 614.58 | H75: 614.58 | I75: 614.58 | J75: 614.58
A76: 1900564335 | B76: Quizhpe Chamba Julio Diego | C76: 65 | D76: 3 | E76: POLICIA MUNICIPAL | F76: 566 | G76: 596 | H76: 596 | I76: 596 | J76: 596
A77: 1900392935 | B77: Ramón Montaño Luis Salvador | C77: 66 | D77: 4 | E77: CHOFER DE RECOLECTOR | F77: 584 | G77: 614 | H77: 614 | I77: 614 | J77: 614
A78: 1900447788 | B78: Rengel Sánchez Pedro Walter | C78: 67 | D78: 1 | E78: JORNALERO | F78: 531 | G78: 561 | H78: 561 | I78: 561 | J78: 561
... A83: 1102113907 | B83: Sarango Castillo Pedro Ovidio | C83: 72 | D83: 5 | E83: OPERADOR DE ESCAVADORA | F83: 927.4 | G83: 927.4 | H83: 927.4 | I83: 927.4 | J83: 927.4
A84: 1900292010 | B84: Sarango Reyes José Alfredo | C84: 73 | D84: 3 | E84: POLICIA MUNICIPAL | F84: 610.36 | G84: 610.36 | H84: 610.36 | I84: 610.36 | J84: 610.36
A85: 1900281948 | B85: Tinisaray Villa Jaime Leoncio | C85: 74 | D85: 3 | E85: POLICIA MUNICIPAL | F85: 610.36 | G85: 610.36 | H85: 610.36 | I85: 610.36 | J85: 610.36
A86: 1900130566 | B86: Tocto Ramón Segundo Luis | C86: 75 | D86: 4 | E86: CHOFER DE VEHÍCULOS PESADOS | F86: 584 | G86: 614 | H86: 614 | I86: 614 | J86: 614
A87: 1900268135 | B87: Vasquez Morales Erman Rodrigo | C87: 76 | D87: 5 | E87: OPERADOR DE MOTONIVELADORA | F87: 708 | G87: 738 | H87: 738 | I87: 738 | J87: 738
A88: 1102365010 | B88: Veintimilla Jaramillo Luis Antonio | C88: 77 | D88: 4 | E88: CHOFER DE VEHÍCULOS PESADOS | F88: 584 | G88: 614 | H88: 614 | I88: 614 | J88: 614
A89: 1900498849 | B89: Vera Armijos Rolando Isaias | C89: 78 | D89: 1 | E89: AYUDANTE DE ALBAÑIL | F89: 531 | G89: 561 | H89: 561 | I89: 561 | J89: 561
A90: 1900180538 | B90: Villavicencio Cabrera Galo | C90: 79 | D90: 1 | E90: AYUDANTE DE EQUIPO Y/O MAQUINARIA PESADA | F90: 618.78 | G90: 618.78 | H90: 618.78 | I90: 618.78 | J90: 618.78
A91: 1102014253 | B91: Villavicencio Chimbo Anival Esau | C91: 80 | D91: 3 | E91: CHOFER DE VEHÍCULO LIVIANO | F91: 566 | G91: 596 | H91: 596 | I91: 596 | J91: 596
A92: 1900120195 | B92: Zúñiga Sarango Leonardo | C92: 81 | D92: 4 | E92: CHOFER DE VEHÍCULOS PESADOS | F92: 626.75 | G92: 626.75 | H92: 626.75 | I92: 626.75 | J92: 626.75
E94: REMUNERACION MENSUAL UNIFICADA | F94: =SUM(F12:F92) -> 50525.06 | G94: =SUM(G12:G92) -> 51965.06 | H94: =SUM(H12:H92) -> 51965.06 | I94: =SUM(I12:I92) -> 51965.06 | J94: =SUM(J12:J92) -> 51965.06
E95: REMUNERACION ANUAL UNIFICADA | F95: =F94*4 -> 202100.24 | G95: =G94*8 -> 415720.48 | H95: =H94*12 -> 623580.72 | I95: =I94*12 -> 623580.72 | J95: =J94*12 -> 623580.72
A97: NOTA: El número de trabajadores difiere del proyecto de contrato colectivo puesto que algunos de los trabajadores se han desvinculado de la institución durante la aprobación.
A104: ='FORMULARIO 1'!A28:H28 -> Ing. Leonardo Heriberto Cueva Jimenez
A105: ='FORMULARIO 1'!A29:H29 -> DIRECTOR FINANCIERO GADM YANTZAZA
A107: ='FORMULARIO 1'!A31:H31 -> Yantzaza, 23 de abril de 2021

Sheet FORMULARIO 4
A1: MINISTERIO DE ECONOMIA Y FINANZAS
A2: FORMULARIO 4 "FLUJO PRESUPUESTARIO DE INGRESOS Y GASTOS"
A4: ='FORMULARIO 1'!A5:H5 -> GOBIERNO AUTÓNOMO DESCENTRALIZADO MUNICIPAL DE YANTZAZA
A6: DETALLE DE GRUPOS Y SUBGRUPOS | C6: FLUJO HISTORICO (USD) | I6: FLUJO PROYECTADO (USD) | M6: OBSERVACIONES
A7: Grupo y Subgrupo | B7: Descripción | C7: 2015 | D7: 2016 | E7: 2017 | F7: 2018 | G7: 2019 | H7: 2020 | I7: 2021 | J7: 2022 | K7: 2023 | L7: 2024
A8: TOTAL INGRESOS CORRIENTES (1) | C8: =SUM(C9,C13,C17:C20) -> 3247931 | D8: =SUM(D9,D13,D17:D20) -> 2846323.2 | E8: =SUM(E9,E13,E17:E20) -> 1349651.6 | F8: =SUM(F9,F13,F17:F20) -> 4733296.6 | G8: =SUM(G9,G13,G17:G20) -> 5081231.9 | H8: =SUM(H9,H13,H17:H20) -> 5725427.7 | I8: =SUM(I9,I13,I17:I20) -> 5868563.4 | J8: =SUM(J9,J13,J17:J20) -> 6015277.5 | ... L8: =SUM(L9,L13,L17:L20) -> 6319800.9
A9: 11 | B9: Impuestos | C9: =SUM(C10:C12) -> 967650.68 | D9: =SUM(D10:D12) -> 1033052.6 | E9: =SUM(E10:E12) -> 144135.56 | F9: =SUM(F10:F12) -> 1546509.2 | G9: =SUM(G10:G12) -> 2231453.2 | H9: =SUM(H10:H12) -> 2951059.8 | I9: =SUM(I10:I12) -> 3024836.3 | J9: =SUM(J10:J12) -> 3100457.2 | ... L9: =SUM(L10:L12) -> 3257417.9
A10: 1.1.01 | B10: Sobre la Renta, Utilidades y Ganancias de Capital | C10: 93116.3 | D10: 58723.33 | E10: 10235 | F10: 84797.2 | G10: 81474.7 | H10: 71749.69 | I10: =H10*1.025 -> 73543.432 | J10: =I10*1.025 -> 75382.018 | K10: =J10*1.025 -> 77266.569 | L10: =K10*1.025 -> 79198.233
A11: 1.1.02 | B11: Sobre la propiedad | C11: 636882.69 | D11: 751767.77 | E11: 96157.93 | F11: 1189771.8 | G11: 1804598.1 | H11: 2388529.2 | I11: =H11*1.025 -> 2448242.4 | J11: =I11*1.025 -> 2509448.4 | K11: =J11*1.025 -> 2572184.7 | L11: =K11*1.025 -> 2636489.3
A12: 1.1.07 | B12: Impuestos Diversos | C12: 237651.69 | D12: 222561.54 | E12: 37742.63 | F12: 271940.24 | G12: 345380.36 | H12: 490780.97 | I12: =H12*1.025 -> 503050.49 | J12: =I12*1.025 -> 515626.76 | K12: =J12*1.025 -> 528517.43 | L12: =K12*1.025 -> 541730.36
A13: 13 | B13: Tasas y contribuciones | C13: =SUM(C14:C16) -> 456174.06 | D13: =SUM(D14:D16) -> 449225.21 | E13: =SUM(E14:E16) -> 168544.68 | F13: =SUM(F14:F16) -> 1474118.4 | G13: =SUM(G14:G16) -> 1044660.4 | H13: =SUM(H14:H16) -> 1259095.9 | I13: =SUM(I14:I16) -> 1290573.3 | J13: =SUM(J14:J16) -> 1322837.7 | ... L13: =SUM(L14:L16) -> 1389806.3
A14: 1.3.01 | B14: Tasas generales | C14: 416523.72 | D14: 418858.69 | E14: 168544.68 | F14: 1439364.9 | G14: 641076.19 | H14: 673566.46 | I14: =H14*1.025 -> 690405.62 | J14: =I14*1.025 -> 707665.76 | K14: =J14*1.025 -> 725357.41 | L14: =K14*1.025 -> 743491.34
A15: 1.3.03 | B15: Tasas Diversas | C15: 0 | D15: 0 | E15: 0 | F15: 20457.23 | G15: 389896.61 | H15: 573492.86 | I15: =H15*1.025 -> 587830.18 | J15: =I15*1.025 -> 602525.94 | K15: =J15*1.025 -> 617589.08 | L15: =K15*1.025 -> 633028.81
A16: 1.3.04 | B16: Contribuciones | C16: 39650.34 | D16: 30366.52 | E16: 0 | F16: 14296.25 | G16: 13687.6 | H16: 12036.62 | I16: =H16*1.025 -> 12337.535 | J16: =I16*1.025 -> 12645.974 | K16: =J16*1.025 -> 12962.123 | L16: =K16*1.025 -> 13286.176
A17: 14 | B17: Venta de Bienes y Servicios | C17: 287488.94 | D17: 276620.11 | E17: 123075.91 | F17: 356681.46 | G17: 409549.71 | H17: 422844.29 | I17: =H17*1.025 -> 433415.4 | J17: =I17*1.025 -> 444250.78 | K17: =J17*1.025 -> 455357.05 | L17: =K17*1.025 -> 466740.98
A18: 17 | B18: Rentas de Invesiones y Multas | C18: 118099.83 | D18: 132498.15 | E18: 41797.31 | F18: 193331.48 | G18: 212876.27 | H18: 165895.67 | I18: =H18*1.025 -> 170043.06 | J18: =I18*1.025 -> 174294.14 | K18: =J18*1.025 -> 178651.49 | L18: =K18*1.025 -> 183117.78
A19: 18 | B19: Transferencias y Donaciones Corrientes | C19: 1392333 | D19: 925597.74 | E19: 857961.67 | F19: 1139993.9 | G19: 1039488.3 | H19: 864136.38 | I19: =H19*1.025 -> 885739.79 | J19: =I19*1.025 -> 907883.28 | K19: =J19*1.025 -> 930580.37 | L19: =K19*1.025 -> 953844.88
A20: 19 | B20: Otros ingresos | C20: =SUM(C21:C21) -> 26184.41 | D20: =SUM(D21:D21) -> 29329.4 | E20: =SUM(E21:E21) -> 14136.47 | F20: =SUM(F21:F21) -> 22662.23 | G20: =SUM(G21:G21) -> 143204.03 | H20: =SUM(H21:H21) -> 62395.62 | I20: =SUM(I21:I21) -> 63955.51 | J20: =SUM(J21:J21) -> 65554.398 | ... L20: =SUM(L21:L21) -> 68873.09
A21: 1.9.04 | B21: Otros no Operacionales | C21: 26184.41 | D21: 29329.4 | E21: 14136.47 | F21: 22662.23 | G21: 143204.03 | H21: 62395.62 | I21: =H21*1.025 -> 63955.51 | J21: =I21*1.025 -> 65554.398 | K21: =J21*1.025 -> 67193.258 | L21: =K21*1.025 -> 68873.09
A22: TOTAL GASTOS CORRIENTES (2) | C22: =SUM(C23,C40,C50,C53,C56) -> 2774531.2 | D22: =SUM(D23,D40,D50,D53,D56) -> 2286649.7 | E22: =SUM(E23,E40,E50,E53,E56) -> 2236453.9 | F22: =SUM(F23,F40,F50,F53,F56) -> 2458555.1 | G22: =SUM(G23,G40,G50,G53,G56) -> 2935706.6 | H22: =SUM(H23,H40,H50,H53,H56) -> 2718089.2 | I22: =SUM(I23,I40,I50,I53,I56) -> 2786041.4 | J22: =SUM(J23,J40,J50,J53,J56) -> 2855692.4 | ... L22: =SUM(L23,L40,L50,L53,L56) -> 3000261.9
A23: 51 | B23: Gastos en personal | C23: =SUM(C24:C39) -> 2165295.4 | D23: =SUM(D24:D39) -> 1713301.6 | E23: =SUM(E24:E39) -> 1677904.9 | F23: =SUM(F24:F39) -> 1962304.9 | G23: =SUM(G24:G39) -> 2097424.3 | H23: =SUM(H24:H39) -> 2049503.3 | I23: =SUM(I24:I39) -> 2100740.9 | J23: =SUM(J24:J39) -> 2153259.4 | ... L23: =SUM(L24:L39) -> 2262268.2
A24: 5.1.01.05 | B24: Remuneraciones Unificadas | C24: 747880.52 | D24: 544874.28 | E24: 592199.5 | F24: 768452.03 | G24: 852272.51 | H24: 839204.25 | I24: =H24*1.025 -> 860184.36 | J24: =I24*1.025 -> 881688.97 | K24: =J24*1.025 -> 903731.19 | L24: =K24*1.025 -> 926324.47
A25: 5.1.01.06 | B25: Salazarios Unificados | C25: 456277.38 | D25: 310149.81 | E25: 289597.25 | F25: 299573.99 | G25: 285234.1 | H25: 272492.22 | I25: =H25*1.025 -> 279304.53 | J25: =I25*1.025 -> 286287.14 | K25: =J25*1.025 -> 293444.32 | L25: =K25*1.025 -> 300780.43
A26: 5.1.02.03 | B26: Décimo tercer sueldo | C26: 126845.23 | D26: 103933.71 | E26: 101155.03 | F26: 110074.82 | G26: 122723.23 | H26: 129560.59 | I26: =H26*1.025 -> 132799.6 | J26: =I26*1.025 -> 136119.59 | K26: =J26*1.025 -> 139522.58 | L26: =K26*1.025 -> 143010.65
A27: 5.1.02.04 | B27: Décimo cuarto sueldo | C27: 65210.24 | D27: 48696.68 | E27: 43370.02 | F27: 50950.38 | G27: 55003.34 | H27: 71441.19 | I27: =H27*1.025 -> 73227.22 | J27: =I27*1.025 -> 75057.9 | K27: =J27*1.025 -> 76934.348 | L27: =K27*1.025 -> 78857.706
A28: 5.1.04.01 | B28: Por Cargas Familiares | C28: 2981.76 | D28: 1795.86 | E28: 1995 | F28: 2066.01 | G28: 1924.95 | H28: 2182.08 | I28: =H28*1.025 -> 2236.632 | J28: =I28*1.025 -> 2292.5478 | K28: =J28*1.025 -> 2349.8615 | L28: =K28*1.025 -> 2408.608
A29: 5.1.04.08 | B29: Subsidio De Antiguedad | C29: 10724.4 | D29: 5730.79 | E29: 4503.24 | F29: 8296.5 | G29: 7108.86 | H29: 6942.24 | I29: =H29*1.025 -> 7115.796 | J29: =I29*1.025 -> 7293.6909 | K29: =J29*1.025 -> 7476.0332 | L29: =K29*1.025 -> 7662.934
A30: 5.1.05.07 | B30: Honorarios | C30: 0 | D30: 6955.73 | E30: 10653.19 | F30: 9113.8 | G30: 5634.91 | H30: 0 | I30: =H30*1.025 -> 0 | J30: =I30*1.025 -> 0 | K30: =J30*1.025 -> 0 | L30: =K30*1.025 -> 0
A31: 5.1.05.09 | B31: Horas Extraordinarias Y Suplementarias | C31: 8048.51 | D31: 11381.86 | E31: 8113.44 | F31: 4977.34 | G31: 6658.32 | H31: 7679.05 | I31: =H31*1.025 -> 7871.0262 | J31: =I31*1.025 -> 8067.8019 | K31: =J31*1.025 -> 8269.497 | L31: =K31*1.025 -> 8476.2344
A32: 5.1.05.10 | B32: Servicios personales por contrato | C32: 297257.53 | D32: 365792.49 | E32: 337975.29 | F32: 287487.04 | G32: 365918.46 | H32: 436762.97 | I32: =H32*1.025 -> 447682.04 | J32: =I32*1.025 -> 458874.1 | K32: =J32*1.025 -> 470345.95 | L32: =K32*1.025 -> 482104.6
A33: 5.1.05.12 | B33: Subrogacion | C33: 3500.52 | D33: 3695.8 | E33: 5586.02 | F33: 4748.28 | G33: 555.67 | H33: 1681.62 | I33: =H33*1.025 -> 1723.6605 | J33: =I33*1.025 -> 1766.752 | K33: =J33*1.025 -> 1810.9208 | L33: =K33*1.025 -> 1856.1938
A34: 5.1.06.01 | B34: Aporte patronal | C34: 185023.35 | D34: 148337.2 | E34: 142720.14 | F34: 171295.01 | G34: 177198.17 | H34: 183028.94 | I34: =H34*1.025 -> 187604.66 | J34: =I34*1.025 -> 192294.78 | K34: =J34*1.025 -> 197102.15 | L34: =K34*1.025 -> 202029.7
A35: 5.1.06.02 | B35: Fondo de reserva | C35: 82164.59 | D35: 79192.49 | E35: 80193.66 | F35: 85302.88 | G35: 71487.11 | H35: 81269.99 | I35: =H35*1.025 -> 83301.74 | J35: =I35*1.025 -> 85384.283 | K35: =J35*1.025 -> 87518.89 | L35: =K35*1.025 -> 89706.863
... A39: 5.1.07.11 | B39: Indemnizaciones Laborales | C39: 160610.76 | D39: 52911.45 | E39: 46168.6 | F39: 15546.78 | G39: 0 | H39: 0 | I39: =H39*1.025 -> 0 | J39: =I39*1.025 -> 0 | K39: =J39*1.025 -> 0 | L39: =K39*1.025 -> 0
A40: 53 | B40: Bienes y servicios de consumo | C40: =SUM(C41:C49) -> 360968.99 | D40: =SUM(D41:D49) -> 271170.83 | E40: =SUM(E41:E49) -> 287599.06 | F40: =SUM(F41:F49) -> 265578.02 | G40: =SUM(G41:G49) -> 296706.27 | H40: =SUM(H41:H49) -> 291358.46 | I40: =SUM(I41:I49) -> 298642.42 | J40: =SUM(J41:J49) -> 306108.48 | ... L40: =SUM(L41:L49) -> 321605.22
A41: 5.3.01 | B41: Servicios Básicos | C41: 62635.16 | D41: 55218.28 | E41: 74825.63 | F41: 62677.8 | G41: 73223.15 | H41: 68926.92 | I41: =H41*1.025 -> 70650.093 | J41: =I41*1.025 -> 72416.345 | K41: =J41*1.025 -> 74226.754 | L41: =K41*1.025 -> 76082.423
A42: 5.3.02 | B42: Servicios Generales | C42: 32852.1 | D42: 60091.74 | E42: 24938.13 | F42: 14097.48 | G42: 18708.03 | H42: 28648.68 | I42: =H42*1.025 -> 29364.897 | J42: =I42*1.025 -> 30099.019 | K42: =J42*1.025 -> 30851.495 | L42: =K42*1.025 -> 31622.782
A43: 5.3.03 | B43: Traslados, Instalaciones, Viáticos y Subsistencias | C43: 13898.33 | D43: 9192.44 | E43: 13988.42 | F43: 13189.28 | G43: 14036.67 | H43: 3692.75 | I43: =H43*1.025 -> 3785.0687 | J43: =I43*1.025 -> 3879.6955 | K43: =J43*1.025 -> 3976.6879 | L43: =K43*1.025 -> 4076.1051
A44: 5.3.04 | B44: Instalación, Mantenimiento y Reparaciones | C44: 17862.26 | D44: 8776.53 | E44: 15052 | F44: 27997.7 | G44: 18933.22 | H44: 33178.08 | I44: =H44*1.025 -> 34007.532 | J44: =I44*1.025 -> 34857.72 | K44: =J44*1.025 -> 35729.163 | L44: =K44*1.025 -> 36622.392
A45: 5.3.05 | B45: Arrendamientos de Bienes | C45: 26.88 | D45: 1209.44 | E45: 2722.88 | F45: 6666.24 | G45: 4898.73 | H45: 7020 | I45: =H45*1.025 -> 7195.5 | J45: =I45*1.025 -> 7375.3875 | K45: =J45*1.025 -> 7559.7722 | L45: =K45*1.025 -> 7748.7665
A46: 5.3.06 | B46: Contratación de Estudios, Investigaciones y Servicios Técnicos Especializados | C46: 37958.4 | D46: 45907.52 | E46: 23799.6 | F46: 18333.6 | G46: 3213.73 | H46: 19195.07 | I46: =H46*1.025 -> 19674.947 | J46: =I46*1.025 -> 20166.82 | K46: =J46*1.025 -> 20670.991 | L46: =K46*1.025 -> 21187.766
A47: 5.3.07 | B47: Gastos en Informática | C47: 18519.76 | D47: 0 | E47: 2223 | F47: 1008 | G47: 1494.53 | H47: 504 | I47: =H47*1.025 -> 516.6 | J47: =I47*1.025 -> 529.515 | K47: =J47*1.025 -> 542.75287 | L47: =K47*1.025 -> 556.3217
A48: 5.3.08 | B48: Bienes de Uso y Consumo Corriente | C48: 175531.13 | D48: 90346.27 | E48: 128245.24 | F48: 120819.99 | G48: 160496.86 | H48: 129159.56 | I48: =H48*1.025 -> 132388.55 | J48: =I48*1.025 -> 135698.26 | K48: =J48*1.025 -> 139090.72 | L48: =K48*1.025 -> 142567.99
A49: 5.3.14 | B49: Bienes Muebles no Depreciables | C49: 1684.97 | D49: 428.61 | E49: 1804.16 | F49: 787.93 | G49: 1701.35 | H49: 1033.4 | I49: =H49*1.025 -> 1059.235 | J49: =I49*1.025 -> 1085.7159 | K49: =J49*1.025 -> 1112.8588 | L49: =K49*1.025 -> 1140.6802
A50: 56 | B50: Gastos Financieros | C50: =SUM(C51:C52) -> 150076.83 | D50: =SUM(D51:D52) -> 187088.75 | E50: =SUM(E51:E52) -> 157087.33 | F50: =SUM(F51:F52) -> 130349.83 | G50: =SUM(G51:G52) -> 374133.75 | H50: =SUM(H51:H52) -> 307164.67 | I50: =SUM(I51:I52) -> 314843.79 | J50: =SUM(J51:J52) -> 322714.88 | ... L50: =SUM(L51:L52) -> 339052.32
A51: 5.6.01 | B51: Títulos y Valores en Circulación | C51: 5481.01 | D51: 9271.69 | E51: 9130.85 | F51: 10600.12 | G51: 28912.7 | H51: 27378.55 | I51: =H51*1.025 -> 28063.014 | J51: =I51*1.025 -> 28764.589 | K51: =J51*1.025 -> 29483.704 | L51: =K51*1.025 -> 30220.796
A52: 5.6.02 | B52: Intereses y Otros Cargos de la Deuda Pública Interna | C52: 144595.82 | D52: 177817.06 | E52: 147956.48 | F52: 119749.71 | G52: 345221.05 | H52: 279786.12 | I52: =H52*1.025 -> 286780.77 | J52: =I52*1.025 -> 293950.29 | K52: =J52*1.025 -> 301299.05 | L52: =K52*1.025 -> 308831.53
A53: 57 | B53: Otros gastos corrientes | C53: =SUM(C54:C55) -> 17922.43 | D53: =SUM(D54:D55) -> 15941.46 | E53: =SUM(E54:E55) -> 23279.3 | F53: =SUM(F54:F55) -> 8022.36 | G53: =SUM(G54:G55) -> 21083.88 | H53: =SUM(H54:H55) -> 4189.55 | I53: =SUM(I54:I55) -> 4294.2887 | J53: =SUM(J54:J55) -> 4401.646 | ... L53: =SUM(L54:L55) -> 4624.4793
A54: 5.7.01 | B54: Impuestos, Tasas y Contribuciones | C54: 1822.49 | D54: 0 | E54: 339.22 | F54: 138.96 | G54: 283.68 | H54: 0 | I54: =H54*1.025 -> 0 | J54: =I54*1.025 -> 0 | K54: =J54*1.025 -> 0 | L54: =K54*1.025 -> 0
A55: 5.7.02 | B55: Seguros, Costos Financieros y Otros Gastos | C55: 16099.94 | D55: 15941.46 | E55: 22940.08 | F55: 7883.4 | G55: 20800.2 | H55: 4189.55 | I55: =H55*1.025 -> 4294.2887 | J55: =I55*1.025 -> 4401.646 | K55: =J55*1.025 -> 4511.6871 | L55: =K55*1.025 -> 4624.4793
A56: 58 | B56: Transferencias y donaciones corrientes | C56: =SUM(C57:C58) -> 80267.49 | D56: =SUM(D57:D58) -> 99147.05 | E56: =SUM(E57:E58) -> 90583.25 | F56: =SUM(F57:F58) -> 92300 | G56: =SUM(G57:G58) -> 146358.37 | H56: =SUM(H57:H58) -> 65873.15 | I56: =SUM(I57:I58) -> 67519.979 | J56: =SUM(J57:J58) -> 69207.978 | ... L56: =SUM(L57:L58) -> 72711.632
A57: 5.8.01 | B57: Transferencias Corrientes al Sector Público | C57: 35026.55 | D57: 99147.05 | E57: 90583.25 | F57: 92300 | G57: 146358.37 | H57: 65873.15 | I57: =H57*1.025 -> 67519.979 | J57: =I57*1.025 -> 69207.978 | K57: =J57*1.025 -> 70938.178 | L57: =K57*1.025 -> 72711.632
A58: 5.8.02 | B58: Donaciones Corrientes al Sector Privado Interno | C58: 45240.94 | D58: 0 | E58: 0 | F58: 0 | G58: 0 | H58: 0 | I58: =H58*1.025 -> 0 | J58: =I58*1.025 -> 0 | K58: =J58*1.025 -> 0 | L58: =K58*1.025 -> 0
A59: SUPERAVIT/DEFICIT CORRIENTE (1) - (2) = (3) | C59: =C8-C22 -> 473399.79 | D59: =D8-D22 -> 559673.52 | E59: =E8-E22 -> -886802.28 | F59: =F8-F22 -> 2274741.5 | G59: =G8-G22 -> 2145525.4 | H59: =H8-H22 -> 3007338.6 | I59: =I8-I22 -> 3082522 | J59: =J8-J22 -> 3159585.1 | ... L59: =L8-L22 -> 3319539.1
A60: INGRESOS DE CAPITAL E INVERSIÓN (4) | C60: =SUM(C61:C62) -> 5422385.8 | D60: =SUM(D61:D62) -> 5594464 | E60: =SUM(E61:E62) -> 4378974 | F60: =SUM(F61:F62) -> 5744722.9 | G60: =SUM(G61:G62) -> 8573457.1 | H60: =SUM(H61:H62) -> 5537922.4 | I60: =SUM(I61:I62) -> 5676370.4 | J60: =SUM(J61:J62) -> 5818279.7 | ... L60: =SUM(L61:L62) -> 6112830.1
A61: 24 | B61: Venta de activos no financieros | C61: 5457.14 | D61: 15707.89 | E61: 12224 | F61: 0 | G61: 4817.39 | H61: 6039.42 | I61: =H61*1.025 -> 6190.4055 | J61: =I61*1.025 -> 6345.1656 | K61: =J61*1.025 -> 6503.7948 | L61: =K61*1.025 -> 6666.3896
A62: 28 | B62: Transferencias y donaciones de capital e inversión | C62: =SUM(C63:C69) -> 5416928.7 | D62: =SUM(D63:D69) -> 5578756.1 | E62: =SUM(E63:E69) -> 4366750 | F62: =SUM(F63:F69) -> 5744722.9 | G62: =SUM(G63:G69) -> 8568639.7 | H62: =SUM(H63:H69) -> 5531883 | I62: =SUM(I63:I69) -> 5670180 | J62: =SUM(J63:J69) -> 5811934.5 | ... L62: =SUM(L63:L69) -> 6106163.7
A63: 2.8.01 | B63: Transferencias de Capital e Inversión del Sector Público | C63: 620520.91 | D63: 338486.76 | E63: 152998.4 | F63: 308870.11 | G63: 398359.3 | H63: 1942393.1 | I63: =H63*1.025 -> 1990952.9 | J63: =I63*1.025 -> 2040726.7 | K63: =J63*1.025 -> 2091744.9 | L63: =K63*1.025 -> 2144038.5
A64: 2.8.02 | B64: Transf o Donaciones de Capital e Inversión del Sector Privado Interno | C64: 15000 | D64: 20000 | E64: 0 | F64: 46867.68 | G64: 1641023.5 | H64: 27933.81 | I64: =H64*1.025 -> 28632.155 | J64: =I64*1.025 -> 29347.959 | K64: =J64*1.025 -> 30081.658 | L64: =K64*1.025 -> 30833.7
A65: 2.8.03 | B65: Donaciones de Capital del Exterior | C65: 0 | D65: 80905 | E65: 0 | F65: 0 | G65: 0 | H65: 0 | I65: =H65*1.025 -> 0 | J65: =I65*1.025 -> 0 | K65: =J65*1.025 -> 0 | L65: =K65*1.025 -> 0
A66: 2.8.04 | B66: Aportes y Participaciones del Sector Público | C66: 2139266.9 | D66: 2636329.3 | E66: 0 | F66: 2520998 | G66: 3379889.1 | H66: 2534303.8 | I66: =H66*1.025 -> 2597661.4 | J66: =I66*1.025 -> 2662603 | K66: =J66*1.025 -> 2729168 | L66: =K66*1.025 -> 2797397.2
A67: 2.8.06 | B67: Aport y Particip de Cap e Inv del Régimen Seccional Autónomo | C67: 2001206.1 | D67: 2110728 | E67: 2147985.5 | F67: 2518988 | G67: 2336437.3 | H67: 203758.37 | I67: =H67*1.025 -> 208852.33 | J67: =I67*1.025 -> 214073.64 | K67: =J67*1.025 -> 219425.48 | L67: =K67*1.025 -> 224911.12
A68: 2.8.09 | B68: Participaciones de Capital del Sector Público en Preasignaciones | C68: 0 | D68: 0 | E68: 1927434.9 | F68: 0 | G68: 0 | H68: 0 | I68: =H68*1.025 -> 0 | J68: =I68*1.025 -> 0 | K68: =J68*1.025 -> 0 | L68: =K68*1.025 -> 0
A69: 2.8.10 | B69: Asignación Presupuestaria de valores equivalentes al (IVA) | C69: 640934.71 | D69: 392307.04 | E69: 138331.24 | F69: 348999.06 | G69: 812930.56 | H69: 823493.85 | I69: =H69*1.025 -> 844081.2 | J69: =I69*1.025 -> 865183.23 | K69: =J69*1.025 -> 886812.81 | L69: =K69*1.025 -> 908983.13
A70: GASTOS DE CAPITAL E INVERSIÓN (5) | C70: =SUM(C71:C71,C88,C99,C103,C107,C110) -> 7545231.2 | D70: =SUM(D71:D71,D88,D99,D103,D107,D110) -> 5472523.1 | E70: =SUM(E71:E71,E88,E99,E103,E107,E110) -> 6182571.3 | F70: =SUM(F71:F71,F88,F99,F103,F107,F110) -> 5654586.3 | G70: =SUM(G71:G71,G88,G99,G103,G107,G110) -> 10021533 | H70: =SUM(H71:H71,H88,H99,H103,H107,H110) -> 10474251 | I70: =SUM(I71:I71,I88,I99,I103,I107,I110) -> 10736108 | J70: =SUM(J71:J71,J88,J99,J103,J107,J110) -> 11004510 | ... L70: =SUM(L71:L71,L88,L99,L103,L107,L110) -> 11561614
A71: 71 | B71: Gastos en personal para Inversión | C71: =SUM(C72:C87) -> 1438579.9 | D71: =SUM(D72:D87) -> 1812384.5 | E71: =SUM(E72:E87) -> 1900239.2 | F71: =SUM(F72:F87) -> 2251496.7 | G71: =SUM(G72:G87) -> 2366349.7 | H71: =SUM(H72:H87) -> 2720354.4 | I71: =SUM(I72:I87) -> 2788363.2 | J71: =SUM(J72:J87) -> 2858072.3 | ... L71: =SUM(L72:L87) -> 3002762.2
A72: 7.1.01.05 | B72: Remuneraciones Básicas | C72: 361479.16 | D72: 165026 | E72: 189447.72 | F72: 480138.16 | G72: 569512.49 | H72: 585648.36 | I72: =H72*1.025 -> 600289.57 | J72: =I72*1.025 -> 615296.81 | K72: =J72*1.025 -> 630679.23 | L72: =K72*1.025 -> 646446.21
A73: 7.1.01.06 | B73: Salarios Unificados | C73: 434426.06 | D73: 501260.94 | E73: 464760.83 | F73: 452097.01 | G73: 387671.79 | H73: 380148.12 | I73: =H73*1.025 -> 389651.82 | J73: =I73*1.025 -> 399393.12 | K73: =J73*1.025 -> 409377.95 | L73: =K73*1.025 -> 419612.4
A74: 7.1.02.03 | B74: Décimo tercer sueldo | C74: 88725.11 | D74: 100163.4 | E74: 103830.38 | F74: 115872.34 | G74: 121305.02 | H74: 137881.9 | I74: =H74*1.025 -> 141328.95 | J74: =I74*1.025 -> 144862.17 | K74: =J74*1.025 -> 148483.73 | L74: =K74*1.025 -> 152195.82
A75: 7.1.02.04 | B75: Décimo cuarto sueldo | C75: 49852.84 | D75: 48387.57 | E75: 54816.6 | F75: 60038.66 | G75: 65447.62 | H75: 78557.91 | I75: =H75*1.025 -> 80521.858 | J75: =I75*1.025 -> 82534.904 | K75: =J75*1.025 -> 84598.277 | L75: =K75*1.025 -> 86713.234
A76: 7.1.04.01 | B76: Por cargas familiares | C76: 3459.84 | D76: 2678.56 | E76: 2550 | F76: 2610 | G76: 2618.26 | H76: 2638.21 | I76: =H76*1.025 -> 2704.1653 | J76: =I76*1.025 -> 2771.7694 | K76: =J76*1.025 -> 2841.0636 | L76: =K76*1.025 -> 2912.0902
A77: 7.1.04.08 | B77: Subsidio de antigüedad | C77: 13771.8 | D77: 18069.51 | E77: 12955.56 | F77: 15960.48 | G77: 10869.96 | H77: 11364.37 | I77: =H77*1.025 -> 11648.479 | J77: =I77*1.025 -> 11939.691 | K77: =J77*1.025 -> 12238.184 | L77: =K77*1.025 -> 12544.138
A78: 7.1.05.09 | B78: Horas Extraordinarias y Suplementarias | C78: 1167.32 | D78: 4623.42 | E78: 4182.12 | F78: 854.75 | G78: 4487.22 | H78: 4600 | I78: =H78*1.025 -> 4715 | J78: =I78*1.025 -> 4832.875 | K78: =J78*1.025 -> 4953.6969 | L78: =K78*1.025 -> 5077.5393
A79: 7.1.05.10 | B79: Servicios personales por contrato | C79: 279239.95 | D79: 548122.5 | E79: 619360.86 | F79: 483110.47 | G79: 487280.9 | H79: 599657.36 | I79: =H79*1.025 -> 614648.79 | J79: =I79*1.025 -> 630015.01 | K79: =J79*1.025 -> 645765.39 | L79: =K79*1.025 -> 661909.52
A80: 7.1.05.12 | B80: Subrogacion | C80: 1259.7 | D80: 2191.43 | E80: 5280.63 | F80: 5582.49 | G80: 2350.54 | H80: 819.37 | I80: =H80*1.025 -> 839.85425 | J80: =I80*1.025 -> 860.85061 | K80: =J80*1.025 -> 882.37187 | L80: =K80*1.025 -> 904.43117
A81: 7.1.06.01 | B81: Aporte patronal | C81: 130150.71 | D81: 138893.71 | E81: 149142.37 | F81: 175510.08 | G81: 169363.38 | H81: 185088.18 | I81: =H81*1.025 -> 189715.38 | J81: =I81*1.025 -> 194458.27 | K81: =J81*1.025 -> 199319.73 | L81: =K81*1.025 -> 204302.72
A82: 7.1.06.02 | B82: Fondo de reserva | C82: 58861.23 | D82: 72317.33 | E82: 70807.57 | F82: 79286.44 | G82: 77716.14 | H82: 83279.48 | I82: =H82*1.025 -> 85361.467 | J82: =I82*1.025 -> 87495.504 | K82: =J82*1.025 -> 89682.891 | L82: =K82*1.025 -> 91924.964
A83: 7.1.07.04 | B83: Compensacion por Desahucio | C83: 0 | D83: 0 | E83: 0 | F83: 0 | G83: 1765.8 | H83: 0 | I83: =H83*1.025 -> 0 | J83: =I83*1.025 -> 0 | K83: =J83*1.025 -> 0 | L83: =K83*1.025 -> 0
... A87: 7.1.07.11 | B87: Indemnizaciones Laborales | C87: 3830.9 | D87: 0 | E87: 0 | F87: 0 | G87: 0 | H87: 116574.44 | I87: =H87*1.025 -> 119488.8 | J87: =I87*1.025 -> 122476.02 | K87: =J87*1.025 -> 125537.92 | L87: =K87*1.025 -> 128676.37
A88: 73 | B88: Bienes y servicios para inversión | C88: =SUM(C89:C98) -> 2049403.8 | D88: =SUM(D89:D98) -> 2441358.1 | E88: =SUM(E89:E98) -> 2050128.4 | F88: =SUM(F89:F98) -> 2144905.7 | G88: =SUM(G89:G98) -> 2342242.8 | H88: =SUM(H89:H98) -> 1590313.7 | I88: =SUM(I89:I98) -> 1630071.5 | J88: =SUM(J89:J98) -> 1670823.3 | ... L88: =SUM(L89:L98) -> 1755408.7
A89: 7.3.01 | B89: Servicios Básicos | C89: 861.18 | D89: 1335.21 | E89: 1584.68 | F89: 3349.95 | G89: 2628.51 | H89: 3984.32 | I89: =H89*1.025 -> 4083.928 | J89: =I89*1.025 -> 4186.0262 | K89: =J89*1.025 -> 4290.6769 | L89: =K89*1.025 -> 4397.9438
A90: 7.3.02 | B90: Servicios Generales | C90: 156131.23 | D90: 278377.98 | E90: 296186.01 | F90: 409998.53 | G90: 403976.75 | H90: 240035.34 | I90: =H90*1.025 -> 246036.22 | J90: =I90*1.025 -> 252187.13 | K90: =J90*1.025 -> 258491.81 | L90: =K90*1.025 -> 264954.1
A91: 7.3.03 | B91: Traslados, Instalaciones, Viáticos y Subsistencias | C91: 14441.84 | D91: 10221.67 | E91: 17114.05 | F91: 7213.23 | G91: 5552.86 | H91: 2163.63 | I91: =H91*1.025 -> 2217.7207 | J91: =I91*1.025 -> 2273.1638 | K91: =J91*1.025 -> 2329.9929 | L91: =K91*1.025 -> 2388.2427
A92: 7.3.04 | B92: Instalaciones, Mantenimientos y Reparaciones | C92: 114530.64 | D92: 161404.34 | E92: 121757.71 | F92: 137099.82 | G92: 174745.9 | H92: 260853 | I92: =H92*1.025 -> 267374.32 | J92: =I92*1.025 -> 274058.68 | K92: =J92*1.025 -> 280910.15 | L92: =K92*1.025 -> 287932.9
A93: 7.3.05 | B93: Arrendamientos de Bienes | C93: 82856.9 | D93: 20571.45 | E93: 44041.06 | F93: 73886.85 | G93: 121197.84 | H93: 33864.4 | I93: =H93*1.025 -> 34711.01 | J93: =I93*1.025 -> 35578.785 | K93: =J93*1.025 -> 36468.255 | L93: =K93*1.025 -> 37379.961
A94: 7.3.06 | B94: Contrataciones de Estudios, Investigaciones y Servicios Técnicos Especializados | C94: 187565.23 | D94: 340821.95 | E94: 351058.74 | F94: 495691.88 | G94: 230092.36 | H94: 403512.29 | I94: =H94*1.025 -> 413600.1 | J94: =I94*1.025 -> 423940.1 | K94: =J94*1.025 -> 434538.6 | L94: =K94*1.025 -> 445402.07
A95: 7.3.07 | B95: Gastos en Informática | C95: 0 | D95: 6612 | E95: 0 | F95: 2996 | G95: 761.6 | H95: 0 | I95: =H95*1.025 -> 0 | J95: =I95*1.025 -> 0 | K95: =J95*1.025 -> 0 | L95: =K95*1.025 -> 0
A96: 7.3.08 | B96: Bienes de Uso y Consumo de Inversión | C96: 1491920.7 | D96: 1618173.3 | E96: 1217256.3 | F96: 1013009.4 | G96: 1402793 | H96: 645714.99 | I96: =H96*1.025 -> 661857.86 | J96: =I96*1.025 -> 678404.31 | K96: =J96*1.025 -> 695364.42 | L96: =K96*1.025 -> 712748.53
A97: 7.3.14 | B97: Bienes Muebles no Depreciables | C97: 1096.05 | D97: 2390.25 | E97: 1129.82 | F97: 1659.97 | G97: 493.97 | H97: 185.7 | I97: =H97*1.025 -> 190.3425 | J97: =I97*1.025 -> 195.10106 | K97: =J97*1.025 -> 199.97859 | L97: =K97*1.025 -> 204.97805
A98: 7.3.15 | B98: Bienes Biológicos no Depreciables | C98: 0 | D98: 1450 | E98: 0 | F98: 0 | G98: 0 | H98: 0 | I98: =H98*1.025 -> 0 | J98: =I98*1.025 -> 0 | K98: =J98*1.025 -> 0 | L98: =K98*1.025 -> 0
A99: 75 | B99: Obras públicas | C99: =SUM(C100:C102) -> 2704477.1 | D99: =SUM(D100:D102) -> 777937.27 | E99: =SUM(E100:E102) -> 1757413 | F99: =SUM(F100:F102) -> 978629.15 | G99: =SUM(G100:G102) -> 4712558.4 | H99: =SUM(H100:H102) -> 5699742.5 | I99: =SUM(I100:I102) -> 5842236.1 | J99: =SUM(J100:J102) -> 5988292 | ... L99: =SUM(L100:L102) -> 6291449.3
A100: 7.5.01 | B100: Obras de Infraestructura | C100: 2579431.2 | D100: 715280.31 | E100: 1671484.6 | F100: 964441.18 | G100: 4460217.4 | H100: 5695082.8 | I100: =H100*1.025 -> 5837459.9 | J100: =I100*1.025 -> 5983396.4 | K100: =J100*1.025 -> 6132981.3 | L100: =K100*1.025 -> 6286305.8
A101: 7.5.04 | B101: Obras en Líneas, Redes e Instalaciones Eléctricas y de Telecomunicaciones | C101: 125045.97 | D101: 5214.78 | E101: 0 | F101: 0 | G101: 131546.46 | H101: 0 | I101: =H101*1.025 -> 0 | J101: =I101*1.025 -> 0 | K101: =J101*1.025 -> 0 | L101: =K101*1.025 -> 0
A102: 7.5.05 | B102: Mantenimiento y Reparaciones | C102: 0 | D102: 57442.18 | E102: 85928.4 | F102: 14187.97 | G102: 120794.55 | H102: 4659.75 | I102: =H102*1.025 -> 4776.2437 | J102: =I102*1.025 -> 4895.6498 | K102: =J102*1.025 -> 5018.0411 | L102: =K102*1.025 -> 5143.4921
A103: 77 | B103: Otros Gastos de Inversión | C103: =SUM(C104:C106) -> 72269.93 | D103: =SUM(D104:D106) -> 61731.27 | E103: =SUM(E104:E106) -> 75599.83 | F103: =SUM(F104:F106) -> 15103.86 | G103: =SUM(G104:G106) -> 62073.19 | H103: =SUM(H104:H106) -> 54299.65 | I103: =SUM(I104:I106) -> 55657.141 | J103: =SUM(J104:J106) -> 57048.57 | ... L103: =SUM(L104:L106) -> 59936.654
A104: 77.01 | B104: Impuestos, Tasas y Contribuciones | C104: 22270.89 | D104: 11046.17 | E104: 4739.97 | F104: 7294.91 | G104: 5069.74 | H104: 2875.21 | I104: =H104*1.025 -> 2947.0902 | J104: =I104*1.025 -> 3020.7675 | K104: =J104*1.025 -> 3096.2867 | L104: =K104*1.025 -> 3173.6939
A105: 77.02 | B105: Seguros, Costos Financieros y Otros Gastos | C105: 49999.04 | D105: 50685.1 | E105: 70174.6 | F105: 6861.43 | G105: 57003.45 | H105: 51424.44 | I105: =H105*1.025 -> 52710.051 | J105: =I105*1.025 -> 54027.802 | K105: =J105*1.025 -> 55378.497 | L105: =K105*1.025 -> 56762.96
A106: 77.03 | B106: Dietas | C106: 0 | D106: 0 | E106: 685.26 | F106: 947.52 | G106: 0 | H106: 0 | I106: =H106*1.025 -> 0 | J106: =I106*1.025 -> 0 | K106: =J106*1.025 -> 0 | L106: =K106*1.025 -> 0
A107: 78 | B107: Transferencias y donaciones para inversión | C107: =SUM(C108:C109) -> 61275.11 | D107: =SUM(D108:D109) -> 62954.01 | E107: =SUM(E108:E109) -> 124322.84 | F107: =SUM(F108:F109) -> 112217.99 | G107: =SUM(G108:G109) -> 183117.3 | H107: =SUM(H108:H109) -> 90433.77 | I107: =SUM(I108:I109) -> 92694.614 | J107: =SUM(J108:J109) -> 95011.98 | ... L107: =SUM(L108:L109) -> 99821.961
A108: 78.01 | B108: Transferencias para Inversión al Sector Público | C108: 24275.11 | D108: 6454.01 | E108: 22322.84 | F108: 13217.99 | G108: 63117.3 | H108: 23433.77 | I108: =H108*1.025 -> 24019.614 | J108: =I108*1.025 -> 24620.105 | K108: =J108*1.025 -> 25235.607 | L108: =K108*1.025 -> 25866.497
...
