Workbook

Sheet FORMULARIO 1
A1: MINISTERIO DE FINANZAS
A2: FORMULARIO 1: "FUENTES DE FINANCIAMIENTO DEL PROYECTO DE CONTRATO COLECTIVO"
A3: DETALLE DE INGRESOS
A5: EMPRESA PUBLICA DE VIALIDAD DEL SUR
A6: Nº PROYECTO CONTRATO COLECTIVO PROYECTO DECIMO NOVENO
A7: Nº ACTA TRANSACCIONAL ___________________________
A9: FUENTES DE FINANCIAMIENTO | C9: FINANCIAMIENTO REAL DEL CONTRATO COLECTIVO VIGENTE USD 2014 | D9: FINANCIAMIENTO REAL DEL CONTRATO COLECTIVO PROPUESTO USD 2015 | E9: FINANCIAMIENTO REAL DEL CONTRATO COLECTIVO PROPUESTO USD 2016 | F9: FINANCIAMIENTO REAL DEL CONTRATO COLECTIVO PROPUESTO USD 2017 | G9: FINANCIAMIENTO REAL DEL CONTRATO COLECTIVO PROPUESTO USD 2018 | H9: FINANCIAMIENTO REAL DEL CONTRATO COLECTIVO PROPUESTO USD 2019 | I9: OBSERVACIONES
A10: INGRESOS CORRIENTES Y PERMANENTES
A11: 11 | B11: POR IMPUESTOS
A12: 1101 | B12: Sobre la Renta, Utilidades y Ganancias de Capital
A13: 1102 | B13: Sobre la propiedad
A14: 1103 | B14: Al consumo de Bienes y Servicios
A15: 1107 | B15: Impuestos Diversos
A17: 13 | B17: TASAS Y CONTRIBUCIONES
A18: 1301 | B18: Tasas generales
A19: 1302 | B19: Tasas portuarias y aeroportuarias
A20: 1303 | B20: Tasas diversas
A21: 1304 | B21: Contribuciones
A23: 14 | B23: VENTA DE BIENES Y SERVICIOS
A25: 17 | B25: RENTAS DE INVERSIONES Y MULTAS
A27: 28 | B27: TRANSFERENCIAS Y DONACIONES CORRIENTES
B28: GOBIERNO PROVINCIAL DE LOJA | C28: ='FORMULARIO 2'!C36 -> 3899938.3 | D28: ='FORMULARIO 2'!D36 -> 4053864.5 | E28: ='FORMULARIO 2'!E36 -> 3751997.6 | F28: ='FORMULARIO 2'!F36 -> 3014753.1 | G28: ='FORMULARIO 2'!G36 -> 3056346 | H28: ='FORMULARIO 2'!H36 -> 3131602.4 | I28: PROGRAMA MANTENIMIENTO Y MEJORAMIENTO VIAL
B29: TOTAL | C29: =C28 -> 3899938.3 | D29: =D28 -> 4053864.5 | E29: =E28 -> 3751997.6 | F29: =F28 -> 3014753.1 | G29: =G28 -> 3056346 | H29: =H28 -> 3131602.4
B30: INCREMENTO PORCENTUAL | D30: =(D29/C29-1)*100 -> 3.9468897 | E30: =(E29/C29-1)*100 -> -3.793409 | F30: =(F29/C29-1)*100 -> -22.697414 | G30: =(G29/C29-1)*100 -> -21.630912 | H30: =(H29/C29-1)*100 -> -19.70123
A32: * De ser el caso, se deberá incluir filas adicionales, para detallar los subgrupos o items correspondientes.
A33: * En caso de que en el contrato colectivo se negocie algún beneficio adicional a los expuestos favor incluir el item correspondiente.
A34: * La información de los formularios deberá remitirse en medio magnético (Excel) e impreso con las respectivas firmas de responsabilidad.
B39: FIRMA DIRECTOR (A) FINANCIERO (A)
B41: Nombre: Ing. Roberto Astudillo Medina
B43: Lugar y Fecha: 26 Noviembre 2019
B44: Sello Institucional

Sheet FORMULARIO 2
A1: FORMULARIO 2: "COSTOS DEL PROYECTO DE CONTRATO COLECTIVO"
A2: EMPRESA PUBLICA DE VIALIDAD DEL SUR
A3: Nº PROYECTO CONTRATO COLECTIVO DECIMO NOVENO
A4: Nº ACTA TRANSACCIONAL ___________________________
A6: CLASIFICADOR PRESUPUESTARIO | B6: GASTO DEL PERSONAL | C6: COSTO REAL DEL CONTRATO COLECTIVO VIGENTE USD 2014 | D6: COSTO REAL DEL CONTRATO COLECTIVO PROPUESTO USD 2015 | E6: COSTO REAL DEL CONTRATO COLECTIVO PROPUESTO USD 2016 | F6: COSTO REAL DEL CONTRATO COLECTIVO PROPUESTO USD 2017 | G6: COSTO REAL DEL CONTRATO COLECTIVO PROPUESTO USD 2018 | H6: COSTO ESTIMADO DEL CONTRATO COLECTIVO PROPUESTO USD 2019 | I6: OBSERVACIONES
A7: GASTO PERSONAL
A8: 7101 | B8: REMUNERACIONES BASICAS
A9: 710106 | B9: SALARIOS UNIFICADOS | C9: 1988598 | D9: 1953895.4 | E9: 1948134.2 | F9: 1906754.9 | G9: 1899780.2 | H9: 1801684 | I9: PROGRAMA MANTENIMIENTO Y MEJORAMIENTO VIAL
A11: 7102 | B11: REMUNERACIONES COMPLEMENTARIAS
A12: 710203 | B12: DECIMOTERCER SUELDO | C12: 165716.5 | D12: 162824.62 | E12: 162344.52 | F12: 158896.24 | G12: 158315.02 | H12: 150140.33
A13: 710204 | B13: DECIMOCUARTO SUELDO | C13: 86020 | D13: 89562 | E13: 90036 | F13: 93375 | G13: 95480 | H13: 97712
A15: 7103 | B15: REMUNERACIONES COMPENSATORIAS
A16: 710304 | B16: COMPENSACION POR TRANSPORTE | C16: 33396 | D16: 33187 | E16: 32472 | F16: 32868 | G16: 32736 | H16: 32736
A17: 710306 | B17: ALIMENTACION | C17: 267168 | D17: 265496 | E17: 259776 | F17: 262944 | G17: 261888 | H17: 261888
A19: 7104 | B19: SUBSIDIOS
A20: 710401 | B20: POR CARGAS FAMILIARES | C20: 8690.4 | D20: 13211 | E20: 13395.6 | F20: 13606.92 | G20: 13305.6 | H20: 11873.4
A21: 710408 | B21: SUBSIDIO POR ANTIGÜEDAD | C21: 19818.72 | D21: 23006.52 | E21: 27226.2 | F21: 32561.529 | G21: 38146.486 | H21: 40515.893
A22: 7105 | B22: REMUNERACIONES TEMPORALES
A23: 710509 | B23: HORAS EXTRAORDINARIAS Y SUPLEMENTARIAS | C23: 0 | D23: 0 | E23: 0
A25: 7106 | B25: APORTES A LA SEGURIDAD SOCIAL
A26: 710601 | B26: APORTE PATRONAL | C26: 240854.31 | D26: 240149.82 | E26: 235850.89 | F26: 239226.21 | G26: 238378.79 | H26: 238575.62
A27: 710602 | B27: FONDO DE RESERVA | C27: 165716.5 | D27: 162824.62 | E27: 162344.52 | F27: 158896.24 | G27: 158315.02 | H27: 150140.33
A28: 710603 | B28: FONDO DE JUBILACION PATRONAL | C28: 39230.65 | D28: 46911.25 | E28: 44318.96 | F28: 11828.942 | G28: 11010.82 | H28: 62506.006
A30: 7107 | B30: INDEMNIZACIONES
A31: 710704 | B31: COMPENSACION POR DESAHUCIO | C31: 0 | D31: 0 | E31: 0
A32: 710705 | B32: POR JUBILACIÓN | C32: 716036.22 | D32: 851819.38 | E32: 736502.9 | F32: 95139.467 | G32: 141430.67 | H32: 258344.61
A33: 730802 | B33: VESTUARIO, LENCERIA Y PRENDAS DE PROTECCION | C33: 168692.95 | D33: 201861.48 | E33: 30940.11 | F33: 0 | G33: 0 | H33: 20776.48
A34: 770201 | B34: SEGUROS | C34: 0 | D34: 9115.38 | E34: 8655.7 | F34: 8655.7 | G34: 7559.4 | H34: 4709.8
B36: TOTAL | C36: =SUM(C8:C35) -> 3899938.3 | D36: =SUM(D9:D35) -> 4053864.5 | E36: =SUM(E8:E35) -> 3751997.6 | F36: =SUM(F9:F35) -> 3014753.1 | G36: =SUM(G9:G35) -> 3056346 | H36: =SUM(H9:H35) -> 3131602.4
D37: =(D36/C36-1)*100 -> 3.9468897 | E37: =(E36/C36-1)*100 -> -3.793409 | F37: =(F36/C36-1)*100 -> -22.697414 | G37: =(G36/C36-1)*100 -> -21.630912 | H37: =(H36/C36-1)*100 -> -19.70123
A38: * De ser el caso, se deberá incluir filas adicionales, para detallar los subgrupos o items correspondientes.
A39: * En caso de que en el contrato colectivo se negocie algún beneficio adicional a los expuestos favor incluir el item correspondiente.
A40: * La información de los formularios deberá remitirse en medio magnético (Excel) e impreso con las respectivas firmas de responsabilidad.
B44: FIRMA DIRECTOR (A) FINANCIERO (A)
B46: Nombre: Ing. Roberto Astudillo Medina
B47: Lugar y Fecha: 26 Noviembre 2019
B48: Sello Institucional

Sheet FORMULARIO 3
A1: MINISTERIO DE FINANZAS
A2: FORMULARIO 3: "COMPARATIVO ENTRE REMUNERACIÓN UNIFICADA Y PROPUESTA"
A3: DISTRIBUTIVO DE SALARIO UNIFICADO DESAGREGADO POR TRABAJADOR
A5: EMPRESA PÚBLICA DE VIALIDAD DEL SUR
A6: Nº PROYECTO CONTRATO COLECTIVO: DECIMO NOVENO
A7: Nº ACTA TRANSACCIONAL ___________________________
F8: 2014 | G8: 2015 | H8: 2016 | I8: 2017 | J8: 2018 | K8: 2019
A9: CEDULA | B9: APELLIDOS Y NOMBRES | C9: No. TRABAJADOR | D9: GRADO DEL CARGO O PUESTO | E9: DENOMINACIÓN DEL PUESTO O CARGO DE OCUPACIÓN | F9: REMUNERACIÓN UNIFICADA 2014 | G9: REMUNERACIÓN UNIFICADA CONTRATO COLECTIVO PROPUESTO USD $ | H9: REMUNERACIÓN UNIFICADA CONTRATO COLECTIVO PROPUESTO USD $ | I9: REMUNERACIÓN UNIFICADA CONTRATO COLECTIVO PROPUESTO USD $ | J9: REMUNERACIÓN UNIFICADA CONTRATO COLECTIVO PROPUESTO USD $ | K9: REMUNERACIÓN UNIFICADA CONTRATO COLECTIVO PROPUESTO USD $ | L9: OBSERVACIONES | M9: FECHA DE INGRESO A VIALSUR E.P.
A10: 1101414793 | B10: ABRIGO DIAZ MARCO ALBERTO | C10: 1 | D10: 1 | E10: GUARDIAN | F10: 565.22 | G10: 565.22 | H10: 565.22 | I10: 565.22 | J10: 565.22 | K10: 565.22 | L10: SOBREVALORADO | M10: 40909
A11: 1101891743 | B11: ABRIGO ORTEGA ANGEL BOLIVAR | C11: 2 | D11: 5 | E11: OPERADOR DE MOTONIVELADORA | F11: 889.33 | G11: 889.33 | H11: 889.33 | I11: 889.33 | J11: 889.33 | K11: 889.33 | L11: SOBREVALORADO | M11: 40909
A12: 1102409362 | B12: AGILA VASQUEZ JOSE ARMANDO | C12: 3 | D12: 1 | E12: AYUDANTE DE EQUIPO Y/O MAQUINARIA PESADA | F12: 565.22 | G12: 565.22 | H12: 565.22 | I12: 565.22 | J12: 565.22 | K12: 565.22 | L12: SOBREVALORADO | M12: 40909
A13: 1102462072 | B13: AGUIRRE GUZMAN JORGE ROLANDO | C13: =+C12+1 -> 4 | D13: 5 | E13: OPERADOR DE MAQUINARIA O EQUIPO PESADO | F13: 733 | G13: 733 | H13: 733 | I13: 733 | J13: 733 | K13: 733 | L13: SOBREVALORADO | M13: 41640
A14: 1104225295 | B14: AGUIRRE PAZ RAMIRO GABRIEL | C14: =+C13+1 -> 5 | D14: 1 | E14: AYUDANTE DE EQUIPO Y/O MAQUINARIA PESADA | F14: 565.22 | G14: 565.22 | H14: 565.22 | I14: 565.22 | J14: 565.22 | K14: 565.22 | L14: SOBREVALORADO | M14: 40909
A15: 1101977617 | B15: AGURTO ERIQUE VICTOR VICENTE | C15: =+C14+1 -> 6 | D15: 4 | E15: CHOFER DE VEHÍCULO PESADO | F15: 615.22 | G15: 615.22 | H15: 615.22 | I15: 615.22 | J15: 615.22 | K15: 615.22 | L15: SOBREVALORADO | M15: 40909
A16: 0101325512 | B16: ALARCON HUGO ANIBAL | C16: =+C15+1 -> 7 | D16: 9 | E16: SUPERVISOR MANTENIMIENTO, EQUIPO PESADO Y AUTOMOTRIZ | F16: 1067.86 | G16: 1067.86 | H16: 1067.86 | I16: 1067.86 | J16: 1067.86 | K16: 1067.86 | L16: SOBREVALORADO | M16: 40909
A17: 1101705117 | B17: ALBERCA ARMIJOS CESARIO AGUSTIN | C17: =+C16+1 -> 8 | D17: 1 | E17: CADENERO | F17: 565.22 | G17: 565.22 | H17: 565.22 | I17: 565.22 | J17: 565.22 | K17: 565.22 | L17: SOBREVALORADO | M17: 40909
A18: 1101740460 | B18: ALVARADO ALVARADO MANUEL IGNACIO | C18: =+C17+1 -> 9 | D18: 5 | E18: OPERADOR DE DISTRIBUIDOR DE AGREGADOS | F18: 733.22 | G18: 733.22 | H18: 733.22 | I18: 733.22 | J18: 733.22 | K18: 733.22 | L18: SOBREVALORADO | M18: 40909
A19: 1102957576 | B19: ALVARADO JARAMILLO JUAN CARLOS | C19: =+C18+1 -> 10 | D19: 1 | E19: GUARDIAN | F19: 565.22 | G19: 565.22 | H19: 565.22 | I19: 565.22 | J19: 565.22 | K19: 565.22 | L19: SOBREVALORADO | M19: 40909
A20: 1100202439 | B20: ALVARADO LEON ELEUTERIO | C20: =+C19+1 -> 11 | D20: 5 | E20: OPERADOR DE EXCAVADORA | F20: 733.22 | G20: 733.22 | H20: 733.22 | I20: 733.22 | J20: 733.22 | K20: 733.22 | L20: SOBREVALORADO | M20: 40909
A21: 1104163082 | B21: ALVAREZ CHAVEZ JUAN PABLO | C21: =+C20+1 -> 12 | D21: 1 | E21: AYUDANTE DE MECÁNICA DE EQUIPO Y/O MAQUINARIA | F21: 565.22 | G21: 565.22 | H21: 565.22 | I21: 565.22 | J21: 565.22 | K21: 565.22 | L21: SOBREVALORADO | M21: 40909
A22: 1102165659 | B22: APOLO PINZA ELSA | C22: =+C21+1 -> 13 | D22: 2 | E22: COCINERO-PROVEEDORA | F22: 581.22 | G22: 581.22 | H22: 581.22 | I22: 581.22 | J22: 581.22 | K22: 581.22 | L22: SOBREVALORADO | M22: 40909
A23: 1703633683 | B23: ARBOLEDA ORDOÑEZ MODESTO LOSTICO | C23: =+C22+1 -> 14 | D23: 1 | E23: DESPACHADOR DE MATERIALES | F23: 565.22 | G23: 565.22 | H23: 565.22 | I23: 565.22 | J23: 565.22 | K23: 0 | L23: RETIRO VOLUNTARIO PARA ACOGERSE A LA JUBILACION 2018. | M23: 40909
A24: 1102863857 | B24: AREVALO SUCUNUTA VICTOR ALFREDO | C24: =+C23+1 -> 15 | D24: 4 | E24: CHOFER DE VEHÍCULO PESADO | F24: 615.22 | G24: 615.22 | H24: 615.22 | I24: 615.22 | J24: 615.22 | K24: 615.22 | L24: SOBREVALORADO | M24: 40909
A25: 1102175229 | B25: AREVALO VALDIVIESO RICHARD SONY | C25: =+C24+1 -> 16 | D25: 1 | E25: AYUDANTE DE MECÁNICA | F25: 565 | G25: 565 | H25: 565 | I25: 565 | J25: 565 | K25: 565 | L25: SOBREVALORADO | M25: 41640
A26: 1103403760 | B26: ARIAS VIVANCO ESTEBAN MANUEL | C26: =+C25+1 -> 17 | D26: 4 | E26: CHOFER DE VEHÍCULO PESADO | F26: 615.22 | G26: 615.22 | H26: 615.22 | I26: 615.22 | J26: 615.22 | K26: 615.22 | L26: SOBREVALORADO | M26: 40909
A27: 1102980826 | B27: ARMIJOS VICENTE ARIELITO | C27: =+C26+1 -> 18 | D27: 1 | E27: AYUDANTE DE EQUIPO Y/O MAQUINARIA PESADA | F27: 615.22 | G27: 0 | H27: 0 | I27: 0 | J27: 0 | K27: 0 | L27: TRASPASO AL GPL EL 01 ENERO 2015 | M27: 40909
A28: 1104398951 | B28: ARMIJOS CABRERA JUNIOR ONOFRE | C28: =+C27+1 -> 19 | D28: 5 | E28: OPERADOR DE EXCAVADORA | F28: 733.22 | G28: 733.22 | H28: 733.22 | I28: 733.22 | J28: 733.22 | K28: 733.22 | L28: SOBREVALORADO | M28: 40909
A29: 0701074031 | B29: ARMIJOS TORO HARALDO ONOFRE | C29: =+C28+1 -> 20 | D29: 4 | E29: CHOFER DE VEHÍCULO PESADO | F29: 615.22 | G29: 615.22 | H29: 615.22 | I29: 615.22 | J29: 615.22 | K29: 615.22 | L29: SOBREVALORADO | M29: 40909
A30: 1804035937 | B30: BALLESTEROS CAIZA ALVARO RENATO | C30: =+C29+1 -> 21 | D30: 2 | E30: VULCANIZADOR | F30: 581.22 | G30: 581.22 | H30: 581.22 | I30: 581.22 | J30: 581.22 | K30: 581.22 | L30: SOBREVALORADO | M30: 40909
A31: 1103015093 | B31: BANEGAS CARAGUAY LORGIO EDLIDER | C31: =+C30+1 -> 22 | D31: 8 | E31: TÉCNICO MANTENIMIENTO AUTOMOTRIZ | F31: 816.22 | G31: 816.22 | H31: 816.22 | I31: 816.22 | J31: 816.22 | K31: 816.22 | L31: SOBREVALORADO | M31: 40909
A32: 1703099513 | B32: BARAJA JOSÉ HOMERO | C32: =+C31+1 -> 23 | D32: 5 | E32: OPERADOR DE EXCAVADORA | F32: 733.22 | G32: 733.22 | H32: 733.22 | I32: 733.22 | J32: 733.22 | K32: 0 | L32: RETIRO VOLUNTARIO PARA ACOGERSE A LA JUBILACION 2018. | M32: 40909
A33: 1100587060 | B33: BARBA GORDILLO ESTEBAN NOE | C33: =+C32+1 -> 24 | D33: 4 | E33: CHOFER DE VEHÍCULO PESADO | F33: 615.22 | G33: 615.22 | H33: 615.22 | I33: 615.22 | J33: 615.22 | K33: 615.22 | L33: SOBREVALORADO | M33: 40909
A34: 1105035883 | B34: BECERRA LOPEZ LUIS MIGUEL | C34: =+C33+1 -> 25 | D34: 1 | E34: AYUDANTE DE EQUIPO Y/O MAQUINARIA PESADA | F34: 565 | G34: 565 | H34: 565 | I34: 565 | J34: 565 | K34: 565 | L34: SOBREVALORADO | M34: 41640
A35: 1900383090 | B35: BECERRA SANCHEZ HECTOR GENARO | C35: =+C34+1 -> 26 | D35: 5 | E35: OPERADOR DE MOTONIVELADORA | F35: 733.22 | G35: 733.22 | H35: 733.22 | I35: 733.22 | J35: 733.22 | K35: 733.22 | L35: SOBREVALORADO | M35: 40909
A36: 1103650055 | B36: BENALCAZAR CASTILLO WILSON PATRICIO | C36: =+C35+1 -> 27 | D36: 6 | E36: TOPÓGRAFO | F36: 615.22 | G36: 615.22 | H36: 709 | I36: 709 | J36: 709 | K36: 709 | L36: SIN NOTA | M36: 40909
A37: 1103812838 | B37: BENITEZ QUEZADA VINICIO LEONARDO | C37: =+C36+1 -> 28 | D37: 4 | E37: CHOFER DE VEHÍCULO PESADO | F37: 615.22 | G37: 615.22 | H37: 615.22 | I37: 615.22 | J37: 615.22 | K37: 615.22 | L37: SOBREVALORADO | M37: 40909
A38: 1103632095 | B38: BERMEO YAGUACHE CARLOS VICENTE | C38: =+C37+1 -> 29 | D38: 1 | E38: GUARDIAN | F38: 565.22 | G38: 565.22 | H38: 565.22 | I38: 565.22 | J38: 565.22 | K38: 565.22 | L38: SOBREVALORADO | M38: 40909
A39: 1104565468 | B39: BRAVO SANMARTIN STALIN ARMANDO | C39: =+C38+1 -> 30 | D39: 1 | E39: AYUDANTE DE MECÁNICA | F39: 565 | G39: 565 | H39: 565 | I39: 565 | J39: 565 | K39: 565 | L39: SOBREVALORADO | M39: 41640
A40: 1102803457 | B40: BRAVO YANANGOMEZ CRISTOBAL FERNANDO | C40: =+C39+1 -> 31 | D40: 1 | E40: AUXILIAR DE LABORATORIO DE SUELOS | F40: 565.22 | G40: 565.22 | H40: 565.22 | I40: 565.22 | J40: 565.22 | K40: 565.22 | L40: SOBREVALORADO | M40: 40909
A41: 1104063274 | B41: BRICEÑO CALVA FREDY WILLAN | C41: =+C40+1 -> 32 | D41: 1 | E41: AYUDANTE DE MECÁNICA | F41: 565 | G41: 565 | H41: 565 | I41: 565 | J41: 565 | K41: 565 | L41: SOBREVALORADO | M41: 41640
... A49: 1104466279 | B49: CARCHI FLORES CARLOS ENRIQUE | C49: =+C48+1 -> 40 | D49: 5 | E49: OPERADOR DE MOTONIVELADORA | F49: 733.22 | G49: 733.22 | H49: 733.22 | I49: 733.22 | J49: 733.22 | K49: 733.22 | L49: SOBREVALORADO | M49: 40909
A50: 0704099712 | B50: SANCHEZ PAUTE CRISTIAN MANUEL | C50: =+C49+1 -> 41 | D50: 5 | E50: OPERADOR DE CARGADORA | F50: 733.22 | G50: 733.22 | H50: 733.22 | I50: 733.22 | J50: 733.22 | K50: 733.22 | L50: SOBREVALORADO | M50: 40909
A51: 1102052071 | B51: CARPIO QUISHPE JOSE MAXIMILIANO | C51: =+C50+1 -> 42 | D51: 1 | E51: CADENERO | F51: 565.22 | G51: 565.22 | H51: 565.22 | I51: 565.22 | J51: 565.22 | K51: 565.22 | L51: SOBREVALORADO | M51: 40909
A52: 1103198501 | B52: CARRERA RODRIGUEZ JOSE MANUEL | C52: =+C51+1 -> 43 | D52: 2 | E52: SOLDADOR | F52: 733.22 | G52: 733.22 | H52: 733.22 | I52: 0 | J52: 0 | K52: 0 | L52: FALLECIMIENTO MARZO DEL 2016.
A53: 1103144984 | B53: CARRION ANGEL MELECIO | C53: =+C52+1 -> 44 | D53: 4 | E53: MAQUINISTA AUXILIAR | F53: 615.22 | G53: 615.22 | H53: 615.22 | I53: 615.22 | J53: 615.22 | K53: 615.22 | L53: SOBREVALORADO | M53: 40909
A54: 1100835873 | B54: CARRION CARRION FRANCISCO ROBERTO | C54: =+C53+1 -> 45 | D54: 5 | E54: OPERADOR DE TRACTOR | F54: 733.22 | G54: 733.22 | H54: 733.22 | I54: 733.22 | J54: 733.22 | K54: 733.22 | L54: SOBREVALORADO | M54: 40909
A55: 1101848859 | B55: CARTUCHE MUNOZ LUIS PATRICIO | C55: =+C54+1 -> 46 | D55: 4 | E55: CHOFER DE VEHÍCULO PESADO | F55: 821.82 | G55: 821.82 | H55: 821.82 | I55: 821.82 | J55: 821.82 | K55: 821.82 | L55: SOBREVALORADO | M55: 40909
A56: 1102240403 | B56: CASTILLO TOLEDO MARCO ALBERTO | C56: =+C55+1 -> 47 | D56: 4 | E56: CHOFER DE VEHÍCULO PESADO | F56: 615.22 | G56: 615.22 | H56: 615.22 | I56: 615.22 | J56: 615.22 | K56: 615.22 | L56: SOBREVALORADO | M56: 40909
A57: 1101984449 | B57: CASTILLO VICENTE BOLIVAR | C57: =+C56+1 -> 48 | D57: 6 | E57: TOPÓGRAFO | F57: 825.31 | G57: 825.31 | H57: 825.31 | I57: 825.31 | J57: 825.31 | K57: 825.31 | L57: SOBREVALORADO | M57: 40909
A58: 1102045687 | B58: CHALAN LIVISACA ANGEL GUILLERMO | C58: =+C57+1 -> 49 | D58: 1 | E58: AYUDANTE DE EQUIPO Y/O MAQUINARIA PESADA | F58: 565.22 | G58: 565.22 | H58: 565.22 | I58: 565.22 | J58: 565.22 | K58: 565.22 | L58: SOBREVALORADO | M58: 40909
A59: 1104277346 | B59: CHAMBA CAÑAR JOSE FABIAN | C59: =+C58+1 -> 50 | D59: 5 | E59: OPERADOR DE CARGADORA | F59: 733.22 | G59: 733.22 | H59: 733.22 | I59: 733.22 | J59: 733.22 | K59: 733.22 | L59: SOBREVALORADO | M59: 40909
A60: 1900408590 | B60: CHAMBA TUQUERES VICTOR IVAN | C60: =+C59+1 -> 51 | D60: 5 | E60: OPERADOR DE CARGADORA | F60: 733.22 | G60: 733.22 | H60: 733.22 | I60: 733.22 | J60: 733.22 | K60: 733.22 | L60: SOBREVALORADO | M60: 40909
A61: 1102745450 | B61: CHAMBA VEINTIMILLA MIGUEL EDUARDO | C61: =+C60+1 -> 52 | D61: 4 | E61: CHOFER DE VEHÍCULO PESADO | F61: 598 | G61: 598 | H61: 598 | I61: 598 | J61: 598 | K61: 598 | L61: SOBREVALORADO | M61: 41640
A62: 0502422785 | B62: CHICAIZA CHILUISA JUAN CARLOS | C62: =+C61+1 -> 53 | D62: 1 | E62: AYUDANTE DE ALBAÑIL | F62: 565 | G62: 565 | H62: 565 | I62: 565 | J62: 565 | K62: 565 | L62: SOBREVALORADO | M62: 41640
A63: 1102438197 | B63: CHUQUIMARCA CHUQUIMARCA MARIA CARMITA | C63: =+C62+1 -> 54 | D63: 2 | E63: COCINERO-PROVEEDORA | F63: 581.22 | G63: 581.22 | H63: 581.22 | I63: 581.22 | J63: 581.22 | K63: 581.22 | L63: SOBREVALORADO | M63: 40909
A64: 1804187456 | B64: CORDOVA PALADINES JUAN CARLOS | C64: =+C63+1 -> 55 | D64: 4 | E64: CHOFER DE VEHÍCULO PESADO | F64: 598 | G64: 598 | H64: 598 | I64: 598 | J64: 598 | K64: 598 | L64: SOBREVALORADO | M64: 41640
A65: 1104411390 | B65: CORDOVA PASACA CRISTIAN AUGUSTO | C65: =+C64+1 -> 56 | D65: 5 | E65: OPERDOR DE CARGADORA | F65: 733.22 | G65: 733.22 | H65: 733.22 | I65: 733.22 | J65: 733.22 | K65: 733.22 | L65: SOBREVALORADO | M65: 40909
A66: 1102017751 | B66: CORDOVA ROMAN ERALDIO AUGUSTO | C66: =+C65+1 -> 57 | D66: 2 | E66: GUARDIAN | F66: 581.22 | G66: 0 | H66: 0 | I66: 0 | J66: 0 | K66: 0 | L66: TRASPASO AL GPL EL 01 ENERO 2015 | M66: 42005
A67: 1102343967 | B67: CORDOVA SOCOLA VICTOR HERNALDO | C67: =+C66+1 -> 58 | D67: 1 | E67: CADENERO | F67: 565.22 | G67: 565.22 | H67: 565.22 | I67: 565.22 | J67: 565.22 | K67: 565.22 | L67: SOBREVALORADO | M67: 40909
A68: 1103143291 | B68: CORONEL CORONEL ANGEL RAMIRO | C68: =+C67+1 -> 59 | D68: 4 | E68: CHOFER DE VEHÍCULO PESADO | F68: 598 | G68: 598 | H68: 598 | I68: 598 | J68: 598 | K68: 598 | L68: SOBREVALORADO | M68: 41640
A69: 1102980339 | B69: CRIOLLO SALINAS EDWIN FABIAN | C69: =+C68+1 -> 60 | D69: 4 | E69: CHOFER DE VEHÍCULO PESADO | F69: 615.22 | G69: 615.22 | H69: 615.22 | I69: 615.22 | J69: 615.22 | K69: 615.22 | L69: SOBREVALORADO | M69: 40909
A70: 1103740831 | B70: CRUZ CUEVA DEYSI ADMIRIAN | C70: =+C69+1 -> 61 | D70: 4 | E70: MAQUINISTA AUXILIAR | F70: 615.22 | G70: 615.22 | H70: 615.22 | I70: 615.22 | J70: 615.22 | K70: 615.22 | L70: SOBREVALORADO | M70: 40909
A71: 1103679427 | B71: CUENCA BAHO HENRRY RAFAEL | C71: =+C70+1 -> 62 | D71: 1 | E71: AYUDANTE DE MECÁNICA DE EQUIPO Y/O MAQUINARIA | F71: 565.22 | G71: 565.22 | H71: 565.22 | I71: 565.22 | J71: 565.22 | K71: 565.22 | L71: SOBREVALORADO | M71: 40909
A72: 1104109333 | B72: CUENCA MINGA JUAN HUMBERTO | C72: =+C71+1 -> 63 | D72: 1 | E72: AYUDANTE DE EQUIPO Y/O MAQUINARIA PESADA | F72: 565.22 | G72: 565.22 | H72: 565.22 | I72: 565.22 | J72: 565.22 | K72: 565.22 | L72: SOBREVALORADO | M72: 40909
A73: 1104018294 | B73: CUENCA TOAPANTA EDGAR EFREN | C73: =+C72+1 -> 64 | D73: 1 | E73: AYUDANTE DE TOPOGRAFÍA | F73: 565.22 | G73: 565.22 | H73: 565.22 | I73: 565.22 | J73: 565.22 | K73: 565.22 | L73: SOBREVALORADO | M73: 40909
A74: 1103069082 | B74: CURIMILMA PAUTE JUAN RAMON | C74: =+C73+1 -> 65 | D74: 1 | E74: AYUDANTE DE CUADRILLA | F74: 565.22 | G74: 565.22 | H74: 565.22 | I74: 565.22 | J74: 565.22 | K74: 565.22 | L74: SOBREVALORADO | M74: 40909
A75: 1103203590 | B75: DELGADO CUENCA ERNESTO AMABLE | C75: =+C74+1 -> 66 | D75: 3 | E75: CHOFER VEHÌCULO LIVIANO | F75: 724.43 | G75: 724.43 | H75: 724.43 | I75: 724.43 | J75: 724.43 | K75: 724.43 | L75: SOBREVALORADO | M75: 40909
A76: 1103055370 | B76: ERAS JIMENEZ ANGEL AUGUSTO | C76: =+C75+1 -> 67 | D76: 5 | E76: OPERADOR DE CARGADORA | F76: 733.22 | G76: 733.22 | H76: 733.22 | I76: 733.22 | J76: 733.22 | K76: 733.22 | L76: SOBREVALORADO | M76: 40909
A77: 1102076518 | B77: ERRAEZ VEINTIMILLA JOSE RICARDO | C77: =+C76+1 -> 68 | D77: 1 | E77: DESPACHADOR DE MATERIALES | F77: 565.22 | G77: 565.22 | H77: 565.22 | I77: 565.22 | J77: 565.22 | K77: 565.22 | L77: SOBREVALORADO | M77: 40909
A78: 1103009930 | B78: ERREYES GUALAN VICTOR ROBER | C78: =+C77+1 -> 69 | D78: 1 | E78: GUARDIAN | F78: 565 | G78: 565 | H78: 565 | I78: 565 | J78: 565 | K78: 565 | L78: SOBREVALORADO | M78: 41640
A79: 1101467023 | B79: ESPARZA SINCHIRI VICTOR HUGO | C79: =+C78+1 -> 70 | D79: 2 | E79: SOLDADOR | F79: 876 | G79: 876 | H79: 876 | I79: 876 | J79: 876 | K79: 876 | L79: SOBREVALORADO | M79: 40909
A80: 1102292974 | B80: ESPINOZA JIMENEZ LUIS EDUARDO | C80: =+C79+1 -> 71 | D80: 4 | E80: CHOFER DE VEHÍCULO PESADO | F80: 615.22 | G80: 615.22 | H80: 615.22 | I80: 615.22 | J80: 615.22 | K80: 615.22 | L80: SOBREVALORADO | M80: 40909
A81: 1103300024 | B81: ESTRELLA SILVA GERMANIA JANETH | C81: =+C80+1 -> 72 | D81: 2 | E81: COCINERO-PROVEEDORA | F81: 581.22 | G81: 581.22 | H81: 581.22 | I81: 581.22 | J81: 0 | K81: 0 | L81: TRASPASO AL GPL EL 01 ENERO 2015 | M81: 40909
A82: 1102698733 | B82: FEBRES ORDONEZ MAX ARTURO | C82: =+C81+1 -> 73 | D82: 1 | E82: DESPACHADOR DE MATERIALES | F82: 624.06 | G82: 624.06 | H82: 624.06 | I82: 624.06 | J82: 624.06 | K82: 624.06 | L82: SOBREVALORADO | M82: 40909
A83: 1101348827 | B83: FERNANDEZ FREIRE DANIEL VICTORIANO | C83: =+C82+1 -> 74 | D83: 6 | E83: INSPECTOR SOBRESTANTE | F83: 766.22 | G83: 766.22 | H83: 766.22 | I83: 766.22 | J83: 766.22 | K83: 766.22 | L83: SOBREVALORADO | M83: 40909
A84: 0701764672 | B84: GALVEZ CHUQUIMARCA LUIS ALFREDO | C84: =+C83+1 -> 75 | D84: 2 | E84: ALBAÑIL | F84: 581.22 | G84: 581.22 | H84: 581.22 | I84: 581.22 | J84: 581.22 | K84: 581.22 | L84: SOBREVALORADO | M84: 40909
A85: 1103617385 | B85: GALVEZ OCHOA MIGUEL ANGEL | C85: =+C84+1 -> 76 | D85: 4 | E85: CHOFER DE VEHÍCULO PESADO | F85: 615.22 | G85: 615.22 | H85: 615.22 | I85: 615.22 | J85: 615.22 | K85: 615.22 | L85: SOBREVALORADO | M85: 40909
A86: 1102125513 | B86: GANAZHAPA PLACENCIA MARIA CONSOLACION | C86: =+C85+1 -> 77 | D86: 2 | E86: COCINERO-PROVEEDORA | F86: 581.22 | G86: 581.22 | H86: 581.22 | I86: 581.22 | J86: 581.22 | K86: 581.22 | L86: SOBREVALORADO | M86: 40909
A87: 1103936900 | B87: GAONA CHAMBA MILTON ESTUARDO | C87: =+C86+1 -> 78 | D87: 1 | E87: AYUDANTE DE EQUIPO Y/O MAQUINARIA PESADA | F87: 565.22 | G87: 565.22 | H87: 565.22 | I87: 565.22 | J87: 565.22 | K87: 565.22 | L87: SOBREVALORADO | M87: 40909
A88: 1500611718 | B88: GAONA JIMENEZ JOSE VICENTE | C88: =+C87+1 -> 79 | D88: 1 | E88: AYUDANTE DE EQUIPO Y/O MAQUINARIA PESADA | F88: 565.22 | G88: 565.22 | H88: 565.22 | I88: 565.22 | J88: 565.22 | K88: 565.22 | L88: SOBREVALORADO | M88: 40909
A89: 1103861496 | B89: GARCIA SALAZAR DIEGO ROBERTO | C89: =+C88+1 -> 80 | D89: 5 | E89: OPERADOR DE MAQUINARIA O EQUIPO PESADO | F89: 733 | G89: 733 | H89: 733 | I89: 733 | J89: 733 | K89: 733 | L89: SOBREVALORADO | M89: 41640
A90: 1104976103 | B90: GIRON LOAIZA JHONATAN ALEXANDER | C90: =+C89+1 -> 81 | D90: 2 | E90: VULCANIZADOR | F90: 581.22 | G90: 581.22 | H90: 581.22 | I90: 581.22 | J90: 581.22 | K90: 581.22 | L90: SOBREVALORADO | M90: 40909
A91: 1100647807 | B91: GONZAGA JARAMILLO CARLOS GERMAN | C91: =+C90+1 -> 82 | D91: 4 | E91: CHOFER DE VEHÍCULO PESADO | F91: 615.22 | G91: 615.22 | H91: 615.22 | I91: 615.22 | J91: 615.22 | K91: 615.22 | L91: SOBREVALORADO | M91: 40909
A92: 1900520618 | B92: GONZALEZ CORREA JULIO CESAR | C92: =+C91+1 -> 83 | D92: 5 | E92: OPERADOR DE MOTONIVELADORA | F92: 733.22 | G92: 733.22 | H92: 733.22 | I92: 733.22 | J92: 733.22 | K92: 733.22 | L92: SOBREVALORADO | M92: 40909
A93: 1102094578 | B93: GORDILLO AREVALO YOLANDA NARCIZA | C93: =+C92+1 -> 84 | D93: 2 | E93: COCINERO-PROVEEDORA | F93: 583.17 | G93: 583.17 | H93: 583.17 | I93: 583.17 | J93: 583.17 | K93: 583.17 | L93: SOBREVALORADO | M93: 40909
A94: 1100415452 | B94: GRANDA INIGUEZ JOSE AUGUSTO | C94: =+C93+1 -> 85 | D94: 2 | E94: VULCANIZADOR | F94: 801.57 | G94: 801.57 | H94: 801.57 | I94: 801.57 | J94: 801.57 | K94: 801.57 | L94: SOBREVALORADO | M94: 40909
A95: 1103304877 | B95: GRANDA PATIÑO FREDY AGUSTIN | C95: =+C94+1 -> 86 | D95: 4 | E95: CHOFER DE VEHÍCULO PESADO | F95: 615.22 | G95: 615.22 | H95: 615.22 | I95: 615.22 | J95: 615.22 | K95: 615.22 | L95: SOBREVALORADO | M95: 40909
A96: 1103420111 | B96: GUAICHA JARAMILLO JULIO CESAR | C96: =+C95+1 -> 87 | D96: 1 | E96: DESPACHADOR DE MATERIALES | F96: 565.22 | G96: 565.22 | H96: 565.22 | I96: 565.22 | J96: 565.22 | K96: 565.22 | L96: SOBREVALORADO | M96: 40909
A97: 1101751210 | B97: GUALAN GUALAN JULIA FERNANDA | C97: =+C96+1 -> 88 | D97: 2 | E97: COCINERO-PROVEEDORA | F97: 811.45 | G97: 811.45 | H97: 811.45 | I97: 811.45 | J97: 811.45 | K97: 0 | L97: RETIRO VOLUNTARIO PARA ACOGERSE A LA JUBILACION 2018.
A98: 1102599949 | B98: GUAMAN ALVARADO ANGEL MODESTO | C98: =+C97+1 -> 89 | D98: 5 | E98: OPERADOR DE RODILLO | F98: 733.22 | G98: 733.22 | H98: 733.22 | I98: 733.22 | J98: 733.22 | K98: 733.22 | L98: SOBREVALORADO | M98: 40909
A99: 1102402094 | B99: GUAMAN CABRERA SEGUNDO EMILIANO | C99: =+C98+1 -> 90 | D99: 4 | E99: MAQUINISTA AUXILIAR | F99: 615.22 | G99: 615.22 | H99: 615.22 | I99: 615.22 | J99: 615.22 | K99: 615.22 | L99: SOBREVALORADO | M99: 40909
A100: 1100794641 | B100: GUAMAN CARLOS WASHINGTON | C100: =+C99+1 -> 91 | D100: 4 | E100: CHOFER DE VEHÍCULO PESADO | F100: 615.22 | G100: 615.22 | H100: 615.22 | I100: 615.22 | J100: 615.22 | K100: 0 | L100: RETIRO VOLUNTARIO PARA ACOGERSE A LA JUBILACION 2018.
A101: 1101075966 | B101: GUAMAN CHAMBA MANUEL ANTONIO | C101: =+C100+1 -> 92 | D101: 5 | E101: OPERADOR DE TRACTOR | F101: 953.46 | G101: 953.46 | H101: 953.46 | I101: 953.46 | J101: 953.46 | K101: 0 | L101: RETIRO VOLUNTARIO PARA ACOGERSE A LA JUBILACION 2018. | M101: 40909
A102: 1101198446 | B102: GUAMAN REYES HERMÁN ANIBAL | C102: =+C101+1 -> 93 | D102: 4 | E102: CHOFER DE VEHÍCULO PESADO | F102: 598 | G102: 598 | H102: 598 | I102: 598 | J102: 598 | K102: 598 | L102: SOBREVALORADO | M102: 41640
A103: 1600132706 | B103: GUARNIZO DELGADO HUGO ANIBAL | C103: =+C102+1 -> 94 | D103: 4 | E103: CHOFER DE VEHÍCULO PESADO | F103: 939.95 | G103: 939.95 | H103: 939.95 | I103: 0 | J103: 0 | K103: 0 | L103: VISTO BUENO 2016.
A104: 1101704078 | B104: GUERRERO ABAD JOSE EDILBERTO | C104: =+C103+1 -> 95 | D104: 5 | E104: OPERDOR DE TRACTOR | F104: 876 | G104: 876 | H104: 876 | I104: 876 | J104: 876 | K104: 876 | L104: SOBREVALORADO | M104: 40909
A105: 1103606222 | B105: GUERRERO BERMEO HENRY STALIN | C105: =+C104+1 -> 96 | D105: 1 | E105: AYUDANTE DE MECÁNICA DE EQUIPO Y/O MAQUINARIA | F105: 565.22 | G105: 565.22 | H105: 565.22 | I105: 565.22 | J105: 565.22 | K105: 565.22 | L105: SOBREVALORADO | M105: 40909
A106: 1103270649 | B106: GUERRERO CAMPOS ROBERTO FERNANDO | C106: =+C105+1 -> 97 | D106: 1 | E106: AYUDANTE DE EQUIPO Y/O MAQUINARIA PESADA | F106: 565.22 | G106: 565.22 | H106: 565.22 | I106: 565.22 | J106: 565.22 | K106: 565.22 | L106: SOBREVALORADO | M106: 40909
A107: 1102562111 | B107: GUERRERO PILCO OSCAR WALTER | C107: =+C106+1 -> 98 | D107: 5 | E107: OPERADOR DE TRACTOR | F107: 876 | G107: 876 | H107: 876 | I107: 876 | J107: 876 | K107: 876 | L107: SOBREVALORADO | M107: 40909
A108: 1100417292 | B108: GUERRERO PILCO PEDRO VITALIANO | C108: =+C107+1 -> 99 | D108: 6 | E108: INSPECTOR SOBRESTANTE | F108: 953.03 | G108: 953.03 | H108: 953.03 | I108: 953.03 | J108: 953.03 | K108: 953.03 | L108: SOBREVALORADO | M108: 40909
...

Sheet FORMULARIO 4.
A1: FORMULARIO 4
A2: FLUJO PRESUPUESTARIO DE INGRESOS Y GASTOS
A3: EMPRESA PÚBLICA DE VIALIDAD DEL SUR
A5: DETALLE DE GRUPOS Y SUBGRUPOS | C5: FLUJO HISTÓRICO (USD) | F5: FLUJO PROYECTADO (USD) | J5: OBSERVACIONES
A7: Grupo y Subgrupo | B7: Descripción | C7: 2015 | D7: 2016 | E7: 2017 | F7: AÑO (2018) | G7: AÑO 1 (2019) | H7: AÑO 2 (2020) | I7: AÑO 3 (2021)
A8: TOTAL INGRESOS CORRIENTES (1) | C8: =+C9+C14+C19+C20+C21+C22 -> 96363.44 | D8: =+D9+D14+D19+D20+D21+D22 -> 40401.32 | E8: =+E9+E14+E19+E20+E21+E22 -> 2878494.6 | F8: =+F9+F14+F19+F20+F21+F22 -> 3159453.3 | G8: =+G9+G14+G19+G20+G21+G22 -> 728391.16 | H8: =+H9+H14+H19+H20+H21+H22 -> 89063.676 | I8: =+I9+I14+I19+I20+I21+I22 -> 89954.312
A9: 11 | B9: Impuestos
A10: 1101 | B10: Sobre la Renta, Utilidades y Ganancias de Capital
A11: 1102 | B11: Sobre la propiedad
A12: 1103 | B12: Al consumo de Bienes y Servicios
A13: 1107 | B13: Impuestos Diversos
A14: 13 | B14: Tasas y contribuciones | C14: =SUM(C15:C18) -> 2300 | D14: =SUM(D15:D18) -> 2100 | E14: =SUM(E15:E18) -> 2050 | F14: =SUM(F15:F18) -> 4758 | G14: =SUM(G15:G18) -> 2415.43 | H14: =SUM(H15:H18) -> 2451.6614 | I14: 2476.1781
A15: 1301 | B15: Tasas generales | C15: 2300 | D15: 2100 | E15: 2050 | F15: 4758 | G15: 2415.43 | H15: 2451.6614 | I15: 2476.1781
A16: 1302 | B16: Tasas portuarias y aeroportuarias | H16: 0 | I16: 0
A17: 1303 | B17: Tasas diversas | H17: 0 | I17: 0
A18: 1304 | B18: Contribuciones | H18: 0 | I18: 0
A19: 14 | B19: Venta de Bienes y Servicios | E19: 2855303.1 | F19: 3010466.2 | G19: 689904.78 | H19: 50000 | I19: 50500
A20: 17 | B20: Rentas de Invesiones y Multas | C20: 1696.9 | D20: 4332.27 | E20: 1225.8 | F20: 11010.78 | G20: 14811.08 | H20: 15033.246 | I20: 15183.579
A21: 18 | B21: Transferencias y Donaciones Corrientes
A22: 19 | B22: Otros ingresos | C22: =SUM(C23:C25) -> 92366.54 | D22: =SUM(D23:D25) -> 33969.05 | E22: =SUM(E23:E25) -> 19915.75 | F22: =SUM(F23:F25) -> 133218.34 | G22: 21259.87 | H22: 21578.768 | I22: 21794.556
A23: 1901 | B23: Garantías y Fianzas | I23: 0
A24: 1902 | B24: Indemnizaciones y valores no reclamados | C24: 61492.62 | D24: 5070.34 | E24: 0 | F24: 85756.77 | G24: 0 | H24: 0 | I24: 0
A25: 1904 | B25: Otros no Operacionales | C25: 30873.92 | D25: 28898.71 | E25: 19915.75 | F25: 47461.57 | G25: 21259.87 | H25: 21578.768 | I25: 21794.556
A26: TOTAL GASTOS CORRIENTES (2) | C26: =+C27+C36+C37+C38+C39+C40 -> 31020 | D26: =+D27+D36+D37+D38+D39+D40 -> 33951.76 | E26: =+E27+E36+E37+E38+E39+E40 -> 11748.84 | F26: =+F27+F36+F37+F38+F39+F40 -> 75173.68 | G26: =+G27+G36+G37+G38+G39+G40 -> 3019.31 | H26: 2547.8023 | I26: 2573.2803
A27: 51 | B27: Gastos en personal | H27: 0 | I27: 0
A28: 5101 | B28: Remuneraciones Básicas | H28: 0 | I28: 0
A29: 5102 | B29: Remuneraciones Complementarias | H29: 0 | I29: 0
A30: 5103 | B30: Remuneraciones Compensatorias | H30: 0 | I30: 0
A31: 5104 | B31: Subsidios | H31: 0 | I31: 0
A32: 5105 | B32: Remuneraciones Temporales | H32: 0 | I32: 0
A33: 5106 | B33: Aportes Patronales a la Seguridad Social | H33: 0 | I33: 0
A34: 5107 | B34: Indemnizaciones | H34: 0 | I34: 0
A35: 5199 | B35: Asignaciones a distribuir | H35: 0 | I35: 0
A36: 53 | B36: Bienes y servicios de consumo | H36: 0 | I36: 0
A37: 56 | B37: Gastos Financieros | H37: 0 | I37: 0
A38: 57 | B38: Otros gastos corrientes | F38: 71658.66 | H38: 0 | I38: 0
A39: 58 | B39: Transferencias y donaciones corrientes | C39: 31020 | D39: 33951.76 | E39: 11748.84 | F39: 3515.02 | G39: 3019.31 | H39: 12219.84 | I39: 12342.038
A40: 59 | B40: Previsiones para reasignaciones | K40: =+H40*1/100 -> 0
A41: SUPERAVIT/DEFICIT CORRIENTE (1) - (2) = (3) | C41: =+C8-C26 -> 65343.44 | D41: =+D8-D26 -> 6449.56 | E41: =+E8-E26 -> 2866745.8 | F41: =+F8-F26 -> 3084279.7 | G41: =+G8-G26 -> 725371.85 | H41: =+H8-H26 -> 86515.873 | I41: =+I8-I26 -> 87381.032
A42: INGRESOS DE CAPITAL E INVERSIÓN (4) | C42: =+C44 -> 7425936.1 | D42: =SUM(D43:D44) -> 10247254 | E42: =SUM(E43:E44) -> 7130371.3 | F42: =SUM(F43:F44) -> 8097694.1 | G42: =SUM(G43:G44) -> 6927446.8 | H42: =SUM(H43:H44) -> 6325710.7 | I42: =SUM(I43:I44) -> 6388967.8
A43: 24 | B43: Venta de activos no financieros | D43: 123176.55
A44: 28 | B44: Transferencias y donaciones de capital e inversión | C44: =7381304.34+9793.24+34838.51 -> 7425936.1 | D44: 10124077 | E44: 7130371.3 | F44: 8097694.1 | G44: 6927446.8 | H44: 6325710.7 | I44: 6388967.8
A45: GASTOS DE CAPITAL E INVERSIÓN (5) | C45: =+C49+C58+C59+C66+C68 -> 8052389.3 | D45: =+D49+D58+D59+D66+D68 -> 8101471.6 | E45: =+E49+E58+E59+E66+E68 -> 10566462 | F45: =+F49+F58+F59+F66+F68 -> 10898826 | G45: =+G49+G58+G59+G66+G68 -> 6927446.8 | H45: =+H49+H58+H59+H66+H68 -> 6291577.6 | I45: 6354493.4
A46: 61 | B46: Gastos en personal para producción | I46: 0
A47: 63 | B47: Bienes y servicios para producción | I47: 0
A48: 67 | B48: Otros gastos de producción | I48: 0
A49: 71 | B49: Gastos en personal para Inversión | C49: =SUM(C50:C56) -> 4889679.9 | D49: =SUM(D50:D56) -> 4409022 | E49: =SUM(E50:E56) -> 4509078.1 | F49: =SUM(F50:F56) -> 4619076.7 | G49: =SUM(G50:G56) -> 5241406 | H49: =SUM(H50:H56) -> 4801174.7 | I49: 4849186.5
A50: 7101 | B50: Remuneraciones Básicas | C50: 2341830.5 | D50: 2359670.2 | E50: 2472831.3 | F50: 2510998.8 | G50: 2761957.3 | H50: 2580486.4 | I50: 2606291.2
A51: 7102 | B51: Remuneraciones Complementarias | C51: 460752.72 | D51: 372884.28 | E51: 402354.39 | F51: 403552.13 | G51: 431628.28 | H51: 377127.53 | I51: 380898.81
A52: 7103 | B52: Remuneraciones Compensatorias | C52: 271586.9 | D52: 285985.5 | E52: 258505.52 | F52: 242518.5 | G52: 294624 | H52: 274428 | I52: 277172.28
A53: 7104 | B53: Subsidios | C53: 25809.61 | D53: 55790.16 | E53: 43818.87 | F53: 47279.72 | G53: 52389.29 | H53: 48388.22 | I53: 48872.102
A54: 7105 | B54: Remuneraciones Temporales | C54: 1071893.1 | D54: 655757.04 | E54: 667919.63 | F54: 652585.01 | G54: 600695 | H54: 359820 | I54: 363418.2
A55: 7106 | B55: Aportes Patronales a la Seguridad Social | C55: 633374.64 | D55: 591846.64 | E55: 615279.94 | F55: 626262.54 | G55: 681675.86 | H55: 596529.22 | I55: 602494.51
A56: 7107 | B56: Indemnizaciones | C56: 84432.41 | D56: 87088.15 | E56: 48368.5 | F56: 135880.04 | G56: 418436.29 | H56: 564395.39 | I56: 570039.34
A57: 7199 | B57: Asignaciones a distribuir | I57: 0
A58: 73 | B58: Bienes y servicios para inversión | C58: 2116076.3 | D58: 3164798.3 | E58: 5609480.2 | F58: 4785743.6 | G58: 1492691.6 | H58: 1336241 | I58: 1349603.4
A59: 75 | B59: Obras públicas | C59: =+C60 -> 645409.84 | D59: =+D60 -> 216577.61 | E59: =+E60 -> 159572.84 | F59: =+F60 -> 1265077.8 | G59: 0 | H59: 0 | I59: 0
A60: 7501 | B60: Obras de Infraestructura | C60: 645409.84 | D60: 216577.61 | E60: 159572.84 | F60: 1265077.8 | G60: 0 | H60: 0 | I60: 0
A61: 7502 | B61: Obras para generación de energía | H61: 0 | I61: 0
A62: 7503 | B62: Obras Hidrocarburíferas y Mineras | H62: 0 | I62: 0
A63: 7504 | B63: Obras en líneas, redes, e intalaciones eléctricas y de telecomunicaciones | H63: 0 | I63: 0
A64: 7505 | B64: Mantenimiento y repaciones | H64: 0 | I64: 0
A65: 7599 | B65: Asignaciones a distribuir | H65: 0 | I65: 0
A66: 77 | B66: Otros Gastos de Inversión | C66: 262664.44 | D66: 280514.6 | E66: 236140.96 | F66: 197269.45 | G66: 186949.15 | H66: 147161.86 | I66: 148633.48
A67: 78 | B67: Transferencias y donaciones para inversión | H67: 0 | I67: 0
A68: 84 | B68: Bienes de larga duración | C68: 138558.89 | D68: 30559.12 | E68: 52189.66 | F68: 31658.02 | G68: 6400 | H68: 7000 | I68: 7070
A69: 88 | B69: Transferencias y donaciones de capital | I69: 0
A70: SUPERAVIT/DEFICIT DE CAPITAL E INVERSIÓN (4) - (5) = (6) | C70: =+C42-C45 -> -626453.23 | D70: =+D42-D45 -> 2145782 | E70: =+E42-E45 -> -3436090.5 | F70: =+F42-F45 -> -2801131.5 | G70: =+G42-G45 -> 0.00088456552 | H70: =+H42-H45 -> 34133.1 | I70: 34474.431
A71: SUPERAVIT/DEFICIT FISCAL (3) + (6) | C71: =+C41+C70 -> -561109.79 | D71: =+D41+D70 -> 2152231.6 | E71: =+E41+E70 -> -569344.7 | F71: =+F41+F70 -> 283148.14 | G71: =+G41+G70 -> 725371.85 | H71: =+H41+H70 -> 120648.97 | I71: 121855.46
A72: FUENTES FINANCIERAS (7) | C72: =SUM(C73:C76) -> 2548941.7 | D72: =SUM(D73:D76) -> 1640068.7 | E72: =SUM(E73:E76) -> 3321633.5 | F72: =SUM(F73:F76) -> 1722584.3 | G72: =SUM(G73:G76) -> 587246.65 | H72: =SUM(H73:H76) -> 596055.35 | I72: 602015.9
A73: 27 | B73: Recuperación de inversiones
A74: 36 | B74: Financiamiento Público
A75: 37 | B75: Saldos disponibles | C75: 2487823.2 | D75: 656168.35 | E75: 2065394.2 | F75: 417194.84 | G75: 255805.55 | H75: =+G75*1.5/100+G75 -> 259642.63 | I75: 262239.06
A76: 38 | B76: Cuenta Pendientes por Cobrar | C76: 61118.51 | D76: 983900.37 | E76: =593367.18+662872.12 -> 1256239.3 | F76: =190774.27+1114615.17 -> 1305389.4 | G76: 331441.1 | H76: =+G76*1.5/100+G76 -> 336412.72 | I76: 339776.84
A77: USOS FINANCIEROS (8) | F77: =+F80 -> 1162793.1 | G77: =+G80 -> 78266.97 | H77: =+H80 -> 0 | I77: =+I80 -> 0
A78: 87 | B78: Inversiones financieras
A79: 96 | B79: Amortización de la deuda
A80: 97 | B80: Pasivo Circulante | F80: 1162793.1 | G80: 78266.97 | H80: 0 | I80: 0
A81: 99 | B81: Otros Pasivos
A82: SUPERAVIT/DEFICIT DE FINANCIAMIENTO (7) - (8) | C82: =+C72-C77 -> 2548941.7 | D82: =+D72-D77 -> 1640068.7 | E82: =+E72-E77 -> 3321633.5 | F82: =+F72-F77 -> 559791.19 | G82: =+G72-G77 -> 508979.68 | H82: =+H72-H77 -> 596055.35 | I82: =+I72-I77 -> 602015.9
A85: CÁLCULO DE LÍMITES DE ENDEUDAMIENTO
A86: NO HAY COMO CALCULAR LIMITE DE ENDEUDAMIENTO POR CUENTO LA EMPRESA NO CUENTA CON DEUDA PUBLICA.
A87: NOTA: LA VARIACIÓN EN LOS INGRESOS EN LOS AÑOS 2017, 2018 Y 2019 ES POR AUTOGESTIÓN DE LA EMPRESA LA CUAL MANTUVO UN CONTRATO PARA REALIZAR UNA VÍA.
A89: * Se requiere detallar claramente qué partida o partidas presupuestarias de ingresos y gastos sustentaran el egreso del contrato colectivo o acta transaccional (Si es necesario desglosando los datos en filas adicionales a nivel de item)
A90: *La información histórica presentada en este anexo deberá corresponder a la que el GAD cargó a través del Módulo de Consolidación del E-sigef del Ministerio de Finanzas.
A91: * Se requiere incluir el cálculo de los límites de endeudamiento establecidos en el artículo 125 del Código Orgánico de Planificación y Finanzas Públicas - COPLAFIP y el artículo 136 al Reglamento al COPLAFIP.
A92: * La información de los formularios deberá remitirse en medio magnético (Excel) e impreso con las respectivas firmas de responsabilidad.
A98: FIRMA AUTORIDAD | E98: FIRMA DIRECTOR (A) FINANCIERO (A)
A99: Nombre: | B99: Ing. Jean Villavicencio Garcia | E99: Nombre: Ing. Roberto Astudillo
A101: Lugar y Fecha: Loja, 26 Noviemrbe 2019
A102: Sello Institucional
