Workbook

Sheet FORMULARIO 1
A1: MINISTERIO DE FINANZAS
A2: FORMULARIO 1: "FUENTES DE FINANCIAMIENTO DEL PROYECTO DE CONTRATO COLECTIVO"
A3: DETALLE DE INGRESOS
A5: GOBIERNO AUTÓNOMO DESCENTRALIZADO MUNICIPAL DE CATAMAYO
A6: Nº PROYECTO CONTRATO COLECTIVO: DÉCIMO SEGUNDO
A7: Nº ACTA TRANSACCIONAL ___________________________
A9: FUENTES DE FINANCIAMIENTO | C9: FINANCIAMIENTO REAL DEL CONTRATO COLECTIVO VIGENTE USD (2015) | D9: FINANCIAMIENTO ESTIMADO DEL CONTRATO COLECTIVO PROPUESTO USD (2016) | E9: OBSERVACIONES
A10: INGRESOS CORRIENTES Y PERMANENTES
A11: 11 | B11: POR IMPUESTOS
A12: 1101 | B12: Sobre la Renta, Utilidades y Ganancias de Capital
A13: 1102 | B13: Sobre la propiedad
A14: 1103 | B14: Al consumo de Bienes y Servicios
A15: 1107 | B15: Impuestos Diversos
A17: 13 | B17: TASAS Y CONTRIBUCIONES
A18: 1301 | B18: Tasas generales
A19: 1302 | B19: Tasas portuarias y aeroportuarias
A20: 1303 | B20: Tasas diversas
A21: 1304 | B21: Contribuciones
A23: 14 | B23: VENTA DE BIENES Y SERVICIOS
A25: 17 | B25: RENTAS DE INVERSIONES Y MULTAS
A27: 18 | B27: TRANSFERENCIAS Y DONACIONES CORRIENTES
B28: COOTAD
A29: 19 | B29: OTROS INGRESOS
A30: 1901 | B30: Garantías y Fianzas
A31: 1902 | B31: Indemnizaciones y valores no reclamados
A32: 1904 | B32: Otros no Operacionales
A33: 28 | B33: INGRESOS DE CAPITAL E INVERSIÓN (4)
A34: 2806 | B34: Transferencias y donaciones de capital e inversión | C34: ='FORMULARIO 2'!C40 -> 1995934.9 | D34: ='FORMULARIO 2'!D40 -> 2260664.8
B35: TOTAL | C35: =C34 -> 1995934.9 | D35: =D34 -> 2260664.8
B36: INCREMENTO PORCENTUAL % | D36: =SUM(D35-C35)/C35*100 -> 13.263457
A38: * De ser el caso, se deberá incluir filas adicionales, para detallar los subgrupos o items correspondientes.
A39: * En caso de que en el contrato colectivo se negocie algún beneficio adicional a los expuestos favor incluir el item correspondiente.
A40: * La información de los formularios deberá remitirse en medio magnético (Excel) e impreso con las respectivas firmas de responsabilidad.
B45: FIRMA DIRECTOR (A) FINANCIERO (A) DEL GAD
B46: Dr. C.P.A. Julio Farinango Benalcázar
B48: Lugar y Fecha: Catamayo, 01/12/2016
B49: Sello Institucional

Sheet FORMULARIO 2
A1: MINISTERIO DE FINANZAS
A2: FORMULARIO 2: "COSTOS DEL PROYECTO DE CONTRATO COLECTIVO"
A4: GOBIERNO AUTÓNOMO DESCENTRALIZADO MUNICIPAL DE CATAMAYO
A5: Nº PROYECTO CONTRATO COLECTIVO: DÉCIMO SEGUNDO
A6: Nº ACTA TRANSACCIONAL ___________________________
A8: CLASIFICADOR PRESUPUESTARIO | B8: GASTO DEL PERSONAL | C8: COSTO REAL DEL CONTRATO COLECTIVO VIGENTE USD (2015) | D8: COSTO ESTIMADO DEL CONTRATO COLECTIVO PROPUESTO USD (2016) | E8: OBSERVACIONES
A9: GASTO PERSONAL
A10: 7101 | B10: REMUNERACIONES BASICAS
A11: 710106 | B11: SALARIOS UNIFICADOS | C11: =(100514)*12 -> 1206168 | D11: ='FORMULARIO 3'!G185*12 -> 1226760
A13: 7102 | B13: REMUNERACIONES COMPLEMENTARIAS
A14: 710203 | B14: DECIMOTERCER SUELDO | C14: =144255.99 -> 144255.99 | D14: ='FORMULARIO 3'!G185 -> 102230
A15: 710204 | B15: DECIMOCUARTO SUELDO | C15: =66966.5 -> 66966.5 | D15: =174*366 -> 63684
A17: 7103 | B17: REMUNERACIONES COMPENSATORIAS
A18: 710304 | B18: COMPENSACION POR TRANSPORTE | C18: =23232 -> 23232 | D18: =22968 -> 22968 | E18: 174 trabajadores
A19: 710306 | B19: ALIMENTACION | C19: =139392 -> 139392 | D19: =183744 -> 183744 | E19: 174 trabajadores
A20: 710307 | B20: COMISARIATO | C20: 0 | D20: 0
A22: 7104 | B22: SUBSIDIOS
A23: 710401 | B23: POR CARGAS FAMILIARES | C23: =102.66 -> 102.66 | D23: =(10.62*12) -> 127.44
A25: 7105 | B25: REMUNERACIONES TEMPORALES
A26: 710509 | B26: HORAS EXTRAORDINARIAS Y SUPLEMENTARIAS | C26: =(10026.96+12790.16+13122.45+10123.66+13608.86+10728.94+11487.59+13784.5+10493.81+13113.98+8428.74+8934.64) -> 136644.29 | D26: =C26*10%+C26 -> 150308.72
A28: 7106 | B28: APORTES A LA SEGURIDAD SOCIAL
A29: 710601 | B29: APORTE PATRONAL | C29: =C11*12.15% -> 146549.41 | D29: =D11*12.15% -> 149051.34
A30: 710602 | B30: FONDO DE RESERVA | C30: =C11/12 -> 100514 | D30: =D11/12 -> 102230
A31: 710603 | B31: FONDO DE JUBILACION PATRONAL | C31: 0 | D31: 0
A33: 7107 | B33: INDEMNIZACIONES
A34: 710704 | B34: COMPENSACION POR DESAHUCIO | C34: 0 | D34: 0
A35: 710705 | B35: POR JUBILACIÓN | C35: 0 | D35: 230155.31
A37: 7308 | B37: BIENES DE USO Y CONUSMO DE INVERSIÓN
A38: 730802 | B38: VESTUARIO, LENCERÍA Y PRENDAS DE PROTECCIÓN | C38: =190*169 -> 32110 | D38: =174*169 -> 29406 | E38: 174 trabajadores
B40: TOTAL | C40: =SUM(C10:C39) -> 1995934.9 | D40: =SUM(D10:D39) -> 2260664.8
B41: INCREMENTO PORCENTUAL % | D41: =SUM(D40-C40)/C40*100 -> 13.263457
A42: NOTA: | B42: Las partidas de inversión corresponden al PROGRAMA OTROS SERVICIOS COMUNALES
A43: * De ser el caso, se deberá incluir filas adicionales, para detallar los subgrupos o items correspondientes.
A44: * En caso de que en el contrato colectivo se negocie algún beneficio adicional a los expuestos favor incluir el item correspondiente.
A45: * La información de los formularios deberá remitirse en medio magnético (Excel) e impreso con las respectivas firmas de responsabilidad.
B50: FIRMA DIRECTOR (A) FINANCIERO (A) DEL GAD
B51: Dr. C.P.A. Julio Farinango Benalcázar
B53: Lugar y Fecha: Catamayo, 01/12/2016
B54: Sello Institucional
E79: ='FORMULARIO 2'!C185 -> 0

Sheet FORMULARIO 3
A1: MINISTERIO DE FINANZAS
A2: FORMULARIO 3: "COMPARATIVO ENTRE REMUNERACIÓN UNIFICADA Y PROPUESTA"
A3: DISTRIBUTIVO DE SALARIO UNIFICADO DESAGREGADO POR TRABAJADOR
A5: GOBIERNO AUTÓNOMO DESCENTRALIZADO MUNICIPAL DE CATAMAYO
A6: Nº PROYECTO CONTRATO COLECTIVO: DÉCIMO SEGUNDO
A7: Nº ACTA TRANSACCIONAL ___________________________
A9: CEDULA | B9: APELLIDOS Y NOMBRES | C9: No. TRABAJADOR | D9: GRADO DEL CARGO O PUESTO | E9: DENOMINACIÓN DEL PUESTO O CARGO DE OCUPACIÓN | F9: REMUNERACIÓN UNIFICADA CONTRATO COLECTIVO VIGENTE USD (2015) | G9: REMUNERACIÓN UNIFICADA 2016 CONTRATO COLECTIVO PROPUESTO USD | H9: OBSERVACIONES
A10: 1103017040 | B10: CARREÑO MARIN IVAN PATRICIO | C10: 1 | D10: 1 | E10: AUXILIAR DE SERV. MUNICIPALES | F10: =531 -> 531 | G10: =549 -> 549
A11: 1101175709 | B11: CUESTA JIMENEZ MARCO ANTONIO | C11: 2 | D11: 1 | E11: JORNALERO DE PARQUES Y JARDINES | F11: =531 -> 531 | G11: =549 -> 549
A12: 1103654313 | B12: MARIN SOLORZANO LEONARDO EZEQUIEL | C12: 3 | D12: 1 | E12: AUXILIAR ADM. DE TRAMITES | F12: =531 -> 531 | G12: =549 -> 549
A13: 1105156853 | B13: MAZA GUAMAN GUIDO RENE | C13: 4 | D13: 1 | E13: AYUDANTE DE ALBAÑIL | F13: =531 -> 531 | G13: =549 -> 549
A14: 1101628483 | B14: SACAPI LUIS ENRIQUE | C14: 5 | D14: 1 | E14: GUARDIAN ADMINISTRATIVO | F14: =531 -> 531 | G14: =549 -> 549
A15: 1100809993 | B15: BALCAZAR RAMIREZ ANGEL TORIBIO | C15: 6 | D15: 1 | E15: GUARDIAN ADMINISTRATIVO | F15: =531 -> 531 | G15: =549 -> 549
A16: 1103256374 | B16: BARRERA POLO HECTOR ENRIQUE | C16: 7 | D16: 1 | E16: AUXILIAR ADMINISTRATIVO 111 | F16: =531 -> 531 | G16: =549 -> 549
A17: 1104721384 | B17: BRICEÑO BRICEÑO DIEGO FERNANDO | C17: 8 | D17: 1 | E17: GUARDIAN ADMINISTRATIVO | F17: =531 -> 531 | G17: =549 -> 549
A18: 1102914007 | B18: CABRERA GONZALEZ MANUEL IGNACIO | C18: 9 | D18: 1 | E18: GUARDIAN ADMINISTRATIVO | F18: =531 -> 531 | G18: =549 -> 549
A19: 1101055463 | B19: CABRERA MACAS EFRAIN | C19: 10 | D19: 1 | E19: GUARDIAN ADMINISTRATIVO | F19: =531 -> 531 | G19: =549 -> 549
A20: 1101060588 | B20: CARRION ENCALADA ELICEO | C20: 11 | D20: 1 | E20: GUARDIAN ADMINISTRATIVO | F20: =531 -> 531 | G20: =549 -> 549
A21: 1101431839 | B21: CASTILLO FRANCO VICENTE | C21: 12 | D21: 1 | E21: GUARDIAN ADMINISTRATIVO | F21: =531 -> 531 | G21: =549 -> 549
... A117: 1100765989 | B117: YAGUANA POGO CESAR AMABLE | C117: 108 | D117: 1 | E117: AYUDANTE DE ALBAÑIL | F117: =531 -> 531 | G117: =549 -> 549
A118: 1104395007 | B118: JARAMILLO JARAMILLO DIEGO ARMANDO | C118: 109 | D118: 2 | E118: CONTROLADOR MANTENIMIENTO AGUA | F118: =548 -> 548 | G118: =566 -> 566
A119: 0701942575 | B119: MACAS CHUNCHO FLORESMILO ADRIANO | C119: 110 | D119: 2 | E119: CONTROLADOR MANTENIMIENTO AGUA | F119: =548 -> 548 | G119: =566 -> 566
A120: 1103141899 | B120: NAVARRO CHIRIBOGA NILO ALBERTO | C120: 111 | D120: 2 | E120: GASFITERO | F120: =548 -> 548 | G120: =566 -> 566
A121: 1102135652 | B121: AGUIRRE GONZAGA WILMAN ORLANDO | C121: 112 | D121: 2 | E121: MAESTRO ALBAÑIL | F121: =548 -> 548 | G121: =566 -> 566
A122: 1101963427 | B122: CASTILLO CUENCA JORGE ENRIQUE | C122: 113 | D122: 2 | E122: MAESTRO ALBAÑIL | F122: =548 -> 548 | G122: =566 -> 566
A123: 1102997705 | B123: CHAMBA CUENCA OLGER EDUARDO | C123: 114 | D123: 2 | E123: MAESTRO ALBAÑIL | F123: =548 -> 548 | G123: =566 -> 566
A124: 1103292759 | B124: JIMENEZ CHAMBA JORGE FELICITO | C124: 115 | D124: 2 | E124: MAESTRO ALBAÑIL | F124: =548 -> 548 | G124: =566 -> 566
A125: 1718055542 | B125: RIVAS ALVAREZ LUIS RODRIGO | C125: 116 | D125: 2 | E125: MECANICO INDUSTRIAL | F125: =548 -> 548 | G125: =566 -> 566
A126: 0701121519 | B126: RODRIGUEZ RODRIGUEZ ROBERT RAUL | C126: 117 | D126: 2 | E126: PINTOR AUTOMOTRIZ | F126: =548 -> 548 | G126: =566 -> 566
A127: 1102740154 | B127: VASQUEZ FERNÁNDEZ HONORATO | C127: 118 | D127: 2 | E127: PINTOR | F127: =548 -> 548 | G127: =566 -> 566
A128: 1102773775 | B128: VEGA VIÑAGUAZO JOSE AUGUSTO | C128: 119 | D128: 2 | E128: MAESTRO ALBAÑIL | F128: =548 -> 548 | G128: =566 -> 566
A129: 1100255023 | B129: VILLALTA TORRES LEONARDO AMADEO | C129: 120 | D129: 2 | E129: MAESTRO ALBAÑIL | F129: =548 -> 548 | G129: =566 -> 566
... A133: 1101797171 | B133: YAGUANA HERRERA FRANCISCO JAVIER | C133: 124 | D133: 2 | E133: MAESTRO ALBAÑIL | F133: =548 -> 548 | G133: =566 -> 566
A134: 1103230585 | B134: SOLANO SOLANO JOSÉ RAMIRO | C134: 125 | D134: 3 | E134: CHOFER VEHICULOS LIVIANOS | F134: =566 -> 566 | G134: =584 -> 584
A135: 1103245146 | B135: CHUBA QUITO CÉSAR ROLANDO | C135: 126 | D135: 3 | E135: CHOFER VEHICULOS LIVIANOS | F135: =566 -> 566 | G135: =584 -> 584
A136: 1101347506 | B136: GONZALEZ AYORA JUAN IGNACIO | C136: 127 | D136: 3 | E136: CHOFER VEHICULOS LIVIANOS | F136: =566 -> 566 | G136: =584 -> 584
A137: 0101510477 | B137: QUITO ENRIQUEZ LUIS MIGUEL | C137: 128 | D137: 3 | E137: MAESTRO ALBAÑIL 11 | F137: =560 -> 560 | G137: =578 -> 578
A138: 1101673034 | B138: VACA TAMAYO ANGEL SALVADOR | C138: 129 | D138: 4 | E138: CHOFER VEHICULOS PESADOS | F138: =584 -> 584 | G138: =602 -> 602
A139: 1101879482 | B139: CARRILLO MARÍN JORGE NICOLÁS | C139: 130 | D139: 4 | E139: CHOFER VEHICULOS PESADOS | F139: =584 -> 584 | G139: =602 -> 602
A140: 1104412398 | B140: CRUZ VALDIVIEZO DIEGO FERNANDO | C140: 131 | D140: 4 | E140: CHOFER VEHICULOS PESADOS | F140: =584 -> 584 | G140: =602 -> 602
A141: 1103908081 | B141: ESCALERAS SANTUORUM CRISTOBAL COLON | C141: 132 | D141: 4 | E141: CHOFER VEHICULOS PESADOS | F141: =584 -> 584 | G141: =602 -> 602
A142: 1102888854 | B142: HIDALGO ORTIZ EDISON FRANKLIN | C142: 133 | D142: 4 | E142: CHOFER RECOLECTOR | F142: =584 -> 584 | G142: =602 -> 602
A143: 1706099841 | B143: JARAMILLO SANCHEZ EFRAIN | C143: 134 | D143: 4 | E143: CHOFER VEHICULOS PESADOS | F143: =584 -> 584 | G143: =602 -> 602
A144: 1104075195 | B144: MERINO RODAS JOSE ANTONIO | C144: 135 | D144: 4 | E144: CHOFER VEHICULOS PESADOS | F144: =584 -> 584 | G144: =602 -> 602
A145: 1104504509 | B145: OGOÑO CARAGUAY ANGEL ROBERTO | C145: 136 | D145: 4 | E145: CHOFER RECOLECTOR | F145: =584 -> 584 | G145: =602 -> 602
A146: 1101402434 | B146: QUINDE ROSILLO FIDEL AGUSTIN | C146: 137 | D146: 4 | E146: CHOFER VEHICULOS PESADOS | F146: =584 -> 584 | G146: =602 -> 602
A147: 1100583804 | B147: RIOFRIO NARVAEZ BENIGNO | C147: 138 | D147: 4 | E147: CHOFER VEHICULOS PESADOS | F147: =584 -> 584 | G147: =602 -> 602
A148: 1103162804 | B148: ROJAS GAONA JIMMY RENÁN | C148: 139 | D148: 4 | E148: CHOFER VEHICULOS PESADOS | F148: =584 -> 584 | G148: =602 -> 602
A149: 1102150636 | B149: ROJAS ROJAS WALTER BENJAMIN | C149: 140 | D149: 4 | E149: CHOFER VEHICULOS PESADOS | F149: =584 -> 584 | G149: =602 -> 602
... A153: 1103390017 | B153: TANDAZO ENCALADA HAMILTON | C153: 144 | D153: 4 | E153: CHOFER VEHICULOS PESADOS | F153: =584 -> 584 | G153: =602 -> 602
A154: 1102487244 | B154: ABAD FRANCO NOE | C154: 145 | D154: 5 | E154: OPERADOR ESTACION DE BOMBEO | F154: =708 -> 708 | G154: =726 -> 726
A155: 1102535182 | B155: CARRION HERRERA SAÚL IVÁN | C155: 146 | D155: 5 | E155: OPERADOR PLANTA DE TRATAMIENTO DE AGUA | F155: =708 -> 708 | G155: =726 -> 726
A156: 1100807815 | B156: CELI OBANDO LUIS HUMBERTO | C156: 147 | D156: 5 | E156: OPERADOR VALVULA SURTIDORA DE AGUA | F156: =708 -> 708 | G156: =726 -> 726
A157: 1101952412 | B157: GUIÑAGUAZO CANGO HIPOLITO | C157: 148 | D157: 5 | E157: OPERADOR ESTACION DE BOMBEO | F157: =708 -> 708 | G157: =726 -> 726
A158: 1102990825 | B158: OCHOA BUSTAMANTE ÁNGEL ENRIQUE | C158: 149 | D158: 5 | E158: OPERADOR VALVULA SURTIDORA DE AGUA | F158: =708 -> 708 | G158: =726 -> 726
A159: 1102705330 | B159: OCHOA BUSTAMANTE HUGO SALVADOR | C159: 150 | D159: 5 | E159: CONTROLADOR MANTENIMIENTO DE AGUA | F159: =708 -> 708 | G159: =726 -> 726
A160: 1102486600 | B160: OCHOA BUSTAMANTE JORGE ALBERTO | C160: 151 | D160: 5 | E160: OPERADOR PLANTA DE TRATAMIENTO DE AGUA | F160: =708 -> 708 | G160: =726 -> 726
A161: 1103957385 | B161: PARDO LEON GLORIA PATRICIA | C161: 152 | D161: 5 | E161: OPERADOR VALVULA SURTIDORA DE AGUA | F161: =708 -> 708 | G161: =726 -> 726
A162: 1103084800 | B162: PAZ QUEZADA FLAVIO OLIVERIO | C162: 153 | D162: 5 | E162: OPERADOR PLANTA DE TRATAMIENTO DE AGUA | F162: =708 -> 708 | G162: =726 -> 726
A163: 1101613709 | B163: PEREZ SILVERIO HIPOLITO LAURIANO | C163: 154 | D163: 5 | E163: OPERADOR PLANTA DE TRATAMIENTO DE AGUA | F163: =708 -> 708 | G163: =726 -> 726
A164: 1102265012 | B164: PEREZ SILVERIO JUAN JAVIER | C164: 155 | D164: 5 | E164: OPERADOR ESTACION DE BOMBEO | F164: =708 -> 708 | G164: =726 -> 726
A165: 1103379531 | B165: ROJAS SALINAS LUCIO STALIN | C165: 156 | D165: 5 | E165: JEFE DE ALCANTARILLADO | F165: =708 -> 708 | G165: =726 -> 726
... A179: 1101438727 | B179: VIVANCO MEJIA CRISTOBAL GONZALO | C179: 170 | D179: 5 | E179: OPERADOR MOTONIVELADORA | F179: =708 -> 708 | G179: =726 -> 726
A180: 1102047964 | B180: CUENCA CELI ANGEL BENIGNO | C180: 171 | D180: 6 | E180: INSPECTOR REDES AGUA POTABLE | F180: =743 -> 743 | G180: =761 -> 761
A181: 1102334206 | B181: AGURTO JIMENEZ CARLOS ENRIQUE | C181: 172 | D181: 6 | E181: MAESTRO MAYOR EN EJECUCION DE OBRAS | F181: =743 -> 743 | G181: =761 -> 761
A182: 0701803074 | B182: GIRON RAMIREZ HUGO RAMIRO | C182: 173 | D182: 6 | E182: SUPERVISOR DE MANT. EQUIPO PESADO | F182: =743 -> 743 | G182: =761 -> 761
A183: 1103213730 | B183: LOAIZA YAGUANA JOSÉ JULIO | C183: 174 | D183: 6 | E183: TECNICO DE ELECTRICIDAD | F183: =743 -> 743 | G183: =761 -> 761
E185: SUMAN | F185: =SUM(F10:F184) -> 99098 | G185: =SUM(G10:G184) -> 102230
A187: * De ser el caso, se deberá incluir filas adicionales para detallar a todos los trabajadores del contrato colectivo.
A188: * La información deberá estar acorde a los techos presupuestarios establecidos por el MRL correspondiente a cada periodo.
A189: * La información de los formularios deberá remitirse en medio magnético (Excel) e impreso con las respectivas firmas de responsabilidad.
B195: FIRMA DIRECTOR (A) FINANCIERO (A) DEL GAD
B196: Dr. C.P.A. Julio Farinango Benalcázar
B198: Lugar y Fecha: Catamayo, 01/12/2016
B199: Sello Institucional

Sheet FORMULARIO 4
A1: FORMULARIO 4
A2: FLUJO PRESUPUESTARIO DE INGRESOS Y GASTOS
A4: GOBIERNO AUTÓNOMO DESCENTRALIZADO MUNICIPAL DE CATAMAYO
A6: DETALLE DE GRUPOS Y SUBGRUPOS | C6: FLUJO HISTÓRICO (USD) | F6: FLUJO PROYECTADO (USD) | J6: OBSERVACIONES
A8: Grupo y Subgrupo | B8: Descripción | C8: 2013 | D8: 2014 | E8: 2015 | F8: AÑO 1 | G8: AÑO 2 | H8: AÑO 3 | I8: AÑO 4
A9: TOTAL INGRESOS CORRIENTES (1) | C9: =SUM(C11:C32) -> 3297110.5 | D9: =SUM(D11:D32) -> 3380227.1 | E9: =SUM(E11:E32) -> 3156612.3 | F9: =SUM(F11:F32) -> 3219744.5 | G9: =SUM(G11:G32) -> 3284139.4 | H9: =SUM(H11:H32) -> 3316980.8 | I9: =SUM(I11:I32) -> 3350150.6
A10: 11 | B10: Impuestos
A11: 1101 | B11: Sobre la Renta, Utilidades y Ganancias de Capital | C11: 111045.83 | D11: =146142.35 -> 146142.35 | E11: =99217.63 -> 99217.63 | F11: =SUM(E11*0.02)+E11 -> 101201.98 | G11: =SUM(F11*0.02)+F11 -> 103226.02 | H11: =SUM(G11*0.01)+G11 -> 104258.28 | I11: =SUM(H11*0.01)+H11 -> 105300.87
A12: 1102 | B12: Sobre la propiedad | C12: =167202.17+12114.77+196402.45+166707.73+46095.16 -> 588522.28 | D12: =173338.9+13645.16+182591.57+138360.88+63500.18 -> 571436.69 | E12: =175676.27+13653.89+164394.88+123512.11+53463.72 -> 530700.87 | F12: =SUM(E12*0.02)+E12 -> 541314.89 | G12: =SUM(F12*0.02)+F12 -> 552141.19 | H12: =SUM(G12*0.01)+G12 -> 557662.6 | I12: =SUM(H12*0.01)+H12 -> 563239.22
A13: 1103 | B13: Al consumo de Bienes y Servicios | C13: 234 | D13: 250 | E13: 184 | F13: =SUM(E13*0.02)+E13 -> 187.68 | G13: =SUM(F13*0.02)+F13 -> 191.4336 | H13: =SUM(G13*0.01)+G13 -> 193.34794 | I13: =SUM(H13*0.01)+H13 -> 195.28142
A14: 1107 | B14: Impuestos Diversos | C14: =128387 -> 128387 | D14: =193144.23 -> 193144.23 | E14: 87304.47 | F14: =SUM(E14*0.02)+E14 -> 89050.559 | G14: =SUM(F14*0.02)+F14 -> 90831.571 | H14: =SUM(G14*0.01)+G14 -> 91739.886 | I14: =SUM(H14*0.01)+H14 -> 92657.285
A15: 13 | B15: Tasas y contribuciones
A16: 1301 | B16: Tasas generales | C16: =122450.83+59887.04+16025+6906.4+46921.35+11581.7+2955+62158.82+54281.68+9367.31+7982.32+64673.63 -> 465191.08 | D16: =126810.25+52132.71+16403+5639+51161.77+3100+63210.49+27807.4+6855.44+9235+64125.13 -> 426480.19 | E16: =133949.71+50030.13+10596.5+6590.52+50521.26+4440+67357.58+47667.92+7554.51+7410+63037.53 -> 449155.66 | F16: =SUM(E16*0.02)+E16 -> 458138.77 | G16: =SUM(F16*0.02)+F16 -> 467301.55 | H16: =SUM(G16*0.01)+G16 -> 471974.56 | I16: =SUM(H16*0.01)+H16 -> 476694.31
A17: 1302 | B17: Tasas portuarias y aeroportuarias
A18: 1303 | B18: Tasas diversas
A19: 1304 | B19: Contribuciones | C19: =28963.58+32272.69+30065.14+231399.67 -> 322701.08 | D19: =1755.94+10980.13+9180.3+219599.83+1089.48 -> 242605.68 | E19: =7185.35+3371.76+19676.54+316687.34 -> 346920.99 | F19: =SUM(E19*0.02)+E19 -> 353859.41 | G19: =SUM(F19*0.02)+F19 -> 360936.6 | H19: =SUM(G19*0.01)+G19 -> 364545.96 | I19: =SUM(H19*0.01)+H19 -> 368191.42
A20: 14 | B20: Venta de Bienes y Servicios
A21: 1402 | B21: Ventas de productos y materiales | C21: =17626.62+230.5 -> 17857.12 | D21: =18974.2+289 -> 19263.2 | E21: =16727.85+182 -> 16909.85 | F21: =SUM(E21*0.02)+E21 -> 17248.047 | G21: =SUM(F21*0.02)+F21 -> 17593.008 | H21: =SUM(G21*0.01)+G21 -> 17768.938 | I21: =SUM(H21*0.01)+H21 -> 17946.627
A22: 1403 | B22: Ventas no industriales | C22: =154831.61+55623.07 -> 210454.68 | D22: =156344.71+56417.14 -> 212761.85 | E22: =168348.81+63825.22 -> 232174.03 | F22: =SUM(E22*0.02)+E22 -> 236817.51 | G22: =SUM(F22*0.02)+F22 -> 241553.86 | H22: =SUM(G22*0.01)+G22 -> 243969.4 | I22: =SUM(H22*0.01)+H22 -> 246409.09
A23: 17 | B23: Rentas de Invesiones y Multas
A24: 1701 | B24: Rentas de inversiones | C24: 15.34
A25: 1702 | B25: Rentas por arrendamientos de bienes | C25: =32905.95+5018.8+7444.94 -> 45369.69 | D25: =6160+324.43+12876.9 -> 19361.33 | E25: =6619+635.24+14203.27 -> 21457.51 | F25: =SUM(E25*0.02)+E25 -> 21886.66 | G25: =SUM(F25*0.02)+F25 -> 22324.393 | H25: =SUM(G25*0.01)+G25 -> 22547.637 | I25: =SUM(H25*0.01)+H25 -> 22773.114
A26: 1704 | B26: Multas | C26: =29987.36+1911+31589.63+7493.6 -> 70981.59 | D26: =39512.92+3234.5+9243.35+55528.12 -> 107518.89 | E26: =35726.56+3103.28+40315.74 -> 79145.58 | F26: =SUM(E26*0.02)+E26 -> 80728.492 | G26: =SUM(F26*0.02)+F26 -> 82343.061 | H26: =SUM(G26*0.01)+G26 -> 83166.492 | I26: =SUM(H26*0.01)+H26 -> 83998.157
A27: 18 | B27: Transferencias y Donaciones Corrientes
A28: 1806 | B28: Aporte y participación cooriente del Régimen Seccional Autónomo | C28: =1336334.83 -> 1336334.8 | D28: =1441262.68 -> 1441262.7 | E28: =1293441.69 -> 1293441.7 | F28: =SUM(E28*0.02)+E28 -> 1319310.5 | G28: =SUM(F28*0.02)+F28 -> 1345696.7 | H28: =SUM(G28*0.01)+G28 -> 1359153.7 | I28: =SUM(H28*0.01)+H28 -> 1372745.2
A29: 19 | B29: Otros ingresos
A30: 1901 | B30: Garantías y Fianzas
A31: 1902 | B31: Indemnizaciones y valores no reclamados
A32: 1904 | B32: Otros no Operacionales | C32: 16.01
A33: TOTAL GASTOS CORRIENTES (2) | C33: =SUM(C35:C62) -> 1837469.1 | D33: =SUM(D35:D62) -> 2461219.6 | E33: =SUM(E35:E62) -> 1158025.5 | F33: =SUM(F35:F62) -> 1181186 | G33: =SUM(G35:G62) -> 1204809.7 | H33: =SUM(H35:H62) -> 1216857.8 | I33: =SUM(I35:I62) -> 1229026.4
A34: 51 | B34: Gastos en personal
A35: 5101 | B35: Remuneraciones Básicas | C35: =230789.6+127969.71+24766.45+47047.6+13917.85+145583.42+199274.3+41710.83+49888.2+41132.2 -> 922080.16 | D35: =239851.96+147437.21+24779.43+47915.88+18473.65+172625.23+249463.04+53470.6+54306.63+49029.36 -> 1057353 | E35: =171120.6+117780.28+24285.62+38590.78+120629.16 -> 472406.44 | F35: =SUM(E35*0.02)+E35 -> 481854.57 | G35: =SUM(F35*0.02)+F35 -> 491491.66 | H35: =SUM(G35*0.01)+G35 -> 496406.58 | I35: =SUM(H35*0.01)+H35 -> 501370.64
A36: 5102 | B36: Remuneraciones Complementarias | C36: =3869.89+4329.42+237.62+1590+287.08+5939+13557.89+2186.25+1590+1271.12 -> 34858.27 | D36: =19116.45+16508.46+2508.76+4048.9+1781.48+22487.66+38719.95+7082.81+6474.25+5003.48 -> 123732.2 | E36: =18148.42+16643.22+3440.24+5221.57+16624.89 -> 60078.34 | F36: =SUM(E36*0.02)+E36 -> 61279.907 | G36: =SUM(F36*0.02)+F36 -> 62505.505 | H36: =SUM(G36*0.01)+G36 -> 63130.56 | I36: =SUM(H36*0.01)+H36 -> 63761.866
A37: 5103 | B37: Remuneraciones Compensatorias
A38: 5104 | B38: Subsidios
A39: 5105 | B39: Remuneraciones Temporales | C39: =46003.36+28482.67+3400.58+5595.63+15202.94+63812.94+1205.2+80217.39+697.84 -> 244618.55 | D39: =17759.87+24793.51+7490.75+8067.13+19557.02+78596.78+577.38+77576.05 -> 234418.49 | E39: =3660+108099.22+12589.07+35727.22 -> 160075.51 | F39: =SUM(E39*0.02)+E39 -> 163277.02 | G39: =SUM(F39*0.02)+F39 -> 166542.56 | H39: =SUM(G39*0.01)+G39 -> 168207.99 | I39: =SUM(H39*0.01)+H39 -> 169890.07
A40: 5106 | B40: Aportes Patronales a la Seguridad Social | C40: =44859.78+21485.36+3528.08+9400.2+1660.72+27991.27+40317.4+8687.54+9563.45+7151.93 -> 174645.73 | D40: =39571.04+24921.14+4583.57+9599.98+2270.35+32133.8+54763.57+10314.38+9669.84+7958.08 -> 195785.75 | E40: =33686.24+23804.1+5321.41+8579.89+27368.88 -> 98760.52 | F40: =SUM(E40*0.02)+E40 -> 100735.73 | G40: =SUM(F40*0.02)+F40 -> 102750.45 | H40: =SUM(G40*0.01)+G40 -> 103777.95 | I40: =SUM(H40*0.01)+H40 -> 104815.73
A41: 5107 | B41: Indemnizaciones | C41: =54416.72 -> 54416.72 | D41: =163813.55 -> 163813.55 | E41: =86010.09 -> 86010.09 | F41: =SUM(E41*0.02)+E41 -> 87730.292 | G41: =SUM(F41*0.02)+F41 -> 89484.898 | H41: =SUM(G41*0.01)+G41 -> 90379.747 | I41: =SUM(H41*0.01)+H41 -> 91283.544
A42: 5199 | B42: Asignaciones a distribuir
A43: 53 | B43: Bienes y servicios de consumo
A44: 5301 | B44: Servicios básicos | C44: =20290.91 -> 20290.91 | D44: =18272.58 -> 18272.58 | E44: =23812.53 -> 23812.53 | F44: =SUM(E44*0.02)+E44 -> 24288.781 | G44: =SUM(F44*0.02)+F44 -> 24774.556 | H44: =SUM(G44*0.01)+G44 -> 25022.302 | I44: =SUM(H44*0.01)+H44 -> 25272.525
A45: 5302 | B45: Servicios generales | C45: =978.89+261.13+48149.48+11129.48+348.32+89705.28+3493.72 -> 154066.3 | D45: =1517.27+2546.95+9778.53+34.82+67396.72+178.46 -> 81452.75 | E45: =15613.21 -> 15613.21 | F45: =SUM(E45*0.02)+E45 -> 15925.474 | G45: =SUM(F45*0.02)+F45 -> 16243.984 | H45: =SUM(G45*0.01)+G45 -> 16406.424 | I45: =SUM(H45*0.01)+H45 -> 16570.488
A46: 5303 | B46: Traslados, instalaciones, viáticos y subsistencias | C46: =7664.78+4728.43+221+209.52+517+1269.41+884.99+712.46 -> 16207.59 | D46: =6353.06+2913.7+600+40+586.81+70+281.93 -> 10845.5 | E46: =3310.26+1763.81+607+1088.17 -> 6769.24 | F46: =SUM(E46*0.02)+E46 -> 6904.6248 | G46: =SUM(F46*0.02)+F46 -> 7042.7173 | H46: =SUM(G46*0.01)+G46 -> 7113.1445 | I46: =SUM(H46*0.01)+H46 -> 7184.2759
A47: 5304 | B47: Instalación, mantenimiento y reparaciones | C47: =2781.96+163.52+3225.39 -> 6170.87 | D47: =1977.42+2590.33+2160.6 -> 6728.35 | E47: =1066.08 -> 1066.08 | F47: =SUM(E47*0.02)+E47 -> 1087.4016 | G47: =SUM(F47*0.02)+F47 -> 1109.1496 | H47: =SUM(G47*0.01)+G47 -> 1120.2411 | I47: =SUM(H47*0.01)+H47 -> 1131.4435
A48: 5305 | B48: Arrendamientos de bienes | C48: =537.6+2606.06 -> 3143.66 | D48: =2556.46 -> 2556.46 | E48: =2507.13 -> 2507.13 | F48: =SUM(E48*0.02)+E48 -> 2557.2726 | G48: =SUM(F48*0.02)+F48 -> 2608.4181 | H48: =SUM(G48*0.01)+G48 -> 2634.5022 | I48: =SUM(H48*0.01)+H48 -> 2660.8473
A49: 5306 | B49: Contratación de estudios, investigaciones y servicios técnicos especial. | C49: =8847.6+1789.6+500+751.6+336+454+500+650+370+18.8 -> 14217.6 | D49: =4816+21280+437.67 -> 26533.67 | E49: =7112+156.8 -> 7268.8 | F49: =SUM(E49*0.02)+E49 -> 7414.176 | G49: =SUM(F49*0.02)+F49 -> 7562.4595 | H49: =SUM(G49*0.01)+G49 -> 7638.0841 | I49: =SUM(H49*0.01)+H49 -> 7714.465
A50: 5307 | B50: Gastos en informática | C50: =110.7 -> 110.7 | D50: =683.2+300 -> 983.2 | E50: =3874.63 -> 3874.63 | F50: =SUM(E50*0.02)+E50 -> 3952.1226 | G50: =SUM(F50*0.02)+F50 -> 4031.1651 | H50: =SUM(G50*0.01)+G50 -> 4071.4767 | I50: =SUM(H50*0.01)+H50 -> 4112.1915
A51: 5308 | B51: Bienes de uso y consumo corriente | C51: =34437.25+3143.19+1299.4+9928.08+9286.38+4172.43+3731.55+5041.88 -> 71040.16 | D51: =64.46+29381.79+3261.39+999.22+10954.2+11179.39+6642.45+4593.23+5634.96 -> 72711.09 | E51: =27407.19+1680.18+9369.82 -> 38457.19 | F51: =SUM(E51*0.02)+E51 -> 39226.334 | G51: =SUM(F51*0.02)+F51 -> 40010.86 | H51: =SUM(G51*0.01)+G51 -> 40410.969 | I51: =SUM(H51*0.01)+H51 -> 40815.079
A52: 5314 | B52: Bienes muebles no depreciables
A53: 56 | B53: Gastos Financieros
A54: 5601 | B54: Títulos y valores en circulación | C54: =771.73 -> 771.73 | D54: =13093.79 -> 13093.79 | E54: 14812.38 | F54: =SUM(E54*0.02)+E54 -> 15108.628 | G54: =SUM(F54*0.02)+F54 -> 15410.8 | H54: =SUM(G54*0.01)+G54 -> 15564.908 | I54: =SUM(H54*0.01)+H54 -> 15720.557
A55: 5602 | B55: Intereses y otros cargos de la deuda pública | C55: =15640.98 -> 15640.98 | D55: =61369.69 -> 61369.69 | E55: =84092.7 -> 84092.7 | F55: =SUM(E55*0.02)+E55 -> 85774.554 | G55: =SUM(F55*0.02)+F55 -> 87490.045 | H55: =SUM(G55*0.01)+G55 -> 88364.946 | I55: =SUM(H55*0.01)+H55 -> 89248.595
A56: 57 | B56: Otros gastos corrientes
A57: 5701 | B57: Impuestos, tasas y contribuciones | C57: =4777.13 -> 4777.13 | D57: =8610.77 -> 8610.77 | E57: =15484.28 -> 15484.28 | F57: =SUM(E57*0.02)+E57 -> 15793.966 | G57: =SUM(F57*0.02)+F57 -> 16109.845 | H57: =SUM(G57*0.01)+G57 -> 16270.943 | I57: =SUM(H57*0.01)+H57 -> 16433.653
A58: 5702 | B58: Seguros, costos financieros y otros gastos | C58: =21538.88+4986.38 -> 26525.26 | D58: =2287.22+3000+5319.73 -> 10606.95 | E58: =325.4+2311.4 -> 2636.8 | F58: =SUM(E58*0.02)+E58 -> 2689.536 | G58: =SUM(F58*0.02)+F58 -> 2743.3267 | H58: =SUM(G58*0.01)+G58 -> 2770.76 | I58: =SUM(H58*0.01)+H58 -> 2798.4676
A59: 58 | B59: Transferencias y donaciones corrientes
A60: 5801 | B60: Transferencias corrientes al sector público | C60: =36777.02 -> 36777.02 | D60: =63103.63 -> 63103.63 | E60: =52771.01 -> 52771.01 | F60: =SUM(E60*0.02)+E60 -> 53826.43 | G60: =SUM(F60*0.02)+F60 -> 54902.959 | H60: =SUM(G60*0.01)+G60 -> 55451.988 | I60: =SUM(H60*0.01)+H60 -> 56006.508
A61: 5802 | B61: Donaciones corrientes al sector privado interno | C61: =37109.8 -> 37109.8 | D61: =309248.23 -> 309248.23 | E61: 11528.6 | F61: =SUM(E61*0.02)+E61 -> 11759.172 | G61: =SUM(F61*0.02)+F61 -> 11994.355 | H61: =SUM(G61*0.01)+G61 -> 12114.299 | I61: =SUM(H61*0.01)+H61 -> 12235.442
A62: 59 | B62: Previsiones para reasignaciones
A63: SUPERAVIT/DEFICIT CORRIENTE (1) - (2) = (3) | C63: =+C9-C33 -> 1459641.4 | D63: =+D9-D33 -> 919007.45 | E63: =+E9-E33 -> 1998586.8 | F63: =+F9-F33 -> 2038558.5 | G63: =+G9-G33 -> 2079329.7 | H63: =+H9-H33 -> 2100123 | I63: =+I9-I33 -> 2121124.2
A64: INGRESOS DE CAPITAL E INVERSIÓN (4) | C64: =SUM(C66:C71) -> 3921248.2 | D64: =SUM(D66:D71) -> 3996262.5 | E64: =SUM(E66:E71) -> 4291120.1 | F64: =SUM(F66:F71) -> 4316581.8 | G64: =SUM(G66:G71) -> 4342552.9 | H64: =SUM(H66:H71) -> 4385978.4 | I64: =SUM(I66:I71) -> 4429838.2
A65: 24 | B65: Venta de Activos no Financieros
A66: 2402 | B66: Bienes inmuebles | C66: 89109.74 | D66: 50683.78 | E66: 50715.66 | F66: =SUM(E66*0.02)+E66 -> 51729.973 | G66: =SUM(F66*0.02)+F66 -> 52764.573 | H66: =SUM(G66*0.01)+G66 -> 53292.218 | I66: =SUM(H66*0.01)+H66 -> 53825.141
A67: 28 | B67: Transferencias y donaciones de capital e inversión
A68: 2801 | B68: Transferencias de capital e inversión del sector público | C68: =12000+10000+77324.2+45000+10000+17703.2+4395+6682.64+22029.43+143331.33+29853.14+2076+7892+8800 -> 397086.94 | D68: =293925.79 -> 293925.79 | E68: =958041.96 -> 958041.96 | F68: =SUM(E68*0.02)+E68 -> 977202.8 | G68: =SUM(F68*0.02)+F68 -> 996746.86 | H68: =SUM(G68*0.01)+G68 -> 1006714.3 | I68: =SUM(H68*0.01)+H68 -> 1016781.5
A69: 2803 | B69: Donaciones de capital del sector externo | D69: =99693 -> 99693 | E69: =264235.68 -> 264235.68 | F69: =SUM(E69*0.02)+E69 -> 269520.39 | G69: =SUM(F69*0.02)+F69 -> 274910.8 | H69: =SUM(G69*0.01)+G69 -> 277659.91 | I69: =SUM(H69*0.01)+H69 -> 280436.51
A70: 2806 | B70: Gobiernos Autónomos | C70: 3118114.8 | D70: =3362946.41 -> 3362946.4 | E70: 3018030.6 | F70: =E70 -> 3018030.6 | G70: =F70 -> 3018030.6 | H70: =SUM(G70*0.01)+G70 -> 3048210.9 | I70: =SUM(H70*0.01)+H70 -> 3078693 | J70: Se considera un incremento del 1% en el año 3 y 4
A71: 2810 | B71: IVA | C71: 316936.73 | D71: =189013.57 -> 189013.57 | E71: =96.19 -> 96.19 | F71: =SUM(E71*0.02)+E71 -> 98.1138 | G71: =SUM(F71*0.02)+F71 -> 100.07608 | H71: =SUM(G71*0.01)+G71 -> 101.07684 | I71: =SUM(H71*0.01)+H71 -> 102.08761
A72: GASTOS DE CAPITAL E INVERSIÓN (5) | C72: =SUM(C74:C108) -> 4091034.6 | D72: =SUM(D74:D108) -> 5540165.2 | E72: =SUM(E74:E108) -> 6275212.4 | F72: =SUM(F74:F108) -> 6400716.7 | G72: =SUM(G74:G108) -> 6528731 | H72: =SUM(H74:H108) -> 6594018.3 | I72: =SUM(I74:I108) -> 6659958.5
A73: 61 | B73: Gastos en personal para producción
A74: 63 | B74: Bienes y servicios para producción
A75: 6312 | B75: Adquisiciones de productos terminados | C75: =10421.6 -> 10421.6 | D75: =7280 -> 7280 | E75: =11278.4 -> 11278.4 | F75: =SUM(E75*0.02)+E75 -> 11503.968 | G75: =SUM(F75*0.02)+F75 -> 11734.047 | H75: =SUM(G75*0.01)+G75 -> 11851.388 | I75: =SUM(H75*0.01)+H75 -> 11969.902
A76: 67 | B76: Otros gastos de producción
A77: 71 | B77: Gastos en personal para Inversión
A78: 7101 | B78: Remuneraciones Básicas | C78: =252583.44+19816+55018.88+89463.95+41017+21498.8+140084.95+185810.94+166509.39 -> 971803.35 | D78: =321131.78+26352.15+71645.63+113745.84+44963.43+26192.95+174129.69+221930.29+212162.34 -> 1212254.1 | E78: =322072.25+28057.76+273796.66+39941.95+27667.37+63664.79+115483.45+54538.65+186336.8+244551.29+171788.28 -> 1527899.2 | F78: =SUM(E78*0.02)+E78 -> 1558457.2 | G78: =SUM(F78*0.02)+F78 -> 1589626.4 | H78: =SUM(G78*0.01)+G78 -> 1605522.6 | I78: =SUM(H78*0.01)+H78 -> 1621577.9
A79: 7102 | B79: Remuneraciones Complementarias | C79: =16849.6+1589.12+1947.3+6360+410.75+954+11044.33+10874.72+8883.09 -> 58912.91 | D79: =47887.38+4005.66+7972.14+16751.23+3987.84+3252.54+27522.67+32764.04+27729.69 -> 171873.19 | E79: =50951.02+4552.04+45804.93+6097.18+4065.45+7854.06+18009.03+5871.66+31981.3+40171+25529.34 -> 240887.01 | F79: =SUM(E79*0.02)+E79 -> 245704.75 | G79: =SUM(F79*0.02)+F79 -> 250618.85 | H79: =SUM(G79*0.01)+G79 -> 253125.03 | I79: =SUM(H79*0.01)+H79 -> 255656.28
A80: 7103 | B80: Remuneraciones Compensatorias | E80: =30162.16+2989+20226.5+563.5+609+9194.5+16439.5+16901.5+11623.5 -> 108709.16 | F80: =SUM(E80*0.02)+E80 -> 110883.34 | G80: =SUM(F80*0.02)+F80 -> 113101.01 | H80: =SUM(G80*0.01)+G80 -> 114232.02 | I80: =SUM(H80*0.01)+H80 -> 115374.34
A81: 7104 | B81: Subsidios | E81: =3864.43+297.92+2401.98+74.48+1191.68+1853.08+2303.67+190439.3 -> 202426.54 | F81: =SUM(E81*0.02)+E81 -> 206475.07 | G81: =SUM(F81*0.02)+F81 -> 210604.57 | H81: =SUM(G81*0.01)+G81 -> 212710.62 | I81: =SUM(H81*0.01)+H81 -> 214837.72
A82: 7105 | B82: Remuneraciones Temporales | C82: =69824.54+48730.78+26009.84+40844.91+1868.99+5193.92+60655.23+69721.39+37175.39 -> 360024.99 | D82: =65228.91+66192.18+3477+37190.72+4621.8+76163.62+63955.2+65302.23 -> 382131.66 | E82: =55853.39+63045.5+84412.22+1026.16+60911.39+289.78+41928.48+52242.54+93234.42+93512.76+161681.63 -> 708138.27 | F82: =SUM(E82*0.02)+E82 -> 722301.04 | G82: =SUM(F82*0.02)+F82 -> 736747.06 | H82: =SUM(G82*0.01)+G82 -> 744114.53 | I82: =SUM(H82*0.01)+H82 -> 751555.67
A83: 7106 | B83: Aportes Patronales a la Seguridad Social | C83: =54024.33+4131.32+10585.31+18516.09+6993.15+4426.7+28688.62+38374.49+31948.14 -> 197688.15 | D83: =67084.05+5290+13561.01+24291.05+6447.54+5205.87+36181.35+46056.5+53355.78 -> 257473.15 | E83: =73682.18+6481.92+61424.67+9188.26+6316+14563.82+26335.5+10978.58+42303.71+55082.68+38124.62 -> 344481.94 | F83: =SUM(E83*0.02)+E83 -> 351371.58 | G83: =SUM(F83*0.02)+F83 -> 358399.01 | H83: =SUM(G83*0.01)+G83 -> 361983 | I83: =SUM(H83*0.01)+H83 -> 365602.83
A84: 7107 | B84: Indemnizaciones | D84: =740.16+2195.56+873.89+546.67 -> 4356.28 | E84: =75000 -> 75000 | F84: =SUM(E84*0.02)+E84 -> 76500 | G84: =SUM(F84*0.02)+F84 -> 78030 | H84: =SUM(G84*0.01)+G84 -> 78810.3 | I84: =SUM(H84*0.01)+H84 -> 79598.403
A85: 7199 | B85: Asignaciones a distribuir
A86: 73 | B86: Bienes y servicios para inversión
A87: 7301 | B87: Servicios básicos | C87: =398008.3 -> 398008.3 | D87: =277564.59 -> 277564.59 | E87: =230905.77 -> 230905.77 | F87: =SUM(E87*0.02)+E87 -> 235523.89 | G87: =SUM(F87*0.02)+F87 -> 240234.36 | H87: =SUM(G87*0.01)+G87 -> 242636.71 | I87: =SUM(H87*0.01)+H87 -> 245063.07
A88: 7302 | B88: Servicios generales | C88: =12+4+30.94+200+570.66+480 -> 1297.6 | D88: =1290.14+1119.56+567 -> 2976.7 | E88: =143136.9+82+300+6.92+7077.17+6386.8+448 -> 157437.79 | F88: =SUM(E88*0.02)+E88 -> 160586.55 | G88: =SUM(F88*0.02)+F88 -> 163798.28 | H88: =SUM(G88*0.01)+G88 -> 165436.26 | I88: =SUM(H88*0.01)+H88 -> 167090.62
A89: 7303 | B89: Traslados, instalaciones, viáticos y subsistencias | C89: =216.96+52+624.75+310.59+907.5 -> 2111.8 | D89: =217.13+518.64+94.64+139.25 -> 969.66 | E89: =80+80+40+901+65+759.75 -> 1925.75 | F89: =SUM(E89*0.02)+E89 -> 1964.265 | G89: =SUM(F89*0.02)+F89 -> 2003.5503 | H89: =SUM(G89*0.01)+G89 -> 2023.5858 | I89: =SUM(H89*0.01)+H89 -> 2043.8217
A90: 7304 | B90: Instalación, mantenimiento y reparaciones | C90: =132.93+2178.4+2317.74+23054.86 -> 27683.93 | D90: =58.5+1526.09+21626.52 -> 23211.11 | E90: =782.61+637.08+12725.96 -> 14145.65 | F90: =SUM(E90*0.02)+E90 -> 14428.563 | G90: =SUM(F90*0.02)+F90 -> 14717.134 | H90: =SUM(G90*0.01)+G90 -> 14864.306 | I90: =SUM(H90*0.01)+H90 -> 15012.949
A91: 7306 | B91: Contratación de estudios, investigaciones y servicios técnicos especial. | C91: =420+9491.07+28649.31 -> 38560.38 | D91: =13095.34+8010.19 -> 21105.53 | E91: =5662.72 -> 5662.72 | F91: =SUM(E91*0.02)+E91 -> 5775.9744 | G91: =SUM(F91*0.02)+F91 -> 5891.4939 | H91: =SUM(G91*0.01)+G91 -> 5950.4088 | I91: =SUM(H91*0.01)+H91 -> 6009.9129
A92: 7308 | B92: Bienes de uso y consumo de inversión | C92: =27000+12384.72+15358.16+4372.3+3396.88+1071.09+430.98+19131.28+76622.56+49217.88 -> 208985.85 | D92: =20560.38+15199.52+382.05+4118.97+801.93+248.31+15532.31+75359.76+147150.78 -> 279354.01 | E92: =19046.09+9988.81+4064.51+4164.81+97188.13+689.71+661+1283.17+17948.67+72438.96+196425.36 -> 423899.22 | F92: =SUM(E92*0.02)+E92 -> 432377.2 | G92: =SUM(F92*0.02)+F92 -> 441024.75 | H92: =SUM(G92*0.01)+G92 -> 445435 | I92: =SUM(H92*0.01)+H92 -> 449889.35
A93: 75 | B93: Obras públicas
A94: 7501 | B94: Obras de Infraestructura | C94: =22023.58+230033.24+943981.28 -> 1196038.1 | D94: =1332.03+5073.53+1308182.57+927639.37 -> 2242227.5 | E94: =18870.78+19.01+418398.31+755990.07 -> 1193278.2 | F94: =SUM(E94*0.02)+E94 -> 1217143.7 | G94: =SUM(F94*0.02)+F94 -> 1241486.6 | H94: =SUM(G94*0.01)+G94 -> 1253901.5 | I94: =SUM(H94*0.01)+H94 -> 1266440.5
A95: 7502 | B95: Obras para generación de energía
A96: 7503 | B96: Obras Hidrocarburíferas y Mineras
A97: 7504 | B97: Obras en líneas, redes, e intalaciones eléctricas y de telecomunicaciones | C97: =8469.95 -> 8469.95 | D97: =1337.63 -> 1337.63 | E97: =12892.63 -> 12892.63 | F97: =SUM(E97*0.02)+E97 -> 13150.483 | G97: =SUM(F97*0.02)+F97 -> 13413.492 | H97: =SUM(G97*0.01)+G97 -> 13547.627 | I97: =SUM(H97*0.01)+H97 -> 13683.103
A98: 7505 | B98: Mantenimiento y repaciones | C98: =8488.04+18848.34+39517.67 -> 66854.05 | D98: =154664.04+22694.94+27569.82 -> 204928.8 | E98: =7867.61+9284.56+35404.13 -> 52556.3 | F98: =SUM(E98*0.02)+E98 -> 53607.426 | G98: =SUM(F98*0.02)+F98 -> 54679.575 | H98: =SUM(G98*0.01)+G98 -> 55226.37 | I98: =SUM(H98*0.01)+H98 -> 55778.634
A99: 7599 | B99: Asignaciones a distribuir
A100: 77 | B100: Otros Gastos de Inversión
A101: 7702 | B101: Segusros, costos financieros y otros gastos | D101: =56113.87 -> 56113.87
A102: 78 | B102: Transferencias y donaciones para inversión
A103: 7801 | B103: Transferencias para inversión al sector público | C103: =221967.45 -> 221967.45 | D103: =321010.45 -> 321010.45 | E103: =787643.89 -> 787643.89 | F103: =SUM(E103*0.02)+E103 -> 803396.77 | G103: =SUM(F103*0.02)+F103 -> 819464.7 | H103: =SUM(G103*0.01)+G103 -> 827659.35 | I103: =SUM(H103*0.01)+H103 -> 835935.94
...

Sheet Hoja2
B1: 2014 | C1: 2015 | E1: 2016 | F1: 2017
A2: total mensual salarios | B2: 88370.42 | C2: 100514 | D2: 99098 | E2: 102230 | F2: 104318
A3: Decimo tercer sueldo | B3: 84911.16 | C3: 129936.74
C4: =2184.94+1964.14+112.82+1964.14+137.66+1827.03+131.47+1827.03+154.35+1827.03+196.11+1827.03+165.5 -> 14319.25
A6: Decimo cuarto | B6: 53380 | C6: =63248+3718.5 -> 66966.5
A11: Decimo Cuarto 2016 | B11: =174*366 -> 63684 | D11: se toma en cuenta 174 trabajadores por 366 que es el salario minimo unificado
A12: Decimo Cuarto 2017 | B12: =174*380 -> 66120 | D12: se toma en cuenta 174 trabajadores por 380 que es el salario minimo unificado
A15: Decimo Tercer 2016 | B15: ='FORMULARIO 3'!G185/12 -> 8519.1667
A16: Decimo Tercer 2017 | B16: ='FORMULARIO 3'!#REF!/12 -> #REF!
A19: Alimentacion 2014 | B19: =(((3*22)*12)*188) -> 148896 | D19: la alimentacion se considera 3 dola diarios por 22 dias del mes por 12 meses y por 188 trabajadores permanentes
A20: Alimentacion 2015 | B20: =(((3*22)*12)*176) -> 139392 | D20: la alimentacion se considera 3 dola diarios por 22 dias del mes por 12 meses y por 176 trabajadores permanentes
A23: Alimentacion 2016 | B23: =(((4*22)*12)*174) -> 183744 | D23: la alimentacion se considera 4 dola diarios por 22 dias del mes por 12 meses y por 174 trabajadores permanentes
A24: Alimentacion 2017 | B24: =(((4*22)*12)*174) -> 183744 | D24: la alimentacion se considera 4 dola diarios por 22 dias del mes por 12 meses y por 174 trabajadores permanentes
A26: transporte 2014 | B26: =(((0.5*22)*12)*188) -> 24816 | D26: la alimentacion se considera 0.5 dola diarios por 22 dias del mes por 12 meses y por 188 trabajadores permanentes
A27: transporte 2015 | B27: =(((0.5*22)*12)*176) -> 23232 | D27: la alimentacion se considera 0.5 dola diarios por 22 dias del mes por 12 meses y por 176 trabajadores permanentes
A29: transporte 2016 | B29: =(((0.5*22)*12)*174) -> 22968 | D29: la alimentacion se considera 0.5 dola diarios por 22 dias del mes por 12 meses y por 174 trabajadores permanentes
A30: transporte 2017 | B30: =(((0.5*22)*12)*174) -> 22968 | D30: la alimentacion se considera 0.5 dola diarios por 22 dias del mes por 12 meses y por 174 trabajadores permanentes
A33: subs. Familiar | B33: 102.66 | D33: solo de marzo a diciembre 2015 7.08 de marzo y 10.62 de abril a diciembre de 2015
